Workbook

Sheet Sheet
A1: Пожалуйста, введите свой ID, который вы получили после подписания соглашения на участие. | B1: Вы уехали из России после 24-го февраля 2022 года? / Did you leave Russia after February 24th 2022? | D1: В данный момент вы проживаете в Грузии или Армении?/ Are you currently residing in Georgia or Armenia? | F1: Вы свободно говорите по-русски? / Are you fluent in Russian? | H1: Ваш пол / Gender | K1: Возраста / Age | R1: Укажите вашу этническую принадлежнось / Which ethnicity best describes you? | T1: На каких языках вы разговариваете? / What languages do you speak? | U1: Из какого города/села вы эмигрировали (название, область)? / What place did you emigrate from? | V1: В каком городе/селе вы сейчас находитесь (название, страна)? Where are you residing now? | W1: Семейное положение / Which of the following best describes your current relationship status? | AD1: У вас есть дети моложе 18 лет? / Do you have any children under 18? | AF1: Если да, то сколько? / If yes, how many? | AG1: Есть ли у вас другие члены семьи на иждивении? / Do you have any other dependents who are currently living with you | AI1: Если да, то сколько? / If yes, how many? | AJ1: Уровень образования / Highest level of education: | AR1: Какой у вас уровень доходов? / What is your current income? | AU1: Почему вы решили уехать из России? / What were your reasons for leaving Russia? | AV1: Я не доверяю людям в этой стране. / I do not trust the people of this country. | AZ1: Я скучаю по атмосфере моего родного города (села). / I miss the atmosphere of my hometown. | BD1: Социум постоянно напоминает мне, что я иммигрант. / Society constantly reminds you that you are an immigrant. | BH1: Я чувствую себя одиноким. / I feel alone. | BL1: У меня слишком много обязанностей. / I have too many responsibilities. | BP1: Меня беспокоит, что я не смогу дать моим детям образование, которое будет соответствовать моей культуре. / It worries me that I cannot educate my children according to my culture. | BT1: Я чувствую, что я потерпел неудачу. / I feel that I have failed. | BX1: Я чувствую, что я не принадлежу к этому обществу. / I feel that I do not belong to this society. | CB1: Я боюсь, что я потерплю неудачу в этой стране. / I fear that I will fail in this country. | CF1: Я не чувствую себя здесь принятым. / I do not feel accepted here. | CJ1: Я чувствую себя очень плохо, когда я думаю о том, что я оставил в своей стране. / I feel very bad when I think about everything I left behind in my country. | CN1: Я переживаю за свое здоровье. / I am worried about my health. | CR1: У меня нет адекватного жилья. / I do not have adequate housing. | CV1: Я чувствую вину за то, что я оставил свою семью. / I feel guilty for having left my family. | CZ1: Я чувствую как будто я бросил свою семью. / I feel like I have abandoned my family. | DD1: Я скучаю по своей семье. / I miss my family. | DH1: Я часто чувствую себя напряженным. / I frequently feel tense. | DL1: Я не уверен, что я хочу здесь остаться. / I am not sure if I want to stay here. | DP1: У меня есть финансовые проблемы. / I have financial problems. | DT1: Мне очень сложно решить свои проблемы. / It is very difficult for me to solve my problems. | DX1: Я жалею, что я покинул свою страну. / I regret having left my country. | EB1: С тех пор как я сюда переехал, моя жизнь стала хуже. / Since I moved here my life has gotten worse. | EF1: Я переживаю, что я вовлек других людей в свое желание эмигрировать. / It worries me that I have involved other people in my decision to immigrate. | EJ1: Я чувствую, что моя культура недооценена. / I have felt that my culture is undervalued. | EN1: Я чувствую давление от жителей этой страны принять их стиль жизни. / I feel pressured by the people of this country to adopt their lifestyle. | ER1: В этой стране иммигранты не имеют возможности получить высокие должности. / In this country, immigrants do not have the opportunity to obtain higher ranking jobs. | EV1: Я переживаю, что я не смогу содержать свою семью. / I am worried that I cannot support my family. | EZ1: Я не чувствую себя хорошо в этой стране. / I don't feel good in this country. | FD1: Я чувствую дискриминацию, когда я пытаюсь найти жилье. / I feel discriminated against when it comes to finding housing. | FH1: Я очень волнуюсь за свою страну происхождения. / I worry a lot about my country of origin. | FL1: Я чувствую, что я никогда не смогу вернуться на родину. / I feel like I will never be able to come back to my homeland. | FP1: Отсутствие жилья / Lack of shelter | FR1: Отсутствие еды или воды / Lack of food or water | FT1: Плохое здоровье без доступа к медицинской помощи / Ill health without access to medical care | FV1: Конфискация имущества / Confiscation of personal property | FX1: Избиение / Beating to the body | FZ1: Изнасилование / Rape | GB1: Другие виды сексуального домогательства или унижения / Other types of sexual abuse or sexual humiliation | GD1: Арест / Imprisonment | GF1: Рэкет или ограбление / Extortion or robbery | GH1: Промывка мозгов / Brainwashing | GJ1: Разделение с членами семьи / Separation from family members | GL1: Предательство члена семьи или друга / Betrayal of family member, or friend | GN1: Присутствие при избиении другого человека / Witness beating to head or body | GP1: Присутствие при пытках / Witness torture | GR1: Присутствие при изнасиловании или сексуальных домогательствах / Witness rape or sexual abuse | GT1: Утопление / Near drowning | GV1: Голод / Starvation | GX1: Пожалуйста, перечислите другие ситуации, в которых вы сильно испугались или почувствовали, что вашей жизни угрожает опасность. / Please list any other situations not included above that were very frightening or in which you felt your life was in danger. | GY1: Насколько нижеприведенные симптомы вас беспокоили в течение последней недели? | IQ1: Насколько нижеприведенные симптомы беспокоили вас в течение последней недели? / How much have the following symptoms bothered you in the past week? | JS1: Насколько нижеприведенные симптомы беспокоили вас в течение последней недели? / How much have the following symptoms bothered you in the past week? | KU1: Внезапный страх без видимой причины / Suddenly scared for no reason | KY1: Чувство пугливости / Feeling fearful | LC1: Обморочность, головокуржение, слабость / Faintness, dizziness or weakness | LG1: Нервозность или внутренняя дрожь / Nervousness or shakiness inside | LK1: Сердебиение или учащение пульса / Heart pounding or racing | LO1: Тремор / Trembling | LS1: Напряжение, взвинченность / Feeling tense or keyed up | LW1: Головная боль / Headaches | MA1: Присуп ужаса, паники / Spell of terror or panic | ME1: Ощущение тревожности, не можете найти себе место / Feeling restless or can’t sit still | MI1: Ощущение вялости, заторможенности / Feeling low in energy, slowed down | MM1: Обвиняете себя за что-либо / Blaming yourself for things | MQ1: Легко начинаете плакать / Crying easily | MU1: Утрата сексуального влечения или удовольствия / Loss of sexual interest or pleasure | MY1: Плохой аппетит / Poor appetite | NC1: Сложности с засыпанием или со сном / Difficulty falling asleep, staying asleep | NG1: Чувство безнадежности в отношении будущего / Feeling hopeless about future | NK1: Подавленное настроение / Feeling blue | NO1: Чувство одиночества / Feeling lonely | NS1: Чувство, что вы в ловушке или пойманы / Feeling of being trapped or caught | NW1: Чрезмерное беспокойство по незначительным поводам / Worry too much about things | OA1: Отсутствие интереса к чему-либо / Feeling no interest in things | OE1: Ощущение, что все дается с трудом / Feeling everything is an effort | OI1: Ощущение своей никчемности / Feeling of worthlessness
A2: Open-Ended Response | B2: Да / Yes | C2: Нет / No | D2: Да / Yes | E2: Нет / No | F2: Да / Yes | G2: Нет / No | H2: Женский / Female | I2: Мужской / Male | J2: Небинарный / Non-binary | K2: Моложе 18 | L2: 18-24 | M2: 25-34 | N2: 35-44 | O2: 45-54 | P2: 55-64 | Q2: 65+ | R2: Русский(ая) / Russian | S2: Другая этническая принадлежность (уточните) / Other (please specify) | T2: Open-Ended Response | U2: Open-Ended Response | V2: Open-Ended Response | W2: Женат (замужем) / Married | X2: Вдовец (вдова) / Widowed | Y2: В разводе / Divorced | Z2: Раздельное проживание / Separated | AA2: Гражданский брак / Cohabiting with a significant other or in a domestic partnership | AB2: Никогда не был женат (замужем) / Single, never married | AC2: Предпочитаю не отвечать / Prefer not to answer | AD2: Да / Yes | AE2: Нет / No | AF2: Open-Ended Response | AG2: Да / Yes | AH2: Нет / No | AI2: Open-Ended Response | AJ2: Незаконченное среднее образование / Less than high school graduate | AK2: Среднее образование / High school graduate | AL2: Незаконченное высшее / Some college | AM2: Высшее образование (бакалавриат) / Bachelor’s Degree | AN2: Высшее образование (специалист) / 5 years of college | AO2: Магистратура / Master’s Degree | AP2: Кандидат наук / Doctoral Degree | AQ2: Профессиональное образование / Professional Degree | AR2: Ниже среднего / Below average | AS2: Средний / Average | AT2: Выше среднего / Above average | AU2: Open-Ended Response | AV2: Полностью согласен / Strongly agree | AW2: Скорее согласен / Moderately agree | AX2: Скорее не согласен / Moderately disagree | AY2: Полностью не согласен / Strongly disagree | AZ2: Полностью согласен / Strongly agree | BA2: Скорее согласен / Moderately agree | BB2: Скорее не согласен / Moderately disagree | BC2: Полностью не согласен / Strongly disagree | BD2: Полностью согласен / Strongly agree | BE2: Скорее согласен / Moderately agree | BF2: Скорее не согласен / Moderately disagree | BG2: Полностью не согласен / Strongly disagree | BH2: Полностью согласен / Strongly agree | BI2: Скорее согласен / Moderately agree | BJ2: Скорее не согласен / Moderately disagree | BK2: Полностью не согласен / Strongly disagree | BL2: Полностью согласен / Strongly agree | BM2: Скорее согласен / Moderately agree | BN2: Скорее не согласен / Moderately disagree | BO2: Полностью не согласен / Strongly disagree | BP2: Полностью согласен / Strongly agree | BQ2: Скорее согласен / Moderately agree | BR2: Скорее не согласен / Moderately disagree | BS2: Полностью не согласен / Strongly disagree | BT2: Полностью согласен / Strongly agree | BU2: Скорее согласен / Moderately agree | BV2: Скорее не согласен / Moderately disagree | BW2: Полностью не согласен / Strongly disagree | BX2: Полностью согласен / Strongly agree | BY2: Скорее согласен / Moderately agree | BZ2: Скорее не согласен / Moderately disagree | CA2: Полностью не согласен / Strongly disagree | CB2: Полностью согласен / Strongly agree | CC2: Скорее согласен / Moderately agree | CD2: Скорее не согласен / Moderately disagree | CE2: Полностью не согласен / Strongly disagree | CF2: Полностью согласен / Strongly agree | CG2: Скорее согласен / Moderately agree | CH2: Скорее не согласен / Moderately disagree | CI2: Полностью не согласен / Strongly disagree | CJ2: Полностью согласен / Strongly agree | CK2: Скорее согласен / Moderately agree | CL2: Скорее не согласен / Moderately disagree | CM2: Полностью не согласен / Strongly disagree | CN2: Полностью согласен / Strongly agree | CO2: Скорее согласен / Moderately agree | CP2: Скорее не согласен / Moderately disagree | CQ2: Полностью не согласен / Strongly disagree | CR2: Полностью согласен / Strongly agree | CS2: Скорее согласен / Moderately agree | CT2: Скорее не согласен / Moderately disagree | CU2: Полностью не согласен / Strongly disagree | CV2: Полностью согласен / Strongly agree | CW2: Скорее согласен / Moderately agree | CX2: Скорее не согласен / Moderately disagree | CY2: Полностью не согласен / Strongly disagree | CZ2: Полностью согласен / Strongly agree | DA2: Скорее согласен / Moderately agree | DB2: Скорее не согласен / Moderately disagree | DC2: Полностью не согласен / Strongly disagree | DD2: Полностью согласен / Strongly agree | DE2: Скорее согласен / Moderately agree | DF2: Скорее не согласен / Moderately disagree | DG2: Полностью не согласен / Strongly disagree | DH2: Полностью согласен / Strongly agree | DI2: Скорее согласен / Moderately agree | DJ2: Скорее не согласен / Moderately disagree | DK2: Полностью не согласен / Strongly disagree | DL2: Полностью согласен / Strongly agree | DM2: Скорее согласен / Moderately agree | DN2: Скорее не согласен / Moderately disagree | DO2: Полностью не согласен / Strongly disagree | DP2: Полностью согласен / Strongly agree | DQ2: Скорее согласен / Moderately agree | DR2: Скорее не согласен / Moderately disagree | DS2: Полностью не согласен / Strongly disagree | DT2: Полностью согласен / Strongly agree | DU2: Скорее согласен / Moderately agree | DV2: Скорее не согласен / Moderately disagree | DW2: Полностью не согласен / Strongly disagree | DX2: Полностью согласен / Strongly agree | DY2: Скорее согласен / Moderately agree | DZ2: Скорее не согласен / Moderately disagree | EA2: Полностью не согласен / Strongly disagree | EB2: Полностью согласен / Strongly agree | EC2: Скорее согласен / Moderately agree | ED2: Скорее не согласен / Moderately disagree | EE2: Полностью не согласен / Strongly disagree | EF2: Полностью согласен / Strongly agree | EG2: Скорее согласен / Moderately agree | EH2: Скорее не согласен / Moderately disagree | EI2: Полностью не согласен / Strongly disagree | EJ2: Полностью согласен / Strongly agree | EK2: Скорее согласен / Moderately agree | EL2: Скорее не согласен / Moderately disagree | EM2: Полностью не согласен / Strongly disagree | EN2: Полностью согласен / Strongly agree | EO2: Скорее согласен / Moderately agree | EP2: Скорее не согласен / Moderately disagree | EQ2: Полностью не согласен / Strongly disagree | ER2: Полностью согласен / Strongly agree | ES2: Скорее согласен / Moderately agree | ET2: Скорее не согласен / Moderately disagree | EU2: Полностью не согласен / Strongly disagree | EV2: Полностью согласен / Strongly agree | EW2: Скорее согласен / Moderately agree | EX2: Скорее не согласен / Moderately disagree | EY2: Полностью не согласен / Strongly disagree | EZ2: Полностью согласен / Strongly agree | FA2: Скорее согласен / Moderately agree | FB2: Скорее не согласен / Moderately disagree | FC2: Полностью не согласен / Strongly disagree | FD2: Полностью согласен / Strongly agree | FE2: Скорее согласен / Moderately agree | FF2: Скорее не согласен / Moderately disagree | FG2: Полностью не согласен / Strongly disagree | FH2: Полностью согласен / Strongly agree | FI2: Скорее согласен / Moderately agree | FJ2: Скорее не согласен / Moderately disagree | FK2: Полностью не согласен / Strongly disagree | FL2: Полностью согласен / Strongly agree | FM2: Скорее согласен / Moderately agree | FN2: Скорее не согласен / Moderately disagree | FO2: Полностью не согласен / Strongly disagree | FP2: Да / Yes | FQ2: Нет / No | FR2: Да / Yes | FS2: Нет / No | FT2: Да / Yes | FU2: Нет / No | FV2: Да / Yes | FW2: Нет / No | FX2: Да / Yes | FY2: Нет / No | FZ2: Да / Yes | GA2: Нет / No | GB2: Да / Yes | GC2: Нет / No | GD2: Да / Yes | GE2: Нет / No | GF2: Да / Yes | GG2: Нет / No | GH2: Да / Yes | GI2: Нет / No | GJ2: Да / Yes | GK2: Нет / No | GL2: Да / Yes | GM2: Нет / No | GN2: Да / Yes | GO2: Нет / No | GP2: Да / Yes | GQ2: Нет / No | GR2: Да / Yes | GS2: Нет / No | GT2: Да / Yes | GU2: Нет / No | GV2: Да / Yes | GW2: Нет / No | GX2: Open-Ended Response | GY2: Навязчивые мысли и воспоминания о наиболее болезненных или пугающих событиях / Recurrent thoughts or memories of the most hurtful or terrifying events - Совсем нет/Not at all | GZ2: Навязчивые мысли и воспоминания о наиболее болезненных или пугающих событиях / Recurrent thoughts or memories of the most hurtful or terrifying events - Немного/A little | HA2: Навязчивые мысли и воспоминания о наиболее болезненных или пугающих событиях / Recurrent thoughts or memories of the most hurtful or terrifying events - Довольно сильно/Quite a bit | HB2: Навязчивые мысли и воспоминания о наиболее болезненных или пугающих событиях / Recurrent thoughts or memories of the most hurtful or terrifying events - Очень сильно/Extremely | HC2: Ощущение, что это событие повторяется вновь / Feeling as though the event is happening again - Совсем нет/Not at all | HD2: Ощущение, что это событие повторяется вновь / Feeling as though the event is happening again - Немного/A little | HE2: Ощущение, что это событие повторяется вновь / Feeling as though the event is happening again - Довольно сильно/Quite a bit | HF2: Ощущение, что это событие повторяется вновь / Feeling as though the event is happening again - Очень сильно/Extremely | HG2: Повторяющиеся ночные кошмары / Recurrent nightmares - Совсем нет/Not at all | HH2: Повторяющиеся ночные кошмары / Recurrent nightmares - Немного/A little | HI2: Повторяющиеся ночные кошмары / Recurrent nightmares - Довольно сильно/Quite a bit | HJ2: Повторяющиеся ночные кошмары / Recurrent nightmares - Очень сильно/Extremely | HK2: Ощущение отовранности или отчужденности от людей / Feeling detached or withdrawn from people - Совсем нет/Not at all | HL2: Ощущение отовранности или отчужденности от людей / Feeling detached or withdrawn from people - Немного/A little | HM2: Ощущение отовранности или отчужденности от людей / Feeling detached or withdrawn from people - Довольно сильно/Quite a bit | HN2: Ощущение отовранности или отчужденности от людей / Feeling detached or withdrawn from people - Очень сильно/Extremely | HO2: Неспособность испытывать эмоции / Unable to feel emotions - Совсем нет/Not at all | HP2: Неспособность испытывать эмоции / Unable to feel emotions - Немного/A little | HQ2: Неспособность испытывать эмоции / Unable to feel emotions - Довольно сильно/Quite a bit | HR2: Неспособность испытывать эмоции / Unable to feel emotions - Очень сильно/Extremely | HS2: Нервозность, вздрагивание / Feeling jumpy, easily startled - Совсем нет/Not at all | HT2: Нервозность, вздрагивание / Feeling jumpy, easily startled - Немного/A little | HU2: Нервозность, вздрагивание / Feeling jumpy, easily startled - Довольно сильно/Quite a bit | HV2: Нервозность, вздрагивание / Feeling jumpy, easily startled - Очень сильно/Extremely | HW2: Трудности с концентрацией внимания / Difficulty concentrating - Совсем нет/Not at all | HX2: Трудности с концентрацией внимания / Difficulty concentrating - Немного/A little | HY2: Трудности с концентрацией внимания / Difficulty concentrating - Довольно сильно/Quite a bit | HZ2: Трудности с концентрацией внимания / Difficulty concentrating - Очень сильно/Extremely | IA2: Проблемы со сном / Trouble sleeping - Совсем нет/Not at all | IB2: Проблемы со сном / Trouble sleeping - Немного/A little | IC2: Проблемы со сном / Trouble sleeping - Довольно сильно/Quite a bit | ID2: Проблемы со сном / Trouble sleeping - Очень сильно/Extremely | IE2: Постоянно настороже / Feeling on guard - Совсем нет/Not at all | IF2: Постоянно настороже / Feeling on guard - Немного/A little | IG2: Постоянно настороже / Feeling on guard - Довольно сильно/Quite a bit | IH2: Постоянно настороже / Feeling on guard - Очень сильно/Extremely | II2: Легко раздражаетесь, испытываете вспышки гнева / Feeling irritable or having outbursts of anger - Совсем нет/Not at all | IJ2: Легко раздражаетесь, испытываете вспышки гнева / Feeling irritable or having outbursts of anger - Немного/A little | IK2: Легко раздражаетесь, испытываете вспышки гнева / Feeling irritable or having outbursts of anger - Довольно сильно/Quite a bit | IL2: Легко раздражаетесь, испытываете вспышки гнева / Feeling irritable or having outbursts of anger - Очень сильно/Extremely | IM2: Избегания действий, которые напоминают вам о траматическом или болезненном событии. / Avoiding activities that remind you of the traumatic or hurtful event - Совсем нет/Not at all | IN2: Избегания действий, которые напоминают вам о траматическом или болезненном событии. / Avoiding activities that remind you of the traumatic or hurtful event - Немного/A little | IO2: Избегания действий, которые напоминают вам о траматическом или болезненном событии. / Avoiding activities that remind you of the traumatic or hurtful event - Довольно сильно/Quite a bit | IP2: Избегания действий, которые напоминают вам о траматическом или болезненном событии. / Avoiding activities that remind you of the traumatic or hurtful event - Очень сильно/Extremely | IQ2: Невозможность вспомнить фрагменты наиболее болезненных или травматичных событий / Inability to remember parts of the most hurtful or traumatic events - Совсем нет/Not at all | IR2: Невозможность вспомнить фрагменты наиболее болезненных или травматичных событий / Inability to remember parts of the most hurtful or traumatic events - Немного/A little | IS2: Невозможность вспомнить фрагменты наиболее болезненных или травматичных событий / Inability to remember parts of the most hurtful or traumatic events - Довольно сильно/Quite a bit | IT2: Невозможность вспомнить фрагменты наиболее болезненных или травматичных событий / Inability to remember parts of the most hurtful or traumatic events - Очень сильно/Extremely | IU2: Пониженный интерес к повседневной деятельности / Less interest in daily activities - Совсем нет/Not at all | IV2: Пониженный интерес к повседневной деятельности / Less interest in daily activities - Немного/A little | IW2: Пониженный интерес к повседневной деятельности / Less interest in daily activities - Довольно сильно/Quite a bit | IX2: Пониженный интерес к повседневной деятельности / Less interest in daily activities - Очень сильно/Extremely | IY2: Чувство, что у вас нет будущего / Feeling as if you don’t have a future - Совсем нет/Not at all | IZ2: Чувство, что у вас нет будущего / Feeling as if you don’t have a future - Немного/A little | JA2: Чувство, что у вас нет будущего / Feeling as if you don’t have a future - Довольно сильно/Quite a bit | JB2: Чувство, что у вас нет будущего / Feeling as if you don’t have a future - Очень сильно/Extremely | JC2: Избегание мыслей и чувств, которые ассоциируются с траматичными или болезненными собиытиями / Avoiding thoughts or feelings associated with the traumatic or hurtful events - Совсем нет/Not at all | JD2: Избегание мыслей и чувств, которые ассоциируются с траматичными или болезненными собиытиями / Avoiding thoughts or feelings associated with the traumatic or hurtful events - Немного/A little | JE2: Избегание мыслей и чувств, которые ассоциируются с траматичными или болезненными собиытиями / Avoiding thoughts or feelings associated with the traumatic or hurtful events - Довольно сильно/Quite a bit | JF2: Избегание мыслей и чувств, которые ассоциируются с траматичными или болезненными собиытиями / Avoiding thoughts or feelings associated with the traumatic or hurtful events - Очень сильно/Extremely | JG2: Внезапная эмоциональная или физическая реакция при напоминании об особенно болезненном или травматичном событии / Sudden emotional or physical reaction when reminded of the most hurtful or traumatic events - Совсем нет/Not at all | JH2: Внезапная эмоциональная или физическая реакция при напоминании об особенно болезненном или травматичном событии / Sudden emotional or physical reaction when reminded of the most hurtful or traumatic events - Немного/A little | JI2: Внезапная эмоциональная или физическая реакция при напоминании об особенно болезненном или травматичном событии / Sudden emotional or physical reaction when reminded of the most hurtful or traumatic events - Довольно сильно/Quite a bit | JJ2: Внезапная эмоциональная или физическая реакция при напоминании об особенно болезненном или травматичном событии / Sudden emotional or physical reaction when reminded of the most hurtful or traumatic events - Очень сильно/Extremely | JK2: Ощущение, что мир очень опасен / Feeling that the world is a very dangerous place - Совсем нет/Not at all | JL2: Ощущение, что мир очень опасен / Feeling that the world is a very dangerous place - Немного/A little | JM2: Ощущение, что мир очень опасен / Feeling that the world is a very dangerous place - Довольно сильно/Quite a bit | JN2: Ощущение, что мир очень опасен / Feeling that the world is a very dangerous place - Очень сильно/Extremely | JO2: Ощущение, что вы плохой человек / Feeling that you are a bad person - Совсем нет/Not at all | JP2: Ощущение, что вы плохой человек / Feeling that you are a bad person - Немного/A little | JQ2: Ощущение, что вы плохой человек / Feeling that you are a bad person - Довольно сильно/Quite a bit | JR2: Ощущение, что вы плохой человек / Feeling that you are a bad person - Очень сильно/Extremely | JS2: Обвинение себя в том, что произошло / Blaming yourself for the traumatic event - Совсем нет/Not at all | JT2: Обвинение себя в том, что произошло / Blaming yourself for the traumatic event - Немного/A little | JU2: Обвинение себя в том, что произошло / Blaming yourself for the traumatic event - Довольно сильно/Quite a bit | JV2: Обвинение себя в том, что произошло / Blaming yourself for the traumatic event - Очень сильно/Extremely | JW2: Сильное чувство страха, ужаса, злости, вины или стыда, когда думаете о травматическом событии / Strong feeling of fear, horror, anger, guilt or shame when thinking about the traumatic event - Совсем нет/Not at all | JX2: Сильное чувство страха, ужаса, злости, вины или стыда, когда думаете о травматическом событии / Strong feeling of fear, horror, anger, guilt or shame when thinking about the traumatic event - Немного/A little | JY2: Сильное чувство страха, ужаса, злости, вины или стыда, когда думаете о травматическом событии / Strong feeling of fear, horror, anger, guilt or shame when thinking about the traumatic event - Довольно сильно/Quite a bit | JZ2: Сильное чувство страха, ужаса, злости, вины или стыда, когда думаете о травматическом событии / Strong feeling of fear, horror, anger, guilt or shame when thinking about the traumatic event - Очень сильно/Extremely | KA2: Сложности с чувствами любви и счастья / Difficulty feeling love or happiness - Совсем нет/Not at all | KB2: Сложности с чувствами любви и счастья / Difficulty feeling love or happiness - Немного/A little | KC2: Сложности с чувствами любви и счастья / Difficulty feeling love or happiness - Довольно сильно/Quite a bit | KD2: Сложности с чувствами любви и счастья / Difficulty feeling love or happiness - Очень сильно/Extremely | KE2: Совершение рискованных поступков, которые могут повредить вам или окружающим / Taking risks that may harm yourself or others - Совсем нет/Not at all | KF2: Совершение рискованных поступков, которые могут повредить вам или окружающим / Taking risks that may harm yourself or others - Немного/A little | KG2: Совершение рискованных поступков, которые могут повредить вам или окружающим / Taking risks that may harm yourself or others - Довольно сильно/Quite a bit | KH2: Совершение рискованных поступков, которые могут повредить вам или окружающим / Taking risks that may harm yourself or others - Очень сильно/Extremely | KI2: Ощущение, что травматическое событие повредило вас как личность / Feeling like you have been damaged as a person by the traumatic event - Совсем нет/Not at all | KJ2: Ощущение, что травматическое событие повредило вас как личность / Feeling like you have been damaged as a person by the traumatic event - Немного/A little | KK2: Ощущение, что травматическое событие повредило вас как личность / Feeling like you have been damaged as a person by the traumatic event - Довольно сильно/Quite a bit | KL2: Ощущение, что травматическое событие повредило вас как личность / Feeling like you have been damaged as a person by the traumatic event - Очень сильно/Extremely | KM2: Ощущение, будто если что-то напоминает вам о травматическом событии, это похоже на сон, что это не случилось с вами и/или это не произошло в реальности / Feeling as if something reminds you of the trauma but it feels like a dream, that it is not happening to you, and/or that it is not real - Совсем нет/Not at all | KN2: Ощущение, будто если что-то напоминает вам о травматическом событии, это похоже на сон, что это не случилось с вами и/или это не произошло в реальности / Feeling as if something reminds you of the trauma but it feels like a dream, that it is not happening to you, and/or that it is not real - Немного/A little | KO2: Ощущение, будто если что-то напоминает вам о травматическом событии, это похоже на сон, что это не случилось с вами и/или это не произошло в реальности / Feeling as if something reminds you of the trauma but it feels like a dream, that it is not happening to you, and/or that it is not real - Довольно сильно/Quite a bit | KP2: Ощущение, будто если что-то напоминает вам о травматическом событии, это похоже на сон, что это не случилось с вами и/или это не произошло в реальности / Feeling as if something reminds you of the trauma but it feels like a dream, that it is not happening to you, and/or that it is not real - Очень сильно/Extremely | KQ2: Ощущение, что люди и предметы вокруг вас не настоящие или не знакомые / Feeling people or objects around you are not real or strange - Совсем нет/Not at all | KR2: Ощущение, что люди и предметы вокруг вас не настоящие или не знакомые / Feeling people or objects around you are not real or strange - Немного/A little | KS2: Ощущение, что люди и предметы вокруг вас не настоящие или не знакомые / Feeling people or objects around you are not real or strange - Довольно сильно/Quite a bit | KT2: Ощущение, что люди и предметы вокруг вас не настоящие или не знакомые / Feeling people or objects around you are not real or strange - Очень сильно/Extremely | KU2: Совсем нет / Not at all | KV2: Немного / A little | KW2: Довольно сильно / Quite a bit | KX2: Очень сильно / Extremely | KY2: Совсем нет / Not at all | KZ2: Немного / A little | LA2: Довольно сильно / Quite a bit | LB2: Очень сильно / Extremely | LC2: Совсем нет / Not at all | LD2: Немного / A little | LE2: Довольно сильно / Quite a bit | LF2: Очень сильно / Extremely | LG2: Совсем нет / Not at all | LH2: Немного / A little | LI2: Довольно сильно / Quite a bit | LJ2: Очень сильно / Extremely | LK2: Совсем нет / Not at all | LL2: Немного / A little | LM2: Довольно сильно / Quite a bit | LN2: Очень сильно / Extremely | LO2: Совсем нет / Not at all | LP2: Немного / A little | LQ2: Довольно сильно / Quite a bit | LR2: Очень сильно / Extremely | LS2: Совсем нет / Not at all | LT2: Немного / A little | LU2: Довольно сильно / Quite a bit | LV2: Очень сильно / Extremely | LW2: Совсем нет / Not at all | LX2: Немного / A little | LY2: Довольно сильно / Quite a bit | LZ2: Очень сильно / Extremely | MA2: Совсем нет / Not at all | MB2: Немного / A little | MC2: Довольно сильно / Quite a bit | MD2: Очень сильно / Extremely | ME2: Совсем нет / Not at all | MF2: Немного / A little | MG2: Довольно сильно / Quite a bit | MH2: Очень сильно / Extremely | MI2: Совсем нет / Not at all | MJ2: Немного / A little | MK2: Довольно сильно / Quite a bit | ML2: Очень сильно / Extremely | MM2: Совсем нет / Not at all | MN2: Немного / A little | MO2: Довольно сильно / Quite a bit | MP2: Очень сильно / Extremely | MQ2: Совсем нет / Not at all | MR2: Немного / A little | MS2: Довольно сильно / Quite a bit | MT2: Очень сильно / Extremely | MU2: Совсем нет / Not at all | MV2: Немного / A little | MW2: Довольно сильно / Quite a bit | MX2: Очень сильно / Extremely | MY2: Совсем нет / Not at all | MZ2: Немного / A little | NA2: Довольно сильно / Quite a bit | NB2: Очень сильно / Extremely | NC2: Совсем нет / Not at all | ND2: Немного / A little | NE2: Довольно сильно / Quite a bit | NF2: Очень сильно / Extremely | NG2: Совсем нет / Not at all | NH2: Немного / A little | NI2: Довольно сильно / Quite a bit | NJ2: Очень сильно / Extremely | NK2: Совсем нет / Not at all | NL2: Немного / A little | NM2: Довольно сильно / Quite a bit | NN2: Очень сильно / Extremely | NO2: Совсем нет / Not at all | NP2: Немного / A little | NQ2: Довольно сильно / Quite a bit | NR2: Очень сильно / Extremely | NS2: Совсем нет / Not at all | NT2: Немного / A little | NU2: Довольно сильно / Quite a bit | NV2: Очень сильно / Extremely | NW2: Совсем нет / Not at all | NX2: Немного / A little | NY2: Довольно сильно / Quite a bit | NZ2: Очень сильно / Extremely | OA2: Совсем нет / Not at all | OB2: Немного / A little | OC2: Довольно сильно / Quite a bit | OD2: Очень сильно / Extremely | OE2: Совсем нет / Not at all | OF2: Немного / A little | OG2: Довольно сильно / Quite a bit | OH2: Очень сильно / Extremely | OI2: Совсем нет / Not at all | OJ2: Немного / A little | OK2: Довольно сильно / Quite a bit | OL2: Очень сильно / Extremely
A3: SC001 | B3: Да / Yes | D3: Да / Yes | F3: Да / Yes | I3: Мужской / Male | M3: 25-34 | S3: Беларус | T3: Русский, Английский | U3: Санкт-Петербург | V3: Тбилиси | AB3: Никогда не был женат (замужем) / Single, never married | AE3: Нет / No | AF3: 0 | AH3: Нет / No | AI3: 0 | AL3: Незаконченное высшее / Some college | AT3: Выше среднего / Above average | AU3: It's more exciting to join the common panic party, rather than staying home | AX3: Скорее не согласен / Moderately disagree | BA3: Скорее согласен / Moderately agree | BD3: Полностью согласен / Strongly agree | BK3: Полностью не согласен / Strongly disagree | BO3: Полностью не согласен / Strongly disagree | BS3: Полностью не согласен / Strongly disagree | BW3: Полностью не согласен / Strongly disagree | BX3: Полностью согласен / Strongly agree | CE3: Полностью не согласен / Strongly disagree | CF3: Полностью согласен / Strongly agree | CL3: Скорее не согласен / Moderately disagree | CQ3: Полностью не согласен / Strongly disagree | CU3: Полностью не согласен / Strongly disagree | CY3: Полностью не согласен / Strongly disagree | DC3: Полностью не согласен / Strongly disagree | DG3: Полностью не согласен / Strongly disagree | DK3: Полностью не согласен / Strongly disagree | DL3: Полностью согласен / Strongly agree | DS3: Полностью не согласен / Strongly disagree | DW3: Полностью не согласен / Strongly disagree | EA3: Полностью не согласен / Strongly disagree | EE3: Полностью не согласен / Strongly disagree | EI3: Полностью не согласен / Strongly disagree | EM3: Полностью не согласен / Strongly disagree | EO3: Скорее согласен / Moderately agree | ET3: Скорее не согласен / Moderately disagree | EY3: Полностью не согласен / Strongly disagree | FA3: Скорее согласен / Moderately agree | FF3: Скорее не согласен / Moderately disagree | FK3: Полностью не согласен / Strongly disagree | FN3: Скорее не согласен / Moderately disagree | FQ3: Нет / No | FS3: Нет / No | FU3: Нет / No | FW3: Нет / No | FY3: Нет / No | GA3: Нет / No | GC3: Нет / No | GE3: Нет / No | GG3: Нет / No | GI3: Нет / No | GK3: Нет / No | GM3: Нет / No | GO3: Нет / No | GQ3: Нет / No | GS3: Нет / No | GU3: Нет / No | GW3: Нет / No | GX3: Нарушение медицинской этики, введение в наркоз против моей воли, проведение операции против моей воли | HB3: Очень сильно/Extremely | HC3: Совсем нет/Not at all | HG3: Совсем нет/Not at all | HK3: Совсем нет/Not at all | HO3: Совсем нет/Not at all | HU3: Довольно сильно/Quite a bit | HW3: Совсем нет/Not at all | IA3: Совсем нет/Not at all | IE3: Совсем нет/Not at all | IK3: Довольно сильно/Quite a bit | IP3: Очень сильно/Extremely | IQ3: Совсем нет/Not at all | IV3: Немного/A little | IY3: Совсем нет/Not at all | JC3: Совсем нет/Not at all | JI3: Довольно сильно/Quite a bit | JL3: Немного/A little | JO3: Совсем нет/Not at all | JS3: Совсем нет/Not at all | JY3: Довольно сильно/Quite a bit | KA3: Совсем нет/Not at all | KF3: Немного/A little | KJ3: Немного/A little | KM3: Совсем нет/Not at all | KQ3: Совсем нет/Not at all | KU3: Совсем нет / Not at all | KY3: Совсем нет / Not at all | LC3: Совсем нет / Not at all | LG3: Совсем нет / Not at all | LK3: Совсем нет / Not at all | LO3: Совсем нет / Not at all | LS3: Совсем нет / Not at all | LW3: Совсем нет / Not at all | MA3: Совсем нет / Not at all | ME3: Совсем нет / Not at all | MI3: Совсем нет / Not at all | MM3: Совсем нет / Not at all | MQ3: Совсем нет / Not at all | MV3: Немного / A little | MZ3: Немного / A little | NC3: Совсем нет / Not at all | NG3: Совсем нет / Not at all | NK3: Совсем нет / Not at all | NO3: Совсем нет / Not at all | NS3: Совсем нет / Not at all | NX3: Немного / A little | OA3: Совсем нет / Not at all | OE3: Совсем нет / Not at all | OJ3: Немного / A little
A4: CF002 | B4: Да / Yes | D4: Да / Yes | F4: Да / Yes | H4: Женский / Female | N4: 35-44 | S4: еврейка | T4: русский, английский, немного иврит, немного немецкий | U4: Москва | V4: Армения, Ереван | W4: Женат (замужем) / Married | AD4: Да / Yes | AF4: 1 | AH4: Нет / No | AI4: - | AL4: Незаконченное высшее / Some college | AR4: Ниже среднего / Below average | AU4: Из-за того, что Россия ведёт захватническую войну | AX4: Скорее не согласен / Moderately disagree | BA4: Скорее согласен / Moderately agree | BG4: Полностью не согласен / Strongly disagree | BK4: Полностью не согласен / Strongly disagree | BN4: Скорее не согласен / Moderately disagree | BS4: Полностью не согласен / Strongly disagree | BV4: Скорее не согласен / Moderately disagree | BY4: Скорее согласен / Moderately agree | CD4: Скорее не согласен / Moderately disagree | CI4: Полностью не согласен / Strongly disagree | CL4: Скорее не согласен / Moderately disagree | CO4: Скорее согласен / Moderately agree | CS4: Скорее согласен / Moderately agree | CX4: Скорее не согласен / Moderately disagree | DB4: Скорее не согласен / Moderately disagree | DE4: Скорее согласен / Moderately agree | DH4: Полностью согласен / Strongly agree | DL4: Полностью согласен / Strongly agree | DQ4: Скорее согласен / Moderately agree | DU4: Скорее согласен / Moderately agree | EA4: Полностью не согласен / Strongly disagree | EC4: Скорее согласен / Moderately agree | EI4: Полностью не согласен / Strongly disagree | EL4: Скорее не согласен / Moderately disagree | EQ4: Полностью не согласен / Strongly disagree | ET4: Скорее не согласен / Moderately disagree | EW4: Скорее согласен / Moderately agree | FB4: Скорее не согласен / Moderately disagree | FF4: Скорее не согласен / Moderately disagree | FH4: Полностью согласен / Strongly agree | FN4: Скорее не согласен / Moderately disagree | FQ4: Нет / No | FS4: Нет / No | FU4: Нет / No | FW4: Нет / No | FY4: Нет / No | GA4: Нет / No | GB4: Да / Yes | GD4: Да / Yes | GF4: Да / Yes | GI4: Нет / No | GJ4: Да / Yes | GL4: Да / Yes | GN4: Да / Yes | GQ4: Нет / No | GS4: Нет / No | GU4: Нет / No | GW4: Нет / No | GZ4: Немного/A little | HC4: Совсем нет/Not at all | HG4: Совсем нет/Not at all | HK4: Совсем нет/Not at all | HO4: Совсем нет/Not at all | HT4: Немного/A little | HW4: Совсем нет/Not at all | IC4: Довольно сильно/Quite a bit | IE4: Совсем нет/Not at all | II4: Совсем нет/Not at all | IM4: Совсем нет/Not at all | IQ4: Совсем нет/Not at all | IW4: Довольно сильно/Quite a bit | IY4: Совсем нет/Not at all | JD4: Немного/A little | JG4: Совсем нет/Not at all | JL4: Немного/A little | JR4: Очень сильно/Extremely | JT4: Немного/A little | JY4: Довольно сильно/Quite a bit | KB4: Немного/A little | KE4: Совсем нет/Not at all | KK4: Довольно сильно/Quite a bit | KM4: Совсем нет/Not at all | KQ4: Совсем нет/Not at all | KU4: Совсем нет / Not at all | KY4: Совсем нет / Not at all | LD4: Немного / A little | LG4: Совсем нет / Not at all | LK4: Совсем нет / Not at all | LO4: Совсем нет / Not at all | LT4: Немного / A little | LW4: Совсем нет / Not at all | MA4: Совсем нет / Not at all | MF4: Немного / A little | MK4: Довольно сильно / Quite a bit | MO4: Довольно сильно / Quite a bit | MQ4: Совсем нет / Not at all | MW4: Довольно сильно / Quite a bit | MY4: Совсем нет / Not at all | NE4: Довольно сильно / Quite a bit | NG4: Совсем нет / Not at all | NM4: Довольно сильно / Quite a bit | NO4: Совсем нет / Not at all | NS4: Совсем нет / Not at all | NW4: Совсем нет / Not at all | OA4: Совсем нет / Not at all | OH4: Очень сильно / Extremely | OL4: Очень сильно / Extremely
A5: CT001 | B5: Да / Yes | D5: Да / Yes | F5: Да / Yes | I5: Мужской / Male | M5: 25-34 | R5: Русский(ая) / Russian | T5: Русский, английский (не очень хорошо знаю) | U5: Красноармейск, Московская область | V5: Тбилиси, Грузия | AB5: Никогда не был женат (замужем) / Single, never married | AE5: Нет / No | AF5: Нет | AH5: Нет / No | AI5: Нет | AL5: Незаконченное высшее / Some college | AR5: Ниже среднего / Below average | AU5: Риск политического преследования и мобилизации | AY5: Полностью не согласен / Strongly disagree | BB5: Скорее не согласен / Moderately disagree | BF5: Скорее не согласен / Moderately disagree | BJ5: Скорее не согласен / Moderately disagree | BN5: Скорее не согласен / Moderately disagree | BS5: Полностью не согласен / Strongly disagree | BV5: Скорее не согласен / Moderately disagree | CA5: Полностью не согласен / Strongly disagree | CD5: Скорее не согласен / Moderately disagree | CH5: Скорее не согласен / Moderately disagree | CM5: Полностью не согласен / Strongly disagree | CQ5: Полностью не согласен / Strongly disagree | CT5: Скорее не согласен / Moderately disagree | CX5: Скорее не согласен / Moderately disagree | DB5: Скорее не согласен / Moderately disagree | DG5: Полностью не согласен / Strongly disagree | DK5: Полностью не согласен / Strongly disagree | DN5: Скорее не согласен / Moderately disagree | DP5: Полностью согласен / Strongly agree | DT5: Полностью согласен / Strongly agree | EA5: Полностью не согласен / Strongly disagree | ED5: Скорее не согласен / Moderately disagree | EH5: Скорее не согласен / Moderately disagree | EM5: Полностью не согласен / Strongly disagree | EP5: Скорее не согласен / Moderately disagree | ES5: Скорее согласен / Moderately agree | EV5: Полностью согласен / Strongly agree | FC5: Полностью не согласен / Strongly disagree | FF5: Скорее не согласен / Moderately disagree | FJ5: Скорее не согласен / Moderately disagree | FM5: Скорее согласен / Moderately agree | FQ5: Нет / No | FS5: Нет / No | FU5: Нет / No | FW5: Нет / No | FY5: Нет / No | GA5: Нет / No | GC5: Нет / No | GD5: Да / Yes | GG5: Нет / No | GH5: Да / Yes | GK5: Нет / No | GL5: Да / Yes | GN5: Да / Yes | GQ5: Нет / No | GS5: Нет / No | GU5: Нет / No | GW5: Нет / No | GX5: Донос на работе, мобилизация, угрозы в соц. сетях, деятельность, за которую могут посадить | GY5: Совсем нет/Not at all | HC5: Совсем нет/Not at all | HH5: Немного/A little | HK5: Совсем нет/Not at all | HO5: Совсем нет/Not at all | HS5: Совсем нет/Not at all | HX5: Немного/A little | IA5: Совсем нет/Not at all | IE5: Совсем нет/Not at all | II5: Совсем нет/Not at all | IM5: Совсем нет/Not at all | IQ5: Совсем нет/Not at all | IU5: Совсем нет/Not at all | IZ5: Немного/A little | JC5: Совсем нет/Not at all | JG5: Совсем нет/Not at all | JK5: Совсем нет/Not at all | JP5: Немного/A little | JT5: Немного/A little | JW5: Совсем нет/Not at all | KA5: Совсем нет/Not at all | KE5: Совсем нет/Not at all | KI5: Совсем нет/Not at all | KM5: Совсем нет/Not at all | KQ5: Совсем нет/Not at all | KU5: Совсем нет / Not at all | KY5: Совсем нет / Not at all | LC5: Совсем нет / Not at all | LG5: Совсем нет / Not at all | LK5: Совсем нет / Not at all | LO5: Совсем нет / Not at all | LS5: Совсем нет / Not at all | LW5: Совсем нет / Not at all | MA5: Совсем нет / Not at all | ME5: Совсем нет / Not at all | MI5: Совсем нет / Not at all | MM5: Совсем нет / Not at all | MQ5: Совсем нет / Not at all | MU5: Совсем нет / Not at all | MY5: Совсем нет / Not at all | NC5: Совсем нет / Not at all | NH5: Немного / A little | NK5: Совсем нет / Not at all | NP5: Немного / A little | NS5: Совсем нет / Not at all | NW5: Совсем нет / Not at all | OB5: Немного / A little | OF5: Немного / A little | OJ5: Немного / A little
A6: GU001 | B6: Да / Yes | D6: Да / Yes | F6: Да / Yes | H6: Женский / Female | N6: 35-44 | R6: Русский(ая) / Russian | T6: Русский, английский | U6: Москва | V6: Батуми, Грузия | W6: Женат (замужем) / Married | AD6: Да / Yes | AF6: 1 | AH6: Нет / No | AI6: нет | AN6: Высшее образование (специалист) / 5 years of college | AS6: Средний / Average | AU6: Воссоединиться с мужем, котрый уехал раньше из-за мобилизации | AY6: Полностью не согласен / Strongly disagree | BA6: Скорее согласен / Moderately agree | BF6: Скорее не согласен / Moderately disagree | BK6: Полностью не согласен / Strongly disagree | BO6: Полностью не согласен / Strongly disagree | BQ6: Скорее согласен / Moderately agree | BW6: Полностью не согласен / Strongly disagree | CA6: Полностью не согласен / Strongly disagree | CE6: Полностью не согласен / Strongly disagree | CI6: Полностью не согласен / Strongly disagree | CK6: Скорее согласен / Moderately agree | CP6: Скорее не согласен / Moderately disagree | CU6: Полностью не согласен / Strongly disagree | CY6: Полностью не согласен / Strongly disagree | DC6: Полностью не согласен / Strongly disagree | DD6: Полностью согласен / Strongly agree | DK6: Полностью не согласен / Strongly disagree | DN6: Скорее не согласен / Moderately disagree | DR6: Скорее не согласен / Moderately disagree | DW6: Полностью не согласен / Strongly disagree | EA6: Полностью не согласен / Strongly disagree | EE6: Полностью не согласен / Strongly disagree | EI6: Полностью не согласен / Strongly disagree | EM6: Полностью не согласен / Strongly disagree | EQ6: Полностью не согласен / Strongly disagree | EU6: Полностью не согласен / Strongly disagree | EW6: Скорее согласен / Moderately agree | FC6: Полностью не согласен / Strongly disagree | FG6: Полностью не согласен / Strongly disagree | FH6: Полностью согласен / Strongly agree | FM6: Скорее согласен / Moderately agree | FQ6: Нет / No | FS6: Нет / No | FU6: Нет / No | FW6: Нет / No | FY6: Нет / No | GA6: Нет / No | GB6: Да / Yes | GE6: Нет / No | GG6: Нет / No | GI6: Нет / No | GK6: Нет / No | GM6: Нет / No | GO6: Нет / No | GQ6: Нет / No | GS6: Нет / No | GU6: Нет / No | GW6: Нет / No | GX6: - | GY6: Совсем нет/Not at all | HC6: Совсем нет/Not at all | HG6: Совсем нет/Not at all | HK6: Совсем нет/Not at all | HO6: Совсем нет/Not at all | HS6: Совсем нет/Not at all | HW6: Совсем нет/Not at all | IA6: Совсем нет/Not at all | IE6: Совсем нет/Not at all | II6: Совсем нет/Not at all | IO6: Довольно сильно/Quite a bit | IQ6: Совсем нет/Not at all | IV6: Немного/A little | IZ6: Немного/A little | JC6: Совсем нет/Not at all | JG6: Совсем нет/Not at all | JK6: Совсем нет/Not at all | JO6: Совсем нет/Not at all | JS6: Совсем нет/Not at all | JX6: Немного/A little | KA6: Совсем нет/Not at all | KE6: Совсем нет/Not at all | KJ6: Немного/A little | KM6: Совсем нет/Not at all | KQ6: Совсем нет/Not at all | KU6: Совсем нет / Not at all | KZ6: Немного / A little | LC6: Совсем нет / Not at all | LH6: Немного / A little | LL6: Немного / A little | LP6: Немного / A little | LS6: Совсем нет / Not at all | LX6: Немного / A little | MA6: Совсем нет / Not at all | ME6: Совсем нет / Not at all | MJ6: Немного / A little | MM6: Совсем нет / Not at all | MQ6: Совсем нет / Not at all | MV6: Немного / A little | MY6: Совсем нет / Not at all | NC6: Совсем нет / Not at all | NH6: Немного / A little | NK6: Совсем нет / Not at all | NO6: Совсем нет / Not at all | NS6: Совсем нет / Not at all | NW6: Совсем нет / Not at all | OC6: Довольно сильно / Quite a bit | OE6: Совсем нет / Not at all | OK6: Довольно сильно / Quite a bit
A7: FM002 | B7: Да / Yes | D7: Да / Yes | F7: Да / Yes | I7: Мужской / Male | N7: 35-44 | R7: Русский(ая) / Russian | T7: Русский, английский | U7: Москва | V7: Ереван, Армения | W7: Женат (замужем) / Married | AE7: Нет / No | AF7: 0 | AH7: Нет / No | AI7: 0 | AL7: Незаконченное высшее / Some college | AT7: Выше среднего / Above average | AU7: Опасения за свою жизнь, нежелание платить налоги на "СВО" | AW7: Скорее согласен / Moderately agree | BB7: Скорее не согласен / Moderately disagree | BF7: Скорее не согласен / Moderately disagree | BI7: Скорее согласен / Moderately agree | BL7: Полностью согласен / Strongly agree | BS7: Полностью не согласен / Strongly disagree | BW7: Полностью не согласен / Strongly disagree | BZ7: Скорее не согласен / Moderately disagree | CD7: Скорее не согласен / Moderately disagree | CH7: Скорее не согласен / Moderately disagree | CM7: Полностью не согласен / Strongly disagree | CO7: Скорее согласен / Moderately agree | CS7: Скорее согласен / Moderately agree | CX7: Скорее не согласен / Moderately disagree | DB7: Скорее не согласен / Moderately disagree | DE7: Скорее согласен / Moderately agree | DH7: Полностью согласен / Strongly agree | DM7: Скорее согласен / Moderately agree | DR7: Скорее не согласен / Moderately disagree | DV7: Скорее не согласен / Moderately disagree | DZ7: Скорее не согласен / Moderately disagree | EC7: Скорее согласен / Moderately agree | EI7: Полностью не согласен / Strongly disagree | EM7: Полностью не согласен / Strongly disagree | EP7: Скорее не согласен / Moderately disagree | ET7: Скорее не согласен / Moderately disagree | EX7: Скорее не согласен / Moderately disagree | FB7: Скорее не согласен / Moderately disagree | FF7: Скорее не согласен / Moderately disagree | FH7: Полностью согласен / Strongly agree | FM7: Скорее согласен / Moderately agree | FQ7: Нет / No | FS7: Нет / No | FU7: Нет / No | FW7: Нет / No | FY7: Нет / No | GA7: Нет / No | GC7: Нет / No | GD7: Да / Yes | GG7: Нет / No | GH7: Да / Yes | GJ7: Да / Yes | GL7: Да / Yes | GN7: Да / Yes | GQ7: Нет / No | GS7: Нет / No | GU7: Нет / No | GW7: Нет / No | GX7: Начало "СВО", начало мобилизации | HA7: Довольно сильно/Quite a bit | HE7: Довольно сильно/Quite a bit | HH7: Немного/A little | HM7: Довольно сильно/Quite a bit | HP7: Немного/A little | HT7: Немного/A little | HX7: Немного/A little | IC7: Довольно сильно/Quite a bit | IH7: Очень сильно/Extremely | IJ7: Немного/A little | IP7: Очень сильно/Extremely | IQ7: Совсем нет/Not at all | IV7: Немного/A little | IZ7: Немного/A little | JD7: Немного/A little | JI7: Довольно сильно/Quite a bit | JN7: Очень сильно/Extremely | JP7: Немного/A little | JU7: Довольно сильно/Quite a bit | JY7: Довольно сильно/Quite a bit | KC7: Довольно сильно/Quite a bit | KE7: Совсем нет/Not at all | KJ7: Немного/A little | KM7: Совсем нет/Not at all | KQ7: Совсем нет/Not at all | KW7: Довольно сильно / Quite a bit | LA7: Довольно сильно / Quite a bit | LD7: Немного / A little | LI7: Довольно сильно / Quite a bit | LN7: Очень сильно / Extremely | LP7: Немного / A little | LU7: Довольно сильно / Quite a bit | LW7: Совсем нет / Not at all | MB7: Немного / A little | MH7: Очень сильно / Extremely | MJ7: Немного / A little | MO7: Довольно сильно / Quite a bit | MS7: Довольно сильно / Quite a bit | MW7: Довольно сильно / Quite a bit | MY7: Совсем нет / Not at all | NE7: Довольно сильно / Quite a bit | NH7: Немного / A little | NM7: Довольно сильно / Quite a bit | NQ7: Довольно сильно / Quite a bit | NU7: Довольно сильно / Quite a bit | NY7: Довольно сильно / Quite a bit | OB7: Немного / A little | OF7: Немного / A little | OI7: Совсем нет / Not at all
A8: FM001 | B8: Да / Yes | D8: Да / Yes | F8: Да / Yes | I8: Мужской / Male | O8: 45-54 | R8: Русский(ая) / Russian | T8: Русский, English, Français | U8: Москва | V8: Ереван, Армения | W8: Женат (замужем) / Married | AD8: Да / Yes | AF8: 1 ребенок 17 лет, 3 ребенка старше 18 лет | AH8: Нет / No | AI8: Нет | AN8: Высшее образование (специалист) / 5 years of college | AS8: Средний / Average | AU8: Формально подлежу мобилизации, не хочу участвовать в войне Путина | AX8: Скорее не согласен / Moderately disagree | BC8: Полностью не согласен / Strongly disagree | BG8: Полностью не согласен / Strongly disagree | BK8: Полностью не согласен / Strongly disagree | BN8: Скорее не согласен / Moderately disagree | BR8: Скорее не согласен / Moderately disagree | BV8: Скорее не согласен / Moderately disagree | BZ8: Скорее не согласен / Moderately disagree | CD8: Скорее не согласен / Moderately disagree | CH8: Скорее не согласен / Moderately disagree | CL8: Скорее не согласен / Moderately disagree | CQ8: Полностью не согласен / Strongly disagree | CU8: Полностью не согласен / Strongly disagree | CX8: Скорее не согласен / Moderately disagree | DC8: Полностью не согласен / Strongly disagree | DF8: Скорее не согласен / Moderately disagree | DJ8: Скорее не согласен / Moderately disagree | DN8: Скорее не согласен / Moderately disagree | DQ8: Скорее согласен / Moderately agree | DV8: Скорее не согласен / Moderately disagree | EA8: Полностью не согласен / Strongly disagree | ED8: Скорее не согласен / Moderately disagree | EI8: Полностью не согласен / Strongly disagree | EM8: Полностью не согласен / Strongly disagree | EQ8: Полностью не согласен / Strongly disagree | ES8: Скорее согласен / Moderately agree | EX8: Скорее не согласен / Moderately disagree | FC8: Полностью не согласен / Strongly disagree | FG8: Полностью не согласен / Strongly disagree | FI8: Скорее согласен / Moderately agree | FN8: Скорее не согласен / Moderately disagree | FQ8: Нет / No | FS8: Нет / No | FU8: Нет / No | FW8: Нет / No | FY8: Нет / No | GA8: Нет / No | GC8: Нет / No | GE8: Нет / No | GG8: Нет / No | GI8: Нет / No | GK8: Нет / No | GM8: Нет / No | GO8: Нет / No | GQ8: Нет / No | GS8: Нет / No | GU8: Нет / No | GW8: Нет / No | GX8: В Армении угрожающих ситуаций не было | GY8: Совсем нет/Not at all | HC8: Совсем нет/Not at all | HG8: Совсем нет/Not at all | HL8: Немного/A little | HO8: Совсем нет/Not at all | HS8: Совсем нет/Not at all | HW8: Совсем нет/Not at all | IA8: Совсем нет/Not at all | IE8: Совсем нет/Not at all | II8: Совсем нет/Not at all | IM8: Совсем нет/Not at all | IQ8: Совсем нет/Not at all | IU8: Совсем нет/Not at all | IZ8: Немного/A little | JD8: Немного/A little | JG8: Совсем нет/Not at all | JK8: Совсем нет/Not at all | JO8: Совсем нет/Not at all | JS8: Совсем нет/Not at all | JW8: Совсем нет/Not at all | KA8: Совсем нет/Not at all | KF8: Немного/A little | KI8: Совсем нет/Not at all | KM8: Совсем нет/Not at all | KQ8: Совсем нет/Not at all | KV8: Немного / A little | KY8: Совсем нет / Not at all | LC8: Совсем нет / Not at all | LH8: Немного / A little | LK8: Совсем нет / Not at all | LO8: Совсем нет / Not at all | LS8: Совсем нет / Not at all | LW8: Совсем нет / Not at all | MA8: Совсем нет / Not at all | MF8: Немного / A little | MJ8: Немного / A little | MN8: Немного / A little | MQ8: Совсем нет / Not at all | MV8: Немного / A little | MY8: Совсем нет / Not at all | ND8: Немного / A little | NH8: Немного / A little | NL8: Немного / A little | NO8: Совсем нет / Not at all | NT8: Немного / A little | NW8: Совсем нет / Not at all | OA8: Совсем нет / Not at all | OE8: Совсем нет / Not at all | OI8: Совсем нет / Not at all
A9: PM001 | B9: Да / Yes | D9: Да / Yes | F9: Да / Yes | H9: Женский / Female | P9: 55-64 | R9: Русский(ая) / Russian | T9: Русский, английский | U9: Москва | V9: Ереван, Армения | W9: Женат (замужем) / Married | AD9: Да / Yes | AF9: 1 | AH9: Нет / No | AN9: Высшее образование (специалист) / 5 years of college | AS9: Средний / Average | AU9: Тревога за мужа, усталось от постоянного напряжения из-за политической обстановки | AX9: Скорее не согласен / Moderately disagree | BA9: Скорее согласен / Moderately agree | BE9: Скорее согласен / Moderately agree | BJ9: Скорее не согласен / Moderately disagree | BN9: Скорее не согласен / Moderately disagree | BR9: Скорее не согласен / Moderately disagree | BU9: Скорее согласен / Moderately agree | BY9: Скорее согласен / Moderately agree | CC9: Скорее согласен / Moderately agree | CH9: Скорее не согласен / Moderately disagree | CL9: Скорее не согласен / Moderately disagree | CP9: Скорее не согласен / Moderately disagree | CT9: Скорее не согласен / Moderately disagree | CX9: Скорее не согласен / Moderately disagree | DB9: Скорее не согласен / Moderately disagree | DD9: Полностью согласен / Strongly agree | DJ9: Скорее не согласен / Moderately disagree | DM9: Скорее согласен / Moderately agree | DQ9: Скорее согласен / Moderately agree | DU9: Скорее согласен / Moderately agree | DZ9: Скорее не согласен / Moderately disagree | ED9: Скорее не согласен / Moderately disagree | EI9: Полностью не согласен / Strongly disagree | EM9: Полностью не согласен / Strongly disagree | EP9: Скорее не согласен / Moderately disagree | ES9: Скорее согласен / Moderately agree | EW9: Скорее согласен / Moderately agree | FB9: Скорее не согласен / Moderately disagree | FG9: Полностью не согласен / Strongly disagree | FH9: Полностью согласен / Strongly agree | FN9: Скорее не согласен / Moderately disagree | FQ9: Нет / No | FS9: Нет / No | FU9: Нет / No | FW9: Нет / No | FY9: Нет / No | GA9: Нет / No | GC9: Нет / No | GE9: Нет / No | GG9: Нет / No | GI9: Нет / No | GK9: Нет / No | GM9: Нет / No | GO9: Нет / No | GQ9: Нет / No | GS9: Нет / No | GU9: Нет / No | GW9: Нет / No | GY9: Совсем нет/Not at all | HC9: Совсем нет/Not at all | HH9: Немного/A little | HL9: Немного/A little | HO9: Совсем нет/Not at all | HS9: Совсем нет/Not at all | HX9: Немного/A little | IA9: Совсем нет/Not at all | IE9: Совсем нет/Not at all | II9: Совсем нет/Not at all | IM9: Совсем нет/Not at all | IQ9: Совсем нет/Not at all | IU9: Совсем нет/Not at all | IZ9: Немного/A little | JD9: Немного/A little | JG9: Совсем нет/Not at all | JL9: Немного/A little | JP9: Немного/A little | JS9: Совсем нет/Not at all | JW9: Совсем нет/Not at all | KA9: Совсем нет/Not at all | KE9: Совсем нет/Not at all | KI9: Совсем нет/Not at all | KM9: Совсем нет/Not at all | KQ9: Совсем нет/Not at all | KU9: Совсем нет / Not at all | KY9: Совсем нет / Not at all | LC9: Совсем нет / Not at all | LG9: Совсем нет / Not at all | LK9: Совсем нет / Not at all | LO9: Совсем нет / Not at all | LS9: Совсем нет / Not at all | LX9: Немного / A little | MA9: Совсем нет / Not at all | MF9: Немного / A little | MJ9: Немного / A little | MM9: Совсем нет / Not at all | MQ9: Совсем нет / Not at all | MV9: Немного / A little | MY9: Совсем нет / Not at all | NC9: Совсем нет / Not at all | NH9: Немного / A little | NL9: Немного / A little | NP9: Немного / A little | NT9: Немного / A little | NX9: Немного / A little | OA9: Совсем нет / Not at all | OF9: Немного / A little | OK9: Довольно сильно / Quite a bit
A10: MF001 | B10: Да / Yes | D10: Да / Yes | F10: Да / Yes | I10: Мужской / Male | M10: 25-34 | R10: Русский(ая) / Russian | T10: Английский B1 | U10: Московская область г. Балашиха | V10: Кобулети | AA10: Гражданский брак / Cohabiting with a significant other or in a domestic partnership | AD10: Да / Yes | AF10: 1 | AH10: Нет / No | AI10: 0 | AN10: Высшее образование (специалист) / 5 years of college | AT10: Выше среднего / Above average | AU10: Моё наличие в России косвенно и напрямую помогает ведению войны | AX10: Скорее не согласен / Moderately disagree | BC10: Полностью не согласен / Strongly disagree | BG10: Полностью не согласен / Strongly disagree | BJ10: Скорее не согласен / Moderately disagree | BN10: Скорее не согласен / Moderately disagree | BR10: Скорее не согласен / Moderately disagree | BW10: Полностью не согласен / Strongly disagree | BZ10: Скорее не согласен / Moderately disagree | CE10: Полностью не согласен / Strongly disagree | CI10: Полностью не согласен / Strongly disagree | CL10: Скорее не согласен / Moderately disagree | CO10: Скорее согласен / Moderately agree | CS10: Скорее согласен / Moderately agree | CX10: Скорее не согласен / Moderately disagree | DB10: Скорее не согласен / Moderately disagree | DD10: Полностью согласен / Strongly agree | DI10: Скорее согласен / Moderately agree | DM10: Скорее согласен / Moderately agree | DR10: Скорее не согласен / Moderately disagree | DV10: Скорее не согласен / Moderately disagree | EA10: Полностью не согласен / Strongly disagree | EE10: Полностью не согласен / Strongly disagree | EI10: Полностью не согласен / Strongly disagree | EL10: Скорее не согласен / Moderately disagree | EQ10: Полностью не согласен / Strongly disagree | EU10: Полностью не согласен / Strongly disagree | EW10: Скорее согласен / Moderately agree | FB10: Скорее не согласен / Moderately disagree | FG10: Полностью не согласен / Strongly disagree | FH10: Полностью согласен / Strongly agree | FL10: Полностью согласен / Strongly agree | FQ10: Нет / No | FS10: Нет / No | FU10: Нет / No | FW10: Нет / No | FY10: Нет / No | GA10: Нет / No | GC10: Нет / No | GE10: Нет / No | GG10: Нет / No | GI10: Нет / No | GJ10: Да / Yes | GM10: Нет / No | GO10: Нет / No | GQ10: Нет / No | GS10: Нет / No | GU10: Нет / No | GW10: Нет / No | GZ10: Немного/A little | HD10: Немного/A little | HG10: Совсем нет/Not at all | HM10: Довольно сильно/Quite a bit | HR10: Очень сильно/Extremely | HS10: Совсем нет/Not at all | HY10: Довольно сильно/Quite a bit | IC10: Довольно сильно/Quite a bit | IE10: Совсем нет/Not at all | IJ10: Немного/A little | IP10: Очень сильно/Extremely | IQ10: Совсем нет/Not at all | IV10: Немного/A little | IZ10: Немного/A little | JD10: Немного/A little | JG10: Совсем нет/Not at all | JK10: Совсем нет/Not at all | JP10: Немного/A little | JT10: Немного/A little | JY10: Довольно сильно/Quite a bit | KB10: Немного/A little | KE10: Совсем нет/Not at all | KI10: Совсем нет/Not at all | KO10: Довольно сильно/Quite a bit | KR10: Немного/A little | KV10: Немного / A little | KY10: Совсем нет / Not at all | LC10: Совсем нет / Not at all | LG10: Совсем нет / Not at all | LK10: Совсем нет / Not at all | LP10: Немного / A little | LT10: Немного / A little | LY10: Довольно сильно / Quite a bit | MA10: Совсем нет / Not at all | ME10: Совсем нет / Not at all | MK10: Довольно сильно / Quite a bit | MN10: Немного / A little | MQ10: Совсем нет / Not at all | MU10: Совсем нет / Not at all | MZ10: Немного / A little | NE10: Довольно сильно / Quite a bit | NH10: Немного / A little | NL10: Немного / A little | NO10: Совсем нет / Not at all | NT10: Немного / A little | NX10: Немного / A little | OA10: Совсем нет / Not at all | OF10: Немного / A little | OI10: Совсем нет / Not at all
A11: MU001 | B11: Да / Yes | D11: Да / Yes | F11: Да / Yes | H11: Женский / Female | M11: 25-34 | R11: Русский(ая) / Russian | T11: Русский, Английский, Французский | U11: Сочи | V11: Батуми | W11: Женат (замужем) / Married | AE11: Нет / No | AF11: Нет | AH11: Нет / No | AI11: Нет | AO11: Магистратура / Master’s Degree | AS11: Средний / Average | AU11: Отсутствие безопасности для мужа и перспектив, что она появится в ближайшее время | AX11: Скорее не согласен / Moderately disagree | BB11: Скорее не согласен / Moderately disagree | BE11: Скорее согласен / Moderately agree | BJ11: Скорее не согласен / Moderately disagree | BN11: Скорее не согласен / Moderately disagree | BR11: Скорее не согласен / Moderately disagree | BW11: Полностью не согласен / Strongly disagree | BZ11: Скорее не согласен / Moderately disagree | CD11: Скорее не согласен / Moderately disagree | CG11: Скорее согласен / Moderately agree | CL11: Скорее не согласен / Moderately disagree | CQ11: Полностью не согласен / Strongly disagree | CU11: Полностью не согласен / Strongly disagree | CY11: Полностью не согласен / Strongly disagree | DC11: Полностью не согласен / Strongly disagree | DG11: Полностью не согласен / Strongly disagree | DK11: Полностью не согласен / Strongly disagree | DM11: Скорее согласен / Moderately agree | DR11: Скорее не согласен / Moderately disagree | DV11: Скорее не согласен / Moderately disagree | EA11: Полностью не согласен / Strongly disagree | ED11: Скорее не согласен / Moderately disagree | EI11: Полностью не согласен / Strongly disagree | EM11: Полностью не согласен / Strongly disagree | EP11: Скорее не согласен / Moderately disagree | ET11: Скорее не согласен / Moderately disagree | EY11: Полностью не согласен / Strongly disagree | FB11: Скорее не согласен / Moderately disagree | FF11: Скорее не согласен / Moderately disagree | FI11: Скорее согласен / Moderately agree | FO11: Полностью не согласен / Strongly disagree | FQ11: Нет / No | FS11: Нет / No | FU11: Нет / No | FW11: Нет / No | FY11: Нет / No | FZ11: Да / Yes | GB11: Да / Yes | GE11: Нет / No | GG11: Нет / No | GH11: Да / Yes | GK11: Нет / No | GL11: Да / Yes | GO11: Нет / No | GQ11: Нет / No | GS11: Нет / No | GU11: Нет / No | GW11: Нет / No | GX11: - | GY11: Совсем нет/Not at all | HC11: Совсем нет/Not at all | HG11: Совсем нет/Not at all | HK11: Совсем нет/Not at all | HP11: Немного/A little | HT11: Немного/A little | HX11: Немного/A little | IB11: Немного/A little | IE11: Совсем нет/Not at all | II11: Совсем нет/Not at all | IM11: Совсем нет/Not at all | IQ11: Совсем нет/Not at all | IU11: Совсем нет/Not at all | IZ11: Немного/A little | JC11: Совсем нет/Not at all | JG11: Совсем нет/Not at all | JK11: Совсем нет/Not at all | JO11: Совсем нет/Not at all | JS11: Совсем нет/Not at all | JW11: Совсем нет/Not at all | KA11: Совсем нет/Not at all | KE11: Совсем нет/Not at all | KI11: Совсем нет/Not at all | KM11: Совсем нет/Not at all | KQ11: Совсем нет/Not at all | KU11: Совсем нет / Not at all | KZ11: Немного / A little | LD11: Немного / A little | LH11: Немного / A little | LL11: Немного / A little | LO11: Совсем нет / Not at all | LT11: Немного / A little | LW11: Совсем нет / Not at all | MA11: Совсем нет / Not at all | MF11: Немного / A little | MJ11: Немного / A little | MM11: Совсем нет / Not at all | MQ11: Совсем нет / Not at all | MU11: Совсем нет / Not at all | MY11: Совсем нет / Not at all | ND11: Немного / A little | NH11: Немного / A little | NL11: Немного / A little | NP11: Немного / A little | NS11: Совсем нет / Not at all | NW11: Совсем нет / Not at all | OA11: Совсем нет / Not at all | OE11: Совсем нет / Not at all | OI11: Совсем нет / Not at all
A12: KU001 | B12: Да / Yes | D12: Да / Yes | F12: Да / Yes | H12: Женский / Female | O12: 45-54 | R12: Русский(ая) / Russian | T12: Английский | U12: Мытищи, Московская обл | V12: Тбилиси, Грузия | Y12: В разводе / Divorced | AE12: Нет / No | AH12: Нет / No | AN12: Высшее образование (специалист) / 5 years of college | AS12: Средний / Average | AU12: Не согласна ни с внутренней, ни, особенно, с внешней политикой государства. Отчаялась, не верю, что что-то можно изменить, или хотя бы сменить президента | AW12: Скорее согласен / Moderately agree | BB12: Скорее не согласен / Moderately disagree | BE12: Скорее согласен / Moderately agree | BJ12: Скорее не согласен / Moderately disagree | BO12: Полностью не согласен / Strongly disagree | BP12: Полностью согласен / Strongly agree | BU12: Скорее согласен / Moderately agree | BY12: Скорее согласен / Moderately agree | CD12: Скорее не согласен / Moderately disagree | CH12: Скорее не согласен / Moderately disagree | CK12: Скорее согласен / Moderately agree | CN12: Полностью согласен / Strongly agree | CR12: Полностью согласен / Strongly agree | DE12: Скорее согласен / Moderately agree | DI12: Скорее согласен / Moderately agree | DM12: Скорее согласен / Moderately agree | DQ12: Скорее согласен / Moderately agree | DU12: Скорее согласен / Moderately agree | EA12: Полностью не согласен / Strongly disagree | EI12: Полностью не согласен / Strongly disagree | EM12: Полностью не согласен / Strongly disagree | EP12: Скорее не согласен / Moderately disagree | ER12: Полностью согласен / Strongly agree | EX12: Скорее не согласен / Moderately disagree | FA12: Скорее согласен / Moderately agree | FE12: Скорее согласен / Moderately agree | FK12: Полностью не согласен / Strongly disagree | FO12: Полностью не согласен / Strongly disagree | FQ12: Нет / No | FS12: Нет / No | FT12: Да / Yes | FV12: Да / Yes | FY12: Нет / No | GA12: Нет / No | GC12: Нет / No | GE12: Нет / No | GG12: Нет / No | GH12: Да / Yes | GJ12: Да / Yes | GL12: Да / Yes | GO12: Нет / No | GQ12: Нет / No | GS12: Нет / No | GU12: Нет / No | GW12: Нет / No | GY12: Совсем нет/Not at all | HD12: Немного/A little | HG12: Совсем нет/Not at all | HK12: Совсем нет/Not at all | HO12: Совсем нет/Not at all | HT12: Немного/A little | HX12: Немного/A little | IB12: Немного/A little | IG12: Довольно сильно/Quite a bit | IJ12: Немного/A little | IO12: Довольно сильно/Quite a bit | IQ12: Совсем нет/Not at all | IW12: Довольно сильно/Quite a bit | JA12: Довольно сильно/Quite a bit | JD12: Немного/A little | JH12: Немного/A little | JL12: Немного/A little | JO12: Совсем нет/Not at all | JT12: Немного/A little | JY12: Довольно сильно/Quite a bit | KB12: Немного/A little | KE12: Совсем нет/Not at all | KJ12: Немного/A little | KM12: Совсем нет/Not at all | KQ12: Совсем нет/Not at all | KU12: Совсем нет / Not at all | KZ12: Немного / A little | LC12: Совсем нет / Not at all | LH12: Немного / A little | LK12: Совсем нет / Not at all | LO12: Совсем нет / Not at all | LT12: Немного / A little | LY12: Довольно сильно / Quite a bit | MA12: Совсем нет / Not at all | MF12: Немного / A little | MJ12: Немного / A little | MM12: Совсем нет / Not at all | MQ12: Совсем нет / Not at all | MW12: Довольно сильно / Quite a bit | MZ12: Немного / A little | ND12: Немного / A little | NI12: Довольно сильно / Quite a bit | NM12: Довольно сильно / Quite a bit | NP12: Немного / A little | NT12: Немного / A little | NX12: Немного / A little | OC12: Довольно сильно / Quite a bit | OG12: Довольно сильно / Quite a bit | OI12: Совсем нет / Not at all
A13: OT001 | B13: Да / Yes | D13: Да / Yes | F13: Да / Yes | I13: Мужской / Male | M13: 25-34 | S13: русский-немец | T13: Russian and English | U13: Ижевск, Удмуртия | V13: Тбилиси, Грузия | AB13: Никогда не был женат (замужем) / Single, never married | AE13: Нет / No | AF13: - | AH13: Нет / No | AI13: - | AK13: Среднее образование / High school graduate | AR13: Ниже среднего / Below average | AU13: Опасения за свою финансовую и физическую безопасность, нежелание молчать | AY13: Полностью не согласен / Strongly disagree | BC13: Полностью не согласен / Strongly disagree | BF13: Скорее не согласен / Moderately disagree | BI13: Скорее согласен / Moderately agree | BM13: Скорее согласен / Moderately agree | BS13: Полностью не согласен / Strongly disagree | BW13: Полностью не согласен / Strongly disagree | CA13: Полностью не согласен / Strongly disagree | CD13: Скорее не согласен / Moderately disagree | CI13: Полностью не согласен / Strongly disagree | CM13: Полностью не согласен / Strongly disagree | CP13: Скорее не согласен / Moderately disagree | CR13: Полностью согласен / Strongly agree | CY13: Полностью не согласен / Strongly disagree | DC13: Полностью не согласен / Strongly disagree | DE13: Скорее согласен / Moderately agree | DH13: Полностью согласен / Strongly agree | DM13: Скорее согласен / Moderately agree | DP13: Полностью согласен / Strongly agree | DU13: Скорее согласен / Moderately agree | EA13: Полностью не согласен / Strongly disagree | EE13: Полностью не согласен / Strongly disagree | EH13: Скорее не согласен / Moderately disagree | EM13: Полностью не согласен / Strongly disagree | EQ13: Полностью не согласен / Strongly disagree | ET13: Скорее не согласен / Moderately disagree | EW13: Скорее согласен / Moderately agree | FC13: Полностью не согласен / Strongly disagree | FF13: Скорее не согласен / Moderately disagree | FI13: Скорее согласен / Moderately agree | FL13: Полностью согласен / Strongly agree | FQ13: Нет / No | FS13: Нет / No | FT13: Да / Yes | FW13: Нет / No | FX13: Да / Yes | GA13: Нет / No | GC13: Нет / No | GD13: Да / Yes | GG13: Нет / No | GH13: Да / Yes | GK13: Нет / No | GL13: Да / Yes | GN13: Да / Yes | GP13: Да / Yes | GS13: Нет / No | GU13: Нет / No | GW13: Нет / No | HA13: Довольно сильно/Quite a bit | HC13: Совсем нет/Not at all | HJ13: Очень сильно/Extremely | HL13: Немного/A little | HO13: Совсем нет/Not at all | HV13: Очень сильно/Extremely | HX13: Немного/A little | IC13: Довольно сильно/Quite a bit | IG13: Довольно сильно/Quite a bit | II13: Совсем нет/Not at all | IN13: Немного/A little | IQ13: Совсем нет/Not at all | IV13: Немного/A little | IY13: Совсем нет/Not at all | JC13: Совсем нет/Not at all | JH13: Немного/A little | JK13: Совсем нет/Not at all | JO13: Совсем нет/Not at all | JS13: Совсем нет/Not at all | JW13: Совсем нет/Not at all | KC13: Довольно сильно/Quite a bit | KE13: Совсем нет/Not at all | KJ13: Немного/A little | KN13: Немного/A little | KQ13: Совсем нет/Not at all | KU13: Совсем нет / Not at all | KZ13: Немного / A little | LD13: Немного / A little | LI13: Довольно сильно / Quite a bit | LL13: Немного / A little | LP13: Немного / A little | LU13: Довольно сильно / Quite a bit | LX13: Немного / A little | MB13: Немного / A little | MG13: Довольно сильно / Quite a bit | MJ13: Немного / A little | MM13: Совсем нет / Not at all | MS13: Довольно сильно / Quite a bit | MU13: Совсем нет / Not at all | MY13: Совсем нет / Not at all | ND13: Немного / A little | NG13: Совсем нет / Not at all | NL13: Немного / A little | NR13: Очень сильно / Extremely | NS13: Совсем нет / Not at all | NW13: Совсем нет / Not at all | OB13: Немного / A little | OE13: Совсем нет / Not at all | OI13: Совсем нет / Not at all
A14: PD001 | B14: Да / Yes | D14: Да / Yes | F14: Да / Yes | I14: Мужской / Male | L14: 18-24 | R14: Русский(ая) / Russian | T14: Русский, Английский. | U14: Москва | V14: Тбилиси, Грузия. | AB14: Никогда не был женат (замужем) / Single, never married | AE14: Нет / No | AF14: Нет | AH14: Нет / No | AI14: Нет | AL14: Незаконченное высшее / Some college | AS14: Средний / Average | AU14: Из соображений безопасности, свободы слова и действия. | AY14: Полностью не согласен / Strongly disagree | BB14: Скорее не согласен / Moderately disagree | BF14: Скорее не согласен / Moderately disagree | BI14: Скорее согласен / Moderately agree | BO14: Полностью не согласен / Strongly disagree | BS14: Полностью не согласен / Strongly disagree | BW14: Полностью не согласен / Strongly disagree | BY14: Скорее согласен / Moderately agree | CC14: Скорее согласен / Moderately agree | CH14: Скорее не согласен / Moderately disagree | CM14: Полностью не согласен / Strongly disagree | CQ14: Полностью не согласен / Strongly disagree | CS14: Скорее согласен / Moderately agree | CY14: Полностью не согласен / Strongly disagree | DC14: Полностью не согласен / Strongly disagree | DE14: Скорее согласен / Moderately agree | DJ14: Скорее не согласен / Moderately disagree | DM14: Скорее согласен / Moderately agree | DQ14: Скорее согласен / Moderately agree | DW14: Полностью не согласен / Strongly disagree | EA14: Полностью не согласен / Strongly disagree | EE14: Полностью не согласен / Strongly disagree | EI14: Полностью не согласен / Strongly disagree | EL14: Скорее не согласен / Moderately disagree | EQ14: Полностью не согласен / Strongly disagree | ET14: Скорее не согласен / Moderately disagree | EW14: Скорее согласен / Moderately agree | FB14: Скорее не согласен / Moderately disagree | FF14: Скорее не согласен / Moderately disagree | FH14: Полностью согласен / Strongly agree | FM14: Скорее согласен / Moderately agree | FP14: Да / Yes | FS14: Нет / No | FU14: Нет / No | FW14: Нет / No | FY14: Нет / No | GA14: Нет / No | GC14: Нет / No | GE14: Нет / No | GG14: Нет / No | GI14: Нет / No | GK14: Нет / No | GM14: Нет / No | GO14: Нет / No | GQ14: Нет / No | GS14: Нет / No | GU14: Нет / No | GW14: Нет / No | GX14: К своему великому счастью, подобных ситуаций мне до сих пор не приходилось испытывать. | GY14: Совсем нет/Not at all | HD14: Немного/A little | HG14: Совсем нет/Not at all | HL14: Немного/A little | HO14: Совсем нет/Not at all | HS14: Совсем нет/Not at all | HW14: Совсем нет/Not at all | IC14: Довольно сильно/Quite a bit | IF14: Немного/A little | II14: Совсем нет/Not at all | IM14: Совсем нет/Not at all | IQ14: Совсем нет/Not at all | IU14: Совсем нет/Not at all | IY14: Совсем нет/Not at all | JC14: Совсем нет/Not at all | JG14: Совсем нет/Not at all | JK14: Совсем нет/Not at all | JO14: Совсем нет/Not at all | JT14: Немного/A little | JW14: Совсем нет/Not at all | KA14: Совсем нет/Not at all | KE14: Совсем нет/Not at all | KI14: Совсем нет/Not at all | KM14: Совсем нет/Not at all | KQ14: Совсем нет/Not at all | KU14: Совсем нет / Not at all | KY14: Совсем нет / Not at all | LC14: Совсем нет / Not at all | LG14: Совсем нет / Not at all | LL14: Немного / A little | LO14: Совсем нет / Not at all | LS14: Совсем нет / Not at all | LW14: Совсем нет / Not at all | MA14: Совсем нет / Not at all | ME14: Совсем нет / Not at all | MJ14: Немного / A little | MM14: Совсем нет / Not at all | MQ14: Совсем нет / Not at all | MU14: Совсем нет / Not at all | MY14: Совсем нет / Not at all | ND14: Немного / A little | NG14: Совсем нет / Not at all | NL14: Немного / A little | NP14: Немного / A little | NS14: Совсем нет / Not at all | NX14: Немного / A little | OA14: Совсем нет / Not at all | OG14: Довольно сильно / Quite a bit | OI14: Совсем нет / Not at all
A15: CI002 | B15: Да / Yes | D15: Да / Yes | F15: Да / Yes | I15: Мужской / Male | O15: 45-54 | R15: Русский(ая) / Russian | T15: Русский, итальянский | U15: Москва | V15: Тбилиси | W15: Женат (замужем) / Married | AD15: Да / Yes | AF15: 2 | AG15: Да / Yes | AI15: 1 | AP15: Кандидат наук / Doctoral Degree | AS15: Средний / Average | AU15: Из-за глубокого отвращения к происходящему в ней | AY15: Полностью не согласен / Strongly disagree | BC15: Полностью не согласен / Strongly disagree | BF15: Скорее не согласен / Moderately disagree | BK15: Полностью не согласен / Strongly disagree | BN15: Скорее не согласен / Moderately disagree | BR15: Скорее не согласен / Moderately disagree | BW15: Полностью не согласен / Strongly disagree | BY15: Скорее согласен / Moderately agree | CD15: Скорее не согласен / Moderately disagree | CH15: Скорее не согласен / Moderately disagree | CL15: Скорее не согласен / Moderately disagree | CO15: Скорее согласен / Moderately agree | CS15: Скорее согласен / Moderately agree | CW15: Скорее согласен / Moderately agree | DB15: Скорее не согласен / Moderately disagree | DG15: Полностью не согласен / Strongly disagree | DI15: Скорее согласен / Moderately agree | DM15: Скорее согласен / Moderately agree | DQ15: Скорее согласен / Moderately agree | DU15: Скорее согласен / Moderately agree | EA15: Полностью не согласен / Strongly disagree | EE15: Полностью не согласен / Strongly disagree | EH15: Скорее не согласен / Moderately disagree | EK15: Скорее согласен / Moderately agree | EP15: Скорее не согласен / Moderately disagree | ET15: Скорее не согласен / Moderately disagree | EW15: Скорее согласен / Moderately agree | FC15: Полностью не согласен / Strongly disagree | FE15: Скорее согласен / Moderately agree | FH15: Полностью согласен / Strongly agree | FN15: Скорее не согласен / Moderately disagree | FP15: Да / Yes | FS15: Нет / No | FU15: Нет / No | FW15: Нет / No | FY15: Нет / No | GA15: Нет / No | GC15: Нет / No | GE15: Нет / No | GG15: Нет / No | GH15: Да / Yes | GK15: Нет / No | GM15: Нет / No | GO15: Нет / No | GQ15: Нет / No | GS15: Нет / No | GU15: Нет / No | GW15: Нет / No | GY15: Совсем нет/Not at all | HC15: Совсем нет/Not at all | HG15: Совсем нет/Not at all | HK15: Совсем нет/Not at all | HO15: Совсем нет/Not at all | HS15: Совсем нет/Not at all | HX15: Немного/A little | IA15: Совсем нет/Not at all | IF15: Немного/A little | IJ15: Немного/A little | IM15: Совсем нет/Not at all | IQ15: Совсем нет/Not at all | IU15: Совсем нет/Not at all | IY15: Совсем нет/Not at all | JC15: Совсем нет/Not at all | JG15: Совсем нет/Not at all | JK15: Совсем нет/Not at all | JO15: Совсем нет/Not at all | JS15: Совсем нет/Not at all | JW15: Совсем нет/Not at all | KA15: Совсем нет/Not at all | KF15: Немного/A little | KI15: Совсем нет/Not at all | KM15: Совсем нет/Not at all | KQ15: Совсем нет/Not at all | KU15: Совсем нет / Not at all | KY15: Совсем нет / Not at all | LC15: Совсем нет / Not at all | LG15: Совсем нет / Not at all | LK15: Совсем нет / Not at all | LO15: Совсем нет / Not at all | LS15: Совсем нет / Not at all | LW15: Совсем нет / Not at all | MA15: Совсем нет / Not at all | ME15: Совсем нет / Not at all | MI15: Совсем нет / Not at all | MN15: Немного / A little | MQ15: Совсем нет / Not at all | MU15: Совсем нет / Not at all | MY15: Совсем нет / Not at all | NC15: Совсем нет / Not at all | NG15: Совсем нет / Not at all | NK15: Совсем нет / Not at all | NO15: Совсем нет / Not at all | NS15: Совсем нет / Not at all | NW15: Совсем нет / Not at all | OA15: Совсем нет / Not at all | OE15: Совсем нет / Not at all | OI15: Совсем нет / Not at all
A16: YC001 | B16: Да / Yes | D16: Да / Yes | F16: Да / Yes | I16: Мужской / Male | N16: 35-44 | R16: Русский(ая) / Russian | T16: English | U16: Piatigorsk city | V16: Tbilisi | AA16: Гражданский брак / Cohabiting with a significant other or in a domestic partnership | AE16: Нет / No | AF16: No | AH16: Нет / No | AI16: No | AQ16: Профессиональное образование / Professional Degree | AR16: Ниже среднего / Below average | AU16: Не хочу быть частью фашистской системы, не хочу быть мобилизованным. Россия - страна террорист. | AW16: Скорее согласен / Moderately agree | BB16: Скорее не согласен / Moderately disagree | BF16: Скорее не согласен / Moderately disagree | BI16: Скорее согласен / Moderately agree | BN16: Скорее не согласен / Moderately disagree | BR16: Скорее не согласен / Moderately disagree | BU16: Скорее согласен / Moderately agree | CA16: Полностью не согласен / Strongly disagree | CD16: Скорее не согласен / Moderately disagree | CF16: Полностью согласен / Strongly agree | CM16: Полностью не согласен / Strongly disagree | CP16: Скорее не согласен / Moderately disagree | CS16: Скорее согласен / Moderately agree | CY16: Полностью не согласен / Strongly disagree | DC16: Полностью не согласен / Strongly disagree | DF16: Скорее не согласен / Moderately disagree | DI16: Скорее согласен / Moderately agree | DL16: Полностью согласен / Strongly agree | DQ16: Скорее согласен / Moderately agree | DV16: Скорее не согласен / Moderately disagree | EA16: Полностью не согласен / Strongly disagree | EE16: Полностью не согласен / Strongly disagree | EI16: Полностью не согласен / Strongly disagree | EM16: Полностью не согласен / Strongly disagree | EP16: Скорее не согласен / Moderately disagree | ET16: Скорее не согласен / Moderately disagree | EW16: Скорее согласен / Moderately agree | FA16: Скорее согласен / Moderately agree | FE16: Скорее согласен / Moderately agree | FH16: Полностью согласен / Strongly agree | FL16: Полностью согласен / Strongly agree | FP16: Да / Yes | FS16: Нет / No | FU16: Нет / No | FV16: Да / Yes | FX16: Да / Yes | GA16: Нет / No | GB16: Да / Yes | GD16: Да / Yes | GF16: Да / Yes | GH16: Да / Yes | GK16: Нет / No | GM16: Нет / No | GO16: Нет / No | GQ16: Нет / No | GS16: Нет / No | GT16: Да / Yes | GW16: Нет / No | GX16: Я люблю жить в дикой природе в палатке по несколько месяцев, однажды упал со скалы и вывихнул руку наизнанку, когда летел думал, что мне конец. | GZ16: Немного/A little | HD16: Немного/A little | HG16: Совсем нет/Not at all | HL16: Немного/A little | HO16: Совсем нет/Not at all | HT16: Немного/A little | HX16: Немного/A little | ID16: Очень сильно/Extremely | IF16: Немного/A little | IJ16: Немного/A little | IM16: Совсем нет/Not at all | IQ16: Совсем нет/Not at all | IV16: Немного/A little | IY16: Совсем нет/Not at all | JC16: Совсем нет/Not at all | JI16: Довольно сильно/Quite a bit | JL16: Немного/A little | JO16: Совсем нет/Not at all | JS16: Совсем нет/Not at all | JY16: Довольно сильно/Quite a bit | KB16: Немного/A little | KE16: Совсем нет/Not at all | KI16: Совсем нет/Not at all | KM16: Совсем нет/Not at all | KQ16: Совсем нет/Not at all | KV16: Немного / A little | KZ16: Немного / A little | LC16: Совсем нет / Not at all | LH16: Немного / A little | LL16: Немного / A little | LO16: Совсем нет / Not at all | LT16: Немного / A little | LW16: Совсем нет / Not at all | MA16: Совсем нет / Not at all | MG16: Довольно сильно / Quite a bit | ML16: Очень сильно / Extremely | MO16: Довольно сильно / Quite a bit | MQ16: Совсем нет / Not at all | MU16: Совсем нет / Not at all | MZ16: Немного / A little | NF16: Очень сильно / Extremely | NH16: Немного / A little | NL16: Немного / A little | NQ16: Довольно сильно / Quite a bit | NS16: Совсем нет / Not at all | NW16: Совсем нет / Not at all | OB16: Немного / A little | OG16: Довольно сильно / Quite a bit | OK16: Довольно сильно / Quite a bit
A17: FG001 | B17: Да / Yes | D17: Да / Yes | F17: Да / Yes | I17: Мужской / Male | L17: 18-24 | S17: Человек | T17: English, Norsk, Русский, немного Espanol | U17: Курск | V17: Ереван, Армения | AB17: Никогда не был женат (замужем) / Single, never married | AE17: Нет / No | AH17: Нет / No | AL17: Незаконченное высшее / Some college | AT17: Выше среднего / Above average | AU17: Потому что 6 мая меня задержали и пытали русские спецслужбы, затем посадили в тюрьму за то что я запостил украинские новости в соц.сети, 3 месяца я провел в холодной сырой одиночно камере с крысами и тараканами, а когда вышел меня начало преследовать ФСБ. | AW17: Скорее согласен / Moderately agree | BC17: Полностью не согласен / Strongly disagree | BD17: Полностью согласен / Strongly agree | BH17: Полностью согласен / Strongly agree | BL17: Полностью согласен / Strongly agree | BS17: Полностью не согласен / Strongly disagree | BU17: Скорее согласен / Moderately agree | BX17: Полностью согласен / Strongly agree | CB17: Полностью согласен / Strongly agree | CF17: Полностью согласен / Strongly agree | CJ17: Полностью согласен / Strongly agree | CN17: Полностью согласен / Strongly agree | CS17: Скорее согласен / Moderately agree | CY17: Полностью не согласен / Strongly disagree | DC17: Полностью не согласен / Strongly disagree | DG17: Полностью не согласен / Strongly disagree | DI17: Скорее согласен / Moderately agree | DL17: Полностью согласен / Strongly agree | DP17: Полностью согласен / Strongly agree | DT17: Полностью согласен / Strongly agree | DZ17: Скорее не согласен / Moderately disagree | EC17: Скорее согласен / Moderately agree | EI17: Полностью не согласен / Strongly disagree | EM17: Полностью не согласен / Strongly disagree | EQ17: Полностью не согласен / Strongly disagree | ER17: Полностью согласен / Strongly agree | EY17: Полностью не согласен / Strongly disagree | EZ17: Полностью согласен / Strongly agree | FD17: Полностью согласен / Strongly agree | FJ17: Скорее не согласен / Moderately disagree | FL17: Полностью согласен / Strongly agree | FP17: Да / Yes | FR17: Да / Yes | FT17: Да / Yes | FV17: Да / Yes | FX17: Да / Yes | GA17: Нет / No | GC17: Нет / No | GD17: Да / Yes | GG17: Нет / No | GH17: Да / Yes | GK17: Нет / No | GM17: Нет / No | GO17: Нет / No | GQ17: Нет / No | GS17: Нет / No | GU17: Нет / No | GV17: Да / Yes | GX17: Тюремное заключение, Пытки спецслужб | GZ17: Немного/A little | HD17: Немного/A little | HG17: Совсем нет/Not at all | HM17: Довольно сильно/Quite a bit | HQ17: Довольно сильно/Quite a bit | HU17: Довольно сильно/Quite a bit | HZ17: Очень сильно/Extremely | ID17: Очень сильно/Extremely | IG17: Довольно сильно/Quite a bit | IL17: Очень сильно/Extremely | IO17: Довольно сильно/Quite a bit | IQ17: Совсем нет/Not at all | IV17: Немного/A little | JB17: Очень сильно/Extremely | JC17: Совсем нет/Not at all | JG17: Совсем нет/Not at all | JL17: Немного/A little | JR17: Очень сильно/Extremely | JU17: Довольно сильно/Quite a bit | JY17: Довольно сильно/Quite a bit | KD17: Очень сильно/Extremely | KH17: Очень сильно/Extremely | KL17: Очень сильно/Extremely | KM17: Совсем нет/Not at all | KQ17: Совсем нет/Not at all
A18: GR001 | B18: Да / Yes | D18: Да / Yes | F18: Да / Yes | J18: Небинарный / Non-binary | L18: 18-24 | S18: Космополит, с точки зрения документов - Русский. | T18: Русский, плохой английский. | U18: Курск, Курская область. | V18: Тбилиси, Грузия | AB18: Никогда не был женат (замужем) / Single, never married | AE18: Нет / No | AH18: Нет / No | AK18: Среднее образование / High school graduate | AR18: Ниже среднего / Below average | AU18: Я ненавижу политику этой страны, Кремль и Путина - практически всю свою жизнь, и могу объяснить почему. Давно хотела уехать, но останавливал финансовый вопрос. Однако, ко мне пришло ФСБ, из за того что я помогла сидевшему по политике парню с пропиской, и конфисковало мою технику с помощью которой я много лет выражала свои взгляды. И теперь мне, скорее всего, грозит тюремный срок. Так что оставаться там уже не представлялось возможным, и моя мама, взяв наши семейные накопления и брата, которому грозит мобилизация - уехала вместе со мной в Грузию. | AX18: Скорее не согласен / Moderately disagree | BC18: Полностью не согласен / Strongly disagree | BF18: Скорее не согласен / Moderately disagree | BK18: Полностью не согласен / Strongly disagree | BN18: Скорее не согласен / Moderately disagree | BS18: Полностью не согласен / Strongly disagree | BW18: Полностью не согласен / Strongly disagree | BZ18: Скорее не согласен / Moderately disagree | CC18: Скорее согласен / Moderately agree | CH18: Скорее не согласен / Moderately disagree | CM18: Полностью не согласен / Strongly disagree | CO18: Скорее согласен / Moderately agree | CT18: Скорее не согласен / Moderately disagree | CY18: Полностью не согласен / Strongly disagree | DC18: Полностью не согласен / Strongly disagree | DG18: Полностью не согласен / Strongly disagree | DI18: Скорее согласен / Moderately agree | DM18: Скорее согласен / Moderately agree | DQ18: Скорее согласен / Moderately agree | DU18: Скорее согласен / Moderately agree | EA18: Полностью не согласен / Strongly disagree | EE18: Полностью не согласен / Strongly disagree | EI18: Полностью не согласен / Strongly disagree | EM18: Полностью не согласен / Strongly disagree | EP18: Скорее не согласен / Moderately disagree | ES18: Скорее согласен / Moderately agree | EW18: Скорее согласен / Moderately agree | FC18: Полностью не согласен / Strongly disagree | FE18: Скорее согласен / Moderately agree | FK18: Полностью не согласен / Strongly disagree | FL18: Полностью согласен / Strongly agree | FQ18: Нет / No | FS18: Нет / No | FU18: Нет / No | FV18: Да / Yes | FY18: Нет / No | GA18: Нет / No | GB18: Да / Yes | GD18: Да / Yes | GG18: Нет / No | GH18: Да / Yes | GK18: Нет / No | GM18: Нет / No | GO18: Нет / No | GQ18: Нет / No | GS18: Нет / No | GU18: Нет / No | GW18: Нет / No | GX18: Ну, меня с начала МВД задержало, а потом ФСБ пришло и конфисковало вещи. НУ и мой бывший парень сидел, и его пытали. И я думала что он сядет лет на 10, но ему повезло. Однако, преследования в Курке были ни за что. + В России я постоянно чувствовала что моей жизни угрожает опасность. По разным причинам. Я ЛГБТ, у меня - антиправительственные взгляды. А мой город - на границе с Украиной, и у нас после 23 февраля начался кошмар, похожий на сериал или фильм про нацистскую Германию. | GZ18: Немного/A little | HD18: Немного/A little | HG18: Совсем нет/Not at all | HL18: Немного/A little | HO18: Совсем нет/Not at all | HT18: Немного/A little | HX18: Немного/A little | IA18: Совсем нет/Not at all | IF18: Немного/A little | II18: Совсем нет/Not at all | IM18: Совсем нет/Not at all | IQ18: Совсем нет/Not at all | IV18: Немного/A little | JA18: Довольно сильно/Quite a bit | JC18: Совсем нет/Not at all | JG18: Совсем нет/Not at all | JM18: Довольно сильно/Quite a bit | JQ18: Довольно сильно/Quite a bit | JS18: Совсем нет/Not at all | JW18: Совсем нет/Not at all | KB18: Немного/A little | KE18: Совсем нет/Not at all | KL18: Очень сильно/Extremely | KM18: Совсем нет/Not at all | KR18: Немного/A little | KV18: Немного / A little | KY18: Совсем нет / Not at all | LC18: Совсем нет / Not at all | LH18: Немного / A little | LL18: Немного / A little | LP18: Немного / A little | LT18: Немного / A little | LX18: Немного / A little | MA18: Совсем нет / Not at all | MF18: Немного / A little | MK18: Довольно сильно / Quite a bit | MM18: Совсем нет / Not at all | MQ18: Совсем нет / Not at all | MU18: Совсем нет / Not at all | MY18: Совсем нет / Not at all | NC18: Совсем нет / Not at all | NH18: Немного / A little | NL18: Немного / A little | NO18: Совсем нет / Not at all | NS18: Совсем нет / Not at all | NW18: Совсем нет / Not at all | OB18: Немного / A little | OG18: Довольно сильно / Quite a bit | OK18: Довольно сильно / Quite a bit
A19: TB001 | B19: Да / Yes | D19: Да / Yes | F19: Да / Yes | I19: Мужской / Male | O19: 45-54 | S19: Татарин | T19: Русский | U19: г. Санкт-Петербург | V19: Грузия, регион Аджария, село Квариати (пригород г. Батуми) | AA19: Гражданский брак / Cohabiting with a significant other or in a domestic partnership | AE19: Нет / No | AG19: Да / Yes | AI19: 1 | AN19: Высшее образование (специалист) / 5 years of college | AS19: Средний / Average | AU19: Страх попасть на войну из-за мобилизации. | AW19: Скорее согласен / Moderately agree | BA19: Скорее согласен / Moderately agree | BG19: Полностью не согласен / Strongly disagree | BJ19: Скорее не согласен / Moderately disagree | BN19: Скорее не согласен / Moderately disagree | BU19: Скорее согласен / Moderately agree | BY19: Скорее согласен / Moderately agree | CE19: Полностью не согласен / Strongly disagree | CI19: Полностью не согласен / Strongly disagree | CL19: Скорее не согласен / Moderately disagree | CN19: Полностью согласен / Strongly agree | CU19: Полностью не согласен / Strongly disagree | CW19: Скорее согласен / Moderately agree | DA19: Скорее согласен / Moderately agree | DE19: Скорее согласен / Moderately agree | DJ19: Скорее не согласен / Moderately disagree | DO19: Полностью не согласен / Strongly disagree | DS19: Полностью не согласен / Strongly disagree | DW19: Полностью не согласен / Strongly disagree | EA19: Полностью не согласен / Strongly disagree | EB19: Полностью согласен / Strongly agree | EH19: Скорее не согласен / Moderately disagree | EM19: Полностью не согласен / Strongly disagree | EQ19: Полностью не согласен / Strongly disagree | EX19: Скорее не согласен / Moderately disagree | FB19: Скорее не согласен / Moderately disagree | FF19: Скорее не согласен / Moderately disagree | FI19: Скорее согласен / Moderately agree | FO19: Полностью не согласен / Strongly disagree | FQ19: Нет / No | FS19: Нет / No | FU19: Нет / No | FW19: Нет / No | FY19: Нет / No | GA19: Нет / No | GC19: Нет / No | GE19: Нет / No | GG19: Нет / No | GI19: Нет / No | GJ19: Да / Yes | GM19: Нет / No | GO19: Нет / No | GQ19: Нет / No | GS19: Нет / No | GU19: Нет / No | GW19: Нет / No | GY19: Совсем нет/Not at all | HC19: Совсем нет/Not at all | HG19: Совсем нет/Not at all | HL19: Немного/A little | HP19: Немного/A little | HS19: Совсем нет/Not at all | HW19: Совсем нет/Not at all | IB19: Немного/A little | IF19: Немного/A little | IJ19: Немного/A little | IM19: Совсем нет/Not at all | IQ19: Совсем нет/Not at all | IV19: Немного/A little | IZ19: Немного/A little | JC19: Совсем нет/Not at all | JG19: Совсем нет/Not at all | JL19: Немного/A little | JO19: Совсем нет/Not at all | JT19: Немного/A little | JW19: Совсем нет/Not at all | KB19: Немного/A little | KE19: Совсем нет/Not at all | KI19: Совсем нет/Not at all | KM19: Совсем нет/Not at all | KQ19: Совсем нет/Not at all | KV19: Немного / A little | KZ19: Немного / A little | LC19: Совсем нет / Not at all | LG19: Совсем нет / Not at all | LK19: Совсем нет / Not at all | LO19: Совсем нет / Not at all | LT19: Немного / A little | LW19: Совсем нет / Not at all | MA19: Совсем нет / Not at all | ME19: Совсем нет / Not at all | MJ19: Немного / A little | MN19: Немного / A little | MQ19: Совсем нет / Not at all | MV19: Немного / A little | MY19: Совсем нет / Not at all | ND19: Немного / A little | NG19: Совсем нет / Not at all | NK19: Совсем нет / Not at all | NP19: Немного / A little | NU19: Довольно сильно / Quite a bit | NW19: Совсем нет / Not at all | OA19: Совсем нет / Not at all | OE19: Совсем нет / Not at all | OI19: Совсем нет / Not at all
A20: VI001 | B20: Да / Yes | D20: Да / Yes | F20: Да / Yes | H20: Женский / Female | M20: 25-34 | R20: Русский(ая) / Russian | T20: Русский, английский, французский | U20: Москва | V20: Тбилиси | W20: Женат (замужем) / Married | AD20: Да / Yes | AF20: 2 | AH20: Нет / No | AI20: Нет | AN20: Высшее образование (специалист) / 5 years of college | AS20: Средний / Average | AU20: Война, мобилизация, новые законы, «патриотическое воспитание» в школе | AY20: Полностью не согласен / Strongly disagree | BA20: Скорее согласен / Moderately agree | BD20: Полностью согласен / Strongly agree | BJ20: Скорее не согласен / Moderately disagree | BM20: Скорее согласен / Moderately agree | BQ20: Скорее согласен / Moderately agree | BW20: Полностью не согласен / Strongly disagree | BZ20: Скорее не согласен / Moderately disagree | CD20: Скорее не согласен / Moderately disagree | CH20: Скорее не согласен / Moderately disagree | CK20: Скорее согласен / Moderately agree | CN20: Полностью согласен / Strongly agree | CU20: Полностью не согласен / Strongly disagree | CV20: Полностью согласен / Strongly agree | DA20: Скорее согласен / Moderately agree | DD20: Полностью согласен / Strongly agree | DH20: Полностью согласен / Strongly agree | DL20: Полностью согласен / Strongly agree | DQ20: Скорее согласен / Moderately agree | DV20: Скорее не согласен / Moderately disagree | DZ20: Скорее не согласен / Moderately disagree | ED20: Скорее не согласен / Moderately disagree | EI20: Полностью не согласен / Strongly disagree | EM20: Полностью не согласен / Strongly disagree | EQ20: Полностью не согласен / Strongly disagree | EU20: Полностью не согласен / Strongly disagree | EW20: Скорее согласен / Moderately agree | FB20: Скорее не согласен / Moderately disagree | FF20: Скорее не согласен / Moderately disagree | FH20: Полностью согласен / Strongly agree | FN20: Скорее не согласен / Moderately disagree | FQ20: Нет / No | FR20: Да / Yes | FU20: Нет / No | FW20: Нет / No | FY20: Нет / No | GA20: Нет / No | GC20: Нет / No | GE20: Нет / No | GG20: Нет / No | GH20: Да / Yes | GJ20: Да / Yes | GM20: Нет / No | GO20: Нет / No | GQ20: Нет / No | GS20: Нет / No | GU20: Нет / No | GW20: Нет / No | GY20: Совсем нет/Not at all | HC20: Совсем нет/Not at all | HG20: Совсем нет/Not at all | HK20: Совсем нет/Not at all | HQ20: Довольно сильно/Quite a bit | HT20: Немного/A little | HY20: Довольно сильно/Quite a bit | IB20: Немного/A little | IF20: Немного/A little | IK20: Довольно сильно/Quite a bit | IM20: Совсем нет/Not at all | IQ20: Совсем нет/Not at all | IX20: Очень сильно/Extremely | JB20: Очень сильно/Extremely | JD20: Немного/A little | JG20: Совсем нет/Not at all | JL20: Немного/A little | JP20: Немного/A little | JS20: Совсем нет/Not at all | JW20: Совсем нет/Not at all | KB20: Немного/A little | KE20: Совсем нет/Not at all | KI20: Совсем нет/Not at all | KM20: Совсем нет/Not at all | KQ20: Совсем нет/Not at all | KU20: Совсем нет / Not at all | KZ20: Немного / A little | LD20: Немного / A little | LH20: Немного / A little | LK20: Совсем нет / Not at all | LO20: Совсем нет / Not at all | LU20: Довольно сильно / Quite a bit | LY20: Довольно сильно / Quite a bit | MA20: Совсем нет / Not at all | MG20: Довольно сильно / Quite a bit | ML20: Очень сильно / Extremely | MN20: Немного / A little | MQ20: Совсем нет / Not at all | MU20: Совсем нет / Not at all | MY20: Совсем нет / Not at all | ND20: Немного / A little | NJ20: Очень сильно / Extremely | NM20: Довольно сильно / Quite a bit | NO20: Совсем нет / Not at all | NT20: Немного / A little | NX20: Немного / A little | OC20: Довольно сильно / Quite a bit | OH20: Очень сильно / Extremely | OK20: Довольно сильно / Quite a bit
A21: ID MT002 | B21: Да / Yes | D21: Да / Yes | F21: Да / Yes | H21: Женский / Female | N21: 35-44 | S21: Еврейка | T21: Русский, английский, понимаю французский | U21: Москва | V21: Тбилиси | Y21: В разводе / Divorced | AD21: Да / Yes | AF21: 2 | AH21: Нет / No | AN21: Высшее образование (специалист) / 5 years of college | AS21: Средний / Average | AU21: Я боялась, что в РОссии введут военное положение и закроют границы, и мои дети и я тоже окажемся заперты. | AY21: Полностью не согласен / Strongly disagree | BA21: Скорее согласен / Moderately agree | BG21: Полностью не согласен / Strongly disagree | BI21: Скорее согласен / Moderately agree | BM21: Скорее согласен / Moderately agree | BR21: Скорее не согласен / Moderately disagree | BV21: Скорее не согласен / Moderately disagree | BY21: Скорее согласен / Moderately agree | CC21: Скорее согласен / Moderately agree | CH21: Скорее не согласен / Moderately disagree | CL21: Скорее не согласен / Moderately disagree | CO21: Скорее согласен / Moderately agree | CU21: Полностью не согласен / Strongly disagree | CW21: Скорее согласен / Moderately agree | DA21: Скорее согласен / Moderately agree | DE21: Скорее согласен / Moderately agree | DH21: Полностью согласен / Strongly agree | DM21: Скорее согласен / Moderately agree | DQ21: Скорее согласен / Moderately agree | DV21: Скорее не согласен / Moderately disagree | EA21: Полностью не согласен / Strongly disagree | ED21: Скорее не согласен / Moderately disagree | EH21: Скорее не согласен / Moderately disagree | EM21: Полностью не согласен / Strongly disagree | EQ21: Полностью не согласен / Strongly disagree | EU21: Полностью не согласен / Strongly disagree | EW21: Скорее согласен / Moderately agree | FC21: Полностью не согласен / Strongly disagree | FF21: Скорее не согласен / Moderately disagree | FH21: Полностью согласен / Strongly agree | FN21: Скорее не согласен / Moderately disagree | FQ21: Нет / No | FS21: Нет / No | FU21: Нет / No | FW21: Нет / No | FY21: Нет / No | GA21: Нет / No | GB21: Да / Yes | GE21: Нет / No | GG21: Нет / No | GI21: Нет / No | GJ21: Да / Yes | GM21: Нет / No | GO21: Нет / No | GQ21: Нет / No | GS21: Нет / No | GU21: Нет / No | GW21: Нет / No | GY21: Совсем нет/Not at all | HD21: Немного/A little | HG21: Совсем нет/Not at all | HM21: Довольно сильно/Quite a bit | HQ21: Довольно сильно/Quite a bit | HS21: Совсем нет/Not at all | HY21: Довольно сильно/Quite a bit | IB21: Немного/A little | IF21: Немного/A little | IJ21: Немного/A little | IM21: Совсем нет/Not at all | IQ21: Совсем нет/Not at all | IV21: Немного/A little | IZ21: Немного/A little | JC21: Совсем нет/Not at all | JG21: Совсем нет/Not at all | JM21: Довольно сильно/Quite a bit | JQ21: Довольно сильно/Quite a bit | JS21: Совсем нет/Not at all | JW21: Совсем нет/Not at all | KC21: Довольно сильно/Quite a bit | KE21: Совсем нет/Not at all | KI21: Совсем нет/Not at all | KM21: Совсем нет/Not at all | KQ21: Совсем нет/Not at all | KU21: Совсем нет / Not at all | KZ21: Немного / A little | LD21: Немного / A little | LH21: Немного / A little | LK21: Совсем нет / Not at all | LO21: Совсем нет / Not at all | LU21: Довольно сильно / Quite a bit | LY21: Довольно сильно / Quite a bit | MA21: Совсем нет / Not at all | MF21: Немного / A little | MK21: Довольно сильно / Quite a bit | MO21: Довольно сильно / Quite a bit | MQ21: Совсем нет / Not at all | MV21: Немного / A little | MY21: Совсем нет / Not at all | ND21: Немного / A little | NH21: Немного / A little | NL21: Немного / A little | NQ21: Довольно сильно / Quite a bit | NT21: Немного / A little | NY21: Довольно сильно / Quite a bit | OB21: Немного / A little | OF21: Немного / A little | OK21: Довольно сильно / Quite a bit
A22: TI001 | B22: Да / Yes | D22: Да / Yes | F22: Да / Yes | H22: Женский / Female | M22: 25-34 | S22: Татарка | T22: русский | U22: Тольятти, Самарская область | V22: Тбилиси, Грузия | AB22: Никогда не был женат (замужем) / Single, never married | AE22: Нет / No | AF22: Нет | AH22: Нет / No | AI22: Нет | AN22: Высшее образование (специалист) / 5 years of college | AR22: Ниже среднего / Below average | AU22: Нет желания жить в России, не согласна с внешней и внутренней политикой государства | AX22: Скорее не согласен / Moderately disagree | BB22: Скорее не согласен / Moderately disagree | BF22: Скорее не согласен / Moderately disagree | BI22: Скорее согласен / Moderately agree | BN22: Скорее не согласен / Moderately disagree | BR22: Скорее не согласен / Moderately disagree | BT22: Полностью согласен / Strongly agree | BY22: Скорее согласен / Moderately agree | CC22: Скорее согласен / Moderately agree | CH22: Скорее не согласен / Moderately disagree | CK22: Скорее согласен / Moderately agree | CN22: Полностью согласен / Strongly agree | CR22: Полностью согласен / Strongly agree | CW22: Скорее согласен / Moderately agree | DB22: Скорее не согласен / Moderately disagree | DD22: Полностью согласен / Strongly agree | DH22: Полностью согласен / Strongly agree | DN22: Скорее не согласен / Moderately disagree | DP22: Полностью согласен / Strongly agree | DT22: Полностью согласен / Strongly agree | EA22: Полностью не согласен / Strongly disagree | ED22: Скорее не согласен / Moderately disagree | EI22: Полностью не согласен / Strongly disagree | EK22: Скорее согласен / Moderately agree | EP22: Скорее не согласен / Moderately disagree | ET22: Скорее не согласен / Moderately disagree | FB22: Скорее не согласен / Moderately disagree | FE22: Скорее согласен / Moderately agree | FH22: Полностью согласен / Strongly agree | FM22: Скорее согласен / Moderately agree | FP22: Да / Yes | FS22: Нет / No | FT22: Да / Yes | FW22: Нет / No | FY22: Нет / No | GA22: Нет / No | GC22: Нет / No | GE22: Нет / No | GG22: Нет / No | GI22: Нет / No | GK22: Нет / No | GM22: Нет / No | GO22: Нет / No | GQ22: Нет / No | GS22: Нет / No | GU22: Нет / No | GW22: Нет / No | GX22: У меня не было ситуаций, которые угрожали моей жизни. Скорее психологическое давление от окружающих, что я не согласна с политикой страны | GZ22: Немного/A little | HC22: Совсем нет/Not at all | HG22: Совсем нет/Not at all | HN22: Очень сильно/Extremely | HO22: Совсем нет/Not at all | HU22: Довольно сильно/Quite a bit | HZ22: Очень сильно/Extremely | ID22: Очень сильно/Extremely | IH22: Очень сильно/Extremely | IL22: Очень сильно/Extremely | IQ22: Совсем нет/Not at all | IV22: Немного/A little | JA22: Довольно сильно/Quite a bit | JD22: Немного/A little | JH22: Немного/A little | JM22: Довольно сильно/Quite a bit | JP22: Немного/A little | JU22: Довольно сильно/Quite a bit | JZ22: Очень сильно/Extremely | KD22: Очень сильно/Extremely | KE22: Совсем нет/Not at all | KK22: Довольно сильно/Quite a bit | KM22: Совсем нет/Not at all | KR22: Немного/A little | KV22: Немного / A little | LA22: Довольно сильно / Quite a bit | LD22: Немного / A little | LH22: Немного / A little | LL22: Немного / A little | LO22: Совсем нет / Not at all | LT22: Немного / A little | LX22: Немного / A little | MB22: Немного / A little | MG22: Довольно сильно / Quite a bit | ML22: Очень сильно / Extremely | MO22: Довольно сильно / Quite a bit | MT22: Очень сильно / Extremely | MV22: Немного / A little | MZ22: Немного / A little | NF22: Очень сильно / Extremely | NI22: Довольно сильно / Quite a bit | NN22: Очень сильно / Extremely | NR22: Очень сильно / Extremely | NU22: Довольно сильно / Quite a bit | NZ22: Очень сильно / Extremely | OB22: Немного / A little | OG22: Довольно сильно / Quite a bit | OJ22: Немного / A little
A23: TK001 | B23: Да / Yes | D23: Да / Yes | F23: Да / Yes | I23: Мужской / Male | M23: 25-34 | R23: Русский(ая) / Russian | T23: русский, английский, иврит | U23: Санкт-Петербург | V23: Тбилиси | W23: Женат (замужем) / Married | AE23: Нет / No | AF23: 0 | AG23: Да / Yes | AI23: 1 | AN23: Высшее образование (специалист) / 5 years of college | AT23: Выше среднего / Above average | AU23: Не вижу перспектив в России, не доволен российскими законами, политикой | AX23: Скорее не согласен / Moderately disagree | BB23: Скорее не согласен / Moderately disagree | BF23: Скорее не согласен / Moderately disagree | BI23: Скорее согласен / Moderately agree | BN23: Скорее не согласен / Moderately disagree | BR23: Скорее не согласен / Moderately disagree | BU23: Скорее согласен / Moderately agree | BX23: Полностью согласен / Strongly agree | CC23: Скорее согласен / Moderately agree | CG23: Скорее согласен / Moderately agree | CM23: Полностью не согласен / Strongly disagree | CO23: Скорее согласен / Moderately agree | CT23: Скорее не согласен / Moderately disagree | CY23: Полностью не согласен / Strongly disagree | DC23: Полностью не согласен / Strongly disagree | DG23: Полностью не согласен / Strongly disagree | DI23: Скорее согласен / Moderately agree | DL23: Полностью согласен / Strongly agree | DR23: Скорее не согласен / Moderately disagree | DW23: Полностью не согласен / Strongly disagree | EA23: Полностью не согласен / Strongly disagree | ED23: Скорее не согласен / Moderately disagree | EI23: Полностью не согласен / Strongly disagree | EM23: Полностью не согласен / Strongly disagree | EP23: Скорее не согласен / Moderately disagree | ER23: Полностью согласен / Strongly agree | EX23: Скорее не согласен / Moderately disagree | FB23: Скорее не согласен / Moderately disagree | FF23: Скорее не согласен / Moderately disagree | FI23: Скорее согласен / Moderately agree | FM23: Скорее согласен / Moderately agree | FQ23: Нет / No | FS23: Нет / No | FU23: Нет / No | FW23: Нет / No | FY23: Нет / No | GA23: Нет / No | GC23: Нет / No | GE23: Нет / No | GG23: Нет / No | GI23: Нет / No | GK23: Нет / No | GM23: Нет / No | GO23: Нет / No | GQ23: Нет / No | GS23: Нет / No | GU23: Нет / No | GW23: Нет / No | GZ23: Немного/A little | HD23: Немного/A little | HG23: Совсем нет/Not at all | HM23: Довольно сильно/Quite a bit | HR23: Очень сильно/Extremely | HU23: Довольно сильно/Quite a bit | HX23: Немного/A little | ID23: Очень сильно/Extremely | IH23: Очень сильно/Extremely | IL23: Очень сильно/Extremely | IM23: Совсем нет/Not at all | IQ23: Совсем нет/Not at all | IV23: Немного/A little | JA23: Довольно сильно/Quite a bit | JC23: Совсем нет/Not at all | JG23: Совсем нет/Not at all | JM23: Довольно сильно/Quite a bit | JO23: Совсем нет/Not at all | JS23: Совсем нет/Not at all | JX23: Немного/A little | KC23: Довольно сильно/Quite a bit | KF23: Немного/A little | KJ23: Немного/A little | KM23: Совсем нет/Not at all | KQ23: Совсем нет/Not at all | KU23: Совсем нет / Not at all | KZ23: Немного / A little | LC23: Совсем нет / Not at all | LH23: Немного / A little | LK23: Совсем нет / Not at all | LO23: Совсем нет / Not at all | LS23: Совсем нет / Not at all | LX23: Немного / A little | MA23: Совсем нет / Not at all | ME23: Совсем нет / Not at all | MJ23: Немного / A little | MM23: Совсем нет / Not at all | MQ23: Совсем нет / Not at all | MW23: Довольно сильно / Quite a bit | MZ23: Немного / A little | NF23: Очень сильно / Extremely | NI23: Довольно сильно / Quite a bit | NM23: Довольно сильно / Quite a bit | NQ23: Довольно сильно / Quite a bit | NS23: Совсем нет / Not at all | NX23: Немного / A little | OC23: Довольно сильно / Quite a bit | OG23: Довольно сильно / Quite a bit | OJ23: Немного / A little
A24: PG001 | B24: Да / Yes | D24: Да / Yes | F24: Да / Yes | H24: Женский / Female | N24: 35-44 | R24: Русский(ая) / Russian | T24: Русский (родной), английский | U24: Архангельск | V24: Ереван | W24: Женат (замужем) / Married | AD24: Да / Yes | AF24: 1 | AG24: Да / Yes | AI24: 1 | AN24: Высшее образование (специалист) / 5 years of college | AS24: Средний / Average | AU24: Задержали два раза в марте, и невозможно там было находиться - везде полиция, буквы зед на адмтнистративных зданиях. И сказать ничего нельзя, и молчать невыносимо | AY24: Полностью не согласен / Strongly disagree | BC24: Полностью не согласен / Strongly disagree | BG24: Полностью не согласен / Strongly disagree | BJ24: Скорее не согласен / Moderately disagree | BM24: Скорее согласен / Moderately agree | BS24: Полностью не согласен / Strongly disagree | BV24: Скорее не согласен / Moderately disagree | BZ24: Скорее не согласен / Moderately disagree | CD24: Скорее не согласен / Moderately disagree | CI24: Полностью не согласен / Strongly disagree | CL24: Скорее не согласен / Moderately disagree | CP24: Скорее не согласен / Moderately disagree | CS24: Скорее согласен / Moderately agree | CV24: Полностью согласен / Strongly agree | DA24: Скорее согласен / Moderately agree | DD24: Полностью согласен / Strongly agree | DI24: Скорее согласен / Moderately agree | DN24: Скорее не согласен / Moderately disagree | DQ24: Скорее согласен / Moderately agree | DU24: Скорее согласен / Moderately agree | EA24: Полностью не согласен / Strongly disagree | ED24: Скорее не согласен / Moderately disagree | EI24: Полностью не согласен / Strongly disagree | EM24: Полностью не согласен / Strongly disagree | EQ24: Полностью не согласен / Strongly disagree | ES24: Скорее согласен / Moderately agree | EW24: Скорее согласен / Moderately agree | FC24: Полностью не согласен / Strongly disagree | FG24: Полностью не согласен / Strongly disagree | FJ24: Скорее не согласен / Moderately disagree | FN24: Скорее не согласен / Moderately disagree | FP24: Да / Yes | FS24: Нет / No | FU24: Нет / No | FV24: Да / Yes | FX24: Да / Yes | GA24: Нет / No | GC24: Нет / No | GD24: Да / Yes | GG24: Нет / No | GH24: Да / Yes | GJ24: Да / Yes | GL24: Да / Yes | GN24: Да / Yes | GQ24: Нет / No | GS24: Нет / No | GU24: Нет / No | GW24: Нет / No | GX24: Задержания полицейскими, обыски. Страх, что закроют границу. Страх потерять близких на войне. Ужас от того, что войну многие поддерживают среди моих знакомых. | HA24: Довольно сильно/Quite a bit | HC24: Совсем нет/Not at all | HI24: Довольно сильно/Quite a bit | HK24: Совсем нет/Not at all | HO24: Совсем нет/Not at all | HU24: Довольно сильно/Quite a bit | HY24: Довольно сильно/Quite a bit | IC24: Довольно сильно/Quite a bit | IG24: Довольно сильно/Quite a bit | IK24: Довольно сильно/Quite a bit | IO24: Довольно сильно/Quite a bit | IQ24: Совсем нет/Not at all | IU24: Совсем нет/Not at all | IY24: Совсем нет/Not at all | JD24: Немного/A little | JI24: Довольно сильно/Quite a bit | JL24: Немного/A little | JO24: Совсем нет/Not at all | JS24: Совсем нет/Not at all | JY24: Довольно сильно/Quite a bit | KA24: Совсем нет/Not at all | KE24: Совсем нет/Not at all | KJ24: Немного/A little | KM24: Совсем нет/Not at all | KQ24: Совсем нет/Not at all | KV24: Немного / A little | KZ24: Немного / A little | LC24: Совсем нет / Not at all | LH24: Немного / A little | LL24: Немного / A little | LO24: Совсем нет / Not at all | LU24: Довольно сильно / Quite a bit | LX24: Немного / A little | MA24: Совсем нет / Not at all | MF24: Немного / A little | MK24: Довольно сильно / Quite a bit | MO24: Довольно сильно / Quite a bit | MS24: Довольно сильно / Quite a bit | MV24: Немного / A little | MY24: Совсем нет / Not at all | NE24: Довольно сильно / Quite a bit | NI24: Довольно сильно / Quite a bit | NM24: Довольно сильно / Quite a bit | NP24: Немного / A little | NU24: Довольно сильно / Quite a bit | NY24: Довольно сильно / Quite a bit | OA24: Совсем нет / Not at all | OF24: Немного / A little | OJ24: Немного / A little
A25: CV001 | B25: Да / Yes | D25: Да / Yes | F25: Да / Yes | H25: Женский / Female | M25: 25-34 | R25: Русский(ая) / Russian | T25: Русский, английский (B1) | U25: Красноярск | V25: Тбилиси, Грузия | W25: Женат (замужем) / Married | AE25: Нет / No | AH25: Нет / No | AM25: Высшее образование (бакалавриат) / Bachelor’s Degree | AR25: Ниже среднего / Below average | AU25: Было невыносимо оставаться в РФ. Нет чувства безопасности, возможность сесть в тюрьму за высказывание мнения. Внутреннее желание не находиться близко с поддерживающими войну людьми. | AY25: Полностью не согласен / Strongly disagree | BB25: Скорее не согласен / Moderately disagree | BD25: Полностью согласен / Strongly agree | BJ25: Скорее не согласен / Moderately disagree | BM25: Скорее согласен / Moderately agree | BS25: Полностью не согласен / Strongly disagree | BW25: Полностью не согласен / Strongly disagree | BX25: Полностью согласен / Strongly agree | CD25: Скорее не согласен / Moderately disagree | CF25: Полностью согласен / Strongly agree | CJ25: Полностью согласен / Strongly agree | CO25: Скорее согласен / Moderately agree | CS25: Скорее согласен / Moderately agree | CY25: Полностью не согласен / Strongly disagree | DC25: Полностью не согласен / Strongly disagree | DE25: Скорее согласен / Moderately agree | DH25: Полностью согласен / Strongly agree | DL25: Полностью согласен / Strongly agree | DP25: Полностью согласен / Strongly agree | DV25: Скорее не согласен / Moderately disagree | EA25: Полностью не согласен / Strongly disagree | EB25: Полностью согласен / Strongly agree | EI25: Полностью не согласен / Strongly disagree | EK25: Скорее согласен / Moderately agree | EO25: Скорее согласен / Moderately agree | EU25: Полностью не согласен / Strongly disagree | EX25: Скорее не согласен / Moderately disagree | EZ25: Полностью согласен / Strongly agree | FD25: Полностью согласен / Strongly agree | FJ25: Скорее не согласен / Moderately disagree | FL25: Полностью согласен / Strongly agree | FP25: Да / Yes | FS25: Нет / No | FT25: Да / Yes | FW25: Нет / No | FY25: Нет / No | GA25: Нет / No | GC25: Нет / No | GE25: Нет / No | GG25: Нет / No | GI25: Нет / No | GK25: Нет / No | GM25: Нет / No | GO25: Нет / No | GQ25: Нет / No | GS25: Нет / No | GU25: Нет / No | GW25: Нет / No | GX25: Угрозы вызова полиции за антивоенную позицию (в рф) Дополнительные вопросы при пересечении границы Армения - Грузия, потому что из IT сферы Страх, что при визаране Грузия - Армения - Грузия не пустят обратно в страну, потому что есть прецеденты с антивоенными активистами Новость о мобилизации в рф и помощь друзьям и членам семьи выехать из страны. | GY25: Совсем нет/Not at all | HC25: Совсем нет/Not at all | HG25: Совсем нет/Not at all | HL25: Немного/A little | HO25: Совсем нет/Not at all | HT25: Немного/A little | HY25: Довольно сильно/Quite a bit | IA25: Совсем нет/Not at all | IE25: Совсем нет/Not at all | IJ25: Немного/A little | IO25: Довольно сильно/Quite a bit | IQ25: Совсем нет/Not at all | IV25: Немного/A little | IY25: Совсем нет/Not at all | JD25: Немного/A little | JJ25: Очень сильно/Extremely | JK25: Совсем нет/Not at all | JO25: Совсем нет/Not at all | JS25: Совсем нет/Not at all | JX25: Немного/A little | KA25: Совсем нет/Not at all | KF25: Немного/A little | KK25: Довольно сильно/Quite a bit | KM25: Совсем нет/Not at all | KR25: Немного/A little | KU25: Совсем нет / Not at all | KY25: Совсем нет / Not at all | LD25: Немного / A little | LI25: Довольно сильно / Quite a bit | LN25: Очень сильно / Extremely | LP25: Немного / A little | LT25: Немного / A little | LW25: Совсем нет / Not at all | MA25: Совсем нет / Not at all | MF25: Немного / A little | MJ25: Немного / A little | MM25: Совсем нет / Not at all | MT25: Очень сильно / Extremely | MV25: Немного / A little | MY25: Совсем нет / Not at all | NC25: Совсем нет / Not at all | NG25: Совсем нет / Not at all | NL25: Немного / A little | NP25: Немного / A little | NS25: Совсем нет / Not at all | NY25: Довольно сильно / Quite a bit | OB25: Немного / A little | OG25: Довольно сильно / Quite a bit | OI25: Совсем нет / Not at all
A26: CG001 | B26: Да / Yes | D26: Да / Yes | F26: Да / Yes | I26: Мужской / Male | O26: 45-54 | R26: Русский(ая) / Russian | T26: English | U26: Краснодар | V26: Тбилиси, Грузия | W26: Женат (замужем) / Married | AE26: Нет / No | AF26: 0 | AH26: Нет / No | AI26: 0 | AN26: Высшее образование (специалист) / 5 years of college | AR26: Ниже среднего / Below average | AU26: 1. Некомфортно находиться в обществе, поддерживающем войну. 2. Страх преследования за убеждения и образ жизни. 3. Опасность быть призванным в действующую армию для ведения боевых действий. | AW26: Скорее согласен / Moderately agree | AZ26: Полностью согласен / Strongly agree | BF26: Скорее не согласен / Moderately disagree | BH26: Полностью согласен / Strongly agree | BN26: Скорее не согласен / Moderately disagree | BQ26: Скорее согласен / Moderately agree | BV26: Скорее не согласен / Moderately disagree | BY26: Скорее согласен / Moderately agree | CB26: Полностью согласен / Strongly agree | CG26: Скорее согласен / Moderately agree | CJ26: Полностью согласен / Strongly agree | CO26: Скорее согласен / Moderately agree | CR26: Полностью согласен / Strongly agree | CW26: Скорее согласен / Moderately agree | DB26: Скорее не согласен / Moderately disagree | DD26: Полностью согласен / Strongly agree | DI26: Скорее согласен / Moderately agree | DL26: Полностью согласен / Strongly agree | DP26: Полностью согласен / Strongly agree | DT26: Полностью согласен / Strongly agree | DY26: Скорее согласен / Moderately agree | EC26: Скорее согласен / Moderately agree | EI26: Полностью не согласен / Strongly disagree | EL26: Скорее не согласен / Moderately disagree | EQ26: Полностью не согласен / Strongly disagree | ES26: Скорее согласен / Moderately agree | EV26: Полностью согласен / Strongly agree | FA26: Скорее согласен / Moderately agree | FF26: Скорее не согласен / Moderately disagree | FH26: Полностью согласен / Strongly agree | FN26: Скорее не согласен / Moderately disagree | FP26: Да / Yes | FR26: Да / Yes | FU26: Нет / No | FW26: Нет / No | FY26: Нет / No | GA26: Нет / No | GC26: Нет / No | GE26: Нет / No | GF26: Да / Yes | GH26: Да / Yes | GJ26: Да / Yes | GL26: Да / Yes | GO26: Нет / No | GQ26: Нет / No | GS26: Нет / No | GT26: Да / Yes | GV26: Да / Yes | GX26: Однажды поперхнулся чаем и чуть не задохнулся. Однажды попал под напряжение 220 В. | GZ26: Немного/A little | HC26: Совсем нет/Not at all | HG26: Совсем нет/Not at all | HL26: Немного/A little | HP26: Немного/A little | HS26: Совсем нет/Not at all | HX26: Немного/A little | IA26: Совсем нет/Not at all | IE26: Совсем нет/Not at all | II26: Совсем нет/Not at all | IM26: Совсем нет/Not at all | IQ26: Совсем нет/Not at all | IU26: Совсем нет/Not at all | JB26: Очень сильно/Extremely | JC26: Совсем нет/Not at all | JH26: Немного/A little | JL26: Немного/A little | JP26: Немного/A little | JT26: Немного/A little | JX26: Немного/A little | KB26: Немного/A little | KE26: Совсем нет/Not at all | KI26: Совсем нет/Not at all | KM26: Совсем нет/Not at all | KR26: Немного/A little | KW26: Довольно сильно / Quite a bit | KZ26: Немного / A little | LD26: Немного / A little | LH26: Немного / A little | LK26: Совсем нет / Not at all | LO26: Совсем нет / Not at all | LT26: Немного / A little | LW26: Совсем нет / Not at all | MC26: Довольно сильно / Quite a bit | MG26: Довольно сильно / Quite a bit | MJ26: Немного / A little | MN26: Немного / A little | MR26: Немного / A little | MV26: Немного / A little | MY26: Совсем нет / Not at all | NC26: Совсем нет / Not at all | NI26: Довольно сильно / Quite a bit | NL26: Немного / A little | NQ26: Довольно сильно / Quite a bit | NU26: Довольно сильно / Quite a bit | NX26: Немного / A little | OB26: Немного / A little | OF26: Немного / A little | OK26: Довольно сильно / Quite a bit
A27: RG001 | B27: Да / Yes | D27: Да / Yes | F27: Да / Yes | H27: Женский / Female | O27: 45-54 | R27: Русский(ая) / Russian | T27: Русский, английский | U27: Москва | V27: Ереван, Армения | Z27: Раздельное проживание / Separated | AE27: Нет / No | AF27: Нет | AG27: Да / Yes | AI27: 4 | AO27: Магистратура / Master’s Degree | AR27: Ниже среднего / Below average | AU27: Из-за преступных действий, которые совершают власти России | AX27: Скорее не согласен / Moderately disagree | BC27: Полностью не согласен / Strongly disagree | BF27: Скорее не согласен / Moderately disagree | BH27: Полностью согласен / Strongly agree | BL27: Полностью согласен / Strongly agree | BS27: Полностью не согласен / Strongly disagree | BW27: Полностью не согласен / Strongly disagree | BX27: Полностью согласен / Strongly agree | CE27: Полностью не согласен / Strongly disagree | CG27: Скорее согласен / Moderately agree | CM27: Полностью не согласен / Strongly disagree | CN27: Полностью согласен / Strongly agree | CS27: Скорее согласен / Moderately agree | CY27: Полностью не согласен / Strongly disagree | DC27: Полностью не согласен / Strongly disagree | DF27: Скорее не согласен / Moderately disagree | DH27: Полностью согласен / Strongly agree | DL27: Полностью согласен / Strongly agree | DR27: Скорее не согласен / Moderately disagree | DV27: Скорее не согласен / Moderately disagree | EA27: Полностью не согласен / Strongly disagree | EE27: Полностью не согласен / Strongly disagree | EI27: Полностью не согласен / Strongly disagree | EM27: Полностью не согласен / Strongly disagree | EQ27: Полностью не согласен / Strongly disagree | ES27: Скорее согласен / Moderately agree | EW27: Скорее согласен / Moderately agree | FB27: Скорее не согласен / Moderately disagree | FE27: Скорее согласен / Moderately agree | FK27: Полностью не согласен / Strongly disagree | FL27: Полностью согласен / Strongly agree | FP27: Да / Yes | FS27: Нет / No | FT27: Да / Yes | FW27: Нет / No | FY27: Нет / No | GA27: Нет / No | GB27: Да / Yes | GE27: Нет / No | GG27: Нет / No | GH27: Да / Yes | GJ27: Да / Yes | GL27: Да / Yes | GN27: Да / Yes | GQ27: Нет / No | GR27: Да / Yes | GU27: Нет / No | GW27: Нет / No | GX27: Нападение России на Украину. | GZ27: Немного/A little | HC27: Совсем нет/Not at all | HG27: Совсем нет/Not at all | HL27: Немного/A little | HQ27: Довольно сильно/Quite a bit | HU27: Довольно сильно/Quite a bit | HZ27: Очень сильно/Extremely | ID27: Очень сильно/Extremely | IH27: Очень сильно/Extremely | IL27: Очень сильно/Extremely | IN27: Немного/A little | IQ27: Совсем нет/Not at all | IX27: Очень сильно/Extremely | JB27: Очень сильно/Extremely | JF27: Очень сильно/Extremely | JG27: Совсем нет/Not at all | JN27: Очень сильно/Extremely | JP27: Немного/A little | JT27: Немного/A little | JY27: Довольно сильно/Quite a bit | KD27: Очень сильно/Extremely | KE27: Совсем нет/Not at all | KL27: Очень сильно/Extremely | KN27: Немного/A little | KR27: Немного/A little | KV27: Немного / A little | KZ27: Немного / A little | LD27: Немного / A little | LI27: Довольно сильно / Quite a bit | LN27: Очень сильно / Extremely | LP27: Немного / A little | LV27: Очень сильно / Extremely | LX27: Немного / A little | MB27: Немного / A little | MH27: Очень сильно / Extremely | ML27: Очень сильно / Extremely | MN27: Немного / A little | MT27: Очень сильно / Extremely | MX27: Очень сильно / Extremely | MY27: Совсем нет / Not at all | NF27: Очень сильно / Extremely | NJ27: Очень сильно / Extremely | NN27: Очень сильно / Extremely | NQ27: Довольно сильно / Quite a bit | NT27: Немного / A little | NZ27: Очень сильно / Extremely | OD27: Очень сильно / Extremely | OH27: Очень сильно / Extremely | OI27: Совсем нет / Not at all
A28: AO001 | B28: Да / Yes | D28: Да / Yes | F28: Да / Yes | H28: Женский / Female | N28: 35-44 | R28: Русский(ая) / Russian | T28: Русский, английский, португальский | U28: Москва | V28: Тбилиси | W28: Женат (замужем) / Married | AD28: Да / Yes | AF28: 2 | AH28: Нет / No | AN28: Высшее образование (специалист) / 5 years of college | AR28: Ниже среднего / Below average | AU28: Отсутствие ощущения безопасности Отсутствие перспектив для меня и моих детей Невозможность говорить то, что я думаю Несогласие с политикой государства, как внутренней, так в внешней (агрессивное вторжение в Украину, политика изоляции) Чувство причастности к войне Тяжелое психологическое состояние на фоне новостей о войне (стыд, отвращение, ненависть, злость) | AW28: Скорее согласен / Moderately agree | BB28: Скорее не согласен / Moderately disagree | BE28: Скорее согласен / Moderately agree | BK28: Полностью не согласен / Strongly disagree | BL28: Полностью согласен / Strongly agree | BR28: Скорее не согласен / Moderately disagree | BV28: Скорее не согласен / Moderately disagree | BZ28: Скорее не согласен / Moderately disagree | CE28: Полностью не согласен / Strongly disagree | CH28: Скорее не согласен / Moderately disagree | CL28: Скорее не согласен / Moderately disagree | CO28: Скорее согласен / Moderately agree | CS28: Скорее согласен / Moderately agree | CW28: Скорее согласен / Moderately agree | DA28: Скорее согласен / Moderately agree | DE28: Скорее согласен / Moderately agree | DI28: Скорее согласен / Moderately agree | DL28: Полностью согласен / Strongly agree | DQ28: Скорее согласен / Moderately agree | DV28: Скорее не согласен / Moderately disagree | DZ28: Скорее не согласен / Moderately disagree | ED28: Скорее не согласен / Moderately disagree | EI28: Полностью не согласен / Strongly disagree | EL28: Скорее не согласен / Moderately disagree | EP28: Скорее не согласен / Moderately disagree | ET28: Скорее не согласен / Moderately disagree | EY28: Полностью не согласен / Strongly disagree | FC28: Полностью не согласен / Strongly disagree | FF28: Скорее не согласен / Moderately disagree | FH28: Полностью согласен / Strongly agree | FN28: Скорее не согласен / Moderately disagree | FQ28: Нет / No | FS28: Нет / No | FU28: Нет / No | FW28: Нет / No | FY28: Нет / No | GA28: Нет / No | GC28: Нет / No | GE28: Нет / No | GG28: Нет / No | GI28: Нет / No | GJ28: Да / Yes | GM28: Нет / No | GO28: Нет / No | GQ28: Нет / No | GS28: Нет / No | GU28: Нет / No | GW28: Нет / No | GY28: Совсем нет/Not at all | HC28: Совсем нет/Not at all | HG28: Совсем нет/Not at all | HL28: Немного/A little | HO28: Совсем нет/Not at all | HT28: Немного/A little | HY28: Довольно сильно/Quite a bit | IC28: Довольно сильно/Quite a bit | IE28: Совсем нет/Not at all | IL28: Очень сильно/Extremely | IM28: Совсем нет/Not at all | IQ28: Совсем нет/Not at all | IU28: Совсем нет/Not at all | IZ28: Немного/A little | JC28: Совсем нет/Not at all | JG28: Совсем нет/Not at all | JM28: Довольно сильно/Quite a bit | JP28: Немного/A little | JT28: Немного/A little | JW28: Совсем нет/Not at all | KC28: Довольно сильно/Quite a bit | KE28: Совсем нет/Not at all | KI28: Совсем нет/Not at all | KM28: Совсем нет/Not at all | KQ28: Совсем нет/Not at all | KU28: Совсем нет / Not at all | KY28: Совсем нет / Not at all | LD28: Немного / A little | LG28: Совсем нет / Not at all | LK28: Совсем нет / Not at all | LO28: Совсем нет / Not at all | LS28: Совсем нет / Not at all | LX28: Немного / A little | MA28: Совсем нет / Not at all | MF28: Немного / A little | MJ28: Немного / A little | MO28: Довольно сильно / Quite a bit | MR28: Немного / A little | MW28: Довольно сильно / Quite a bit | MZ28: Немного / A little | NE28: Довольно сильно / Quite a bit | NI28: Довольно сильно / Quite a bit | NM28: Довольно сильно / Quite a bit | NO28: Совсем нет / Not at all | NT28: Немного / A little | NW28: Совсем нет / Not at all | OB28: Немного / A little | OF28: Немного / A little | OK28: Довольно сильно / Quite a bit
A29: FO001 | B29: Да / Yes | D29: Да / Yes | F29: Да / Yes | I29: Мужской / Male | M29: 25-34 | R29: Русский(ая) / Russian | T29: Deutsch(b2) , serbian(b2) , Englisch(a2) | U29: Dmitrov (Moscow Region) | V29: Tbilisi | W29: Женат (замужем) / Married | AD29: Да / Yes | AF29: 1 | AH29: Нет / No | AI29: 0 | AL29: Незаконченное высшее / Some college | AS29: Средний / Average | AU29: В принципе не разделяю политику путина, плюс к этому я служил в спецподразделении и должен был в первых рядах ехать в Украину. Мои убеждения не позволяют стрелять в братский народ, тем более за то что бы старый узурпатор продолжал разворовывать мою страну. | AX29: Скорее не согласен / Moderately disagree | AZ29: Полностью согласен / Strongly agree | BF29: Скорее не согласен / Moderately disagree | BH29: Полностью согласен / Strongly agree | BM29: Скорее согласен / Moderately agree | BQ29: Скорее согласен / Moderately agree | BV29: Скорее не согласен / Moderately disagree | BY29: Скорее согласен / Moderately agree | CC29: Скорее согласен / Moderately agree | CH29: Скорее не согласен / Moderately disagree | CJ29: Полностью согласен / Strongly agree | CO29: Скорее согласен / Moderately agree | CS29: Скорее согласен / Moderately agree | CV29: Полностью согласен / Strongly agree | CZ29: Полностью согласен / Strongly agree | DD29: Полностью согласен / Strongly agree | DH29: Полностью согласен / Strongly agree | DM29: Скорее согласен / Moderately agree | DP29: Полностью согласен / Strongly agree | DU29: Скорее согласен / Moderately agree | DZ29: Скорее не согласен / Moderately disagree | EC29: Скорее согласен / Moderately agree | EH29: Скорее не согласен / Moderately disagree | EL29: Скорее не согласен / Moderately disagree | EP29: Скорее не согласен / Moderately disagree | ES29: Скорее согласен / Moderately agree | EV29: Полностью согласен / Strongly agree | FA29: Скорее согласен / Moderately agree | FE29: Скорее согласен / Moderately agree | FH29: Полностью согласен / Strongly agree | FL29: Полностью согласен / Strongly agree | FP29: Да / Yes | FR29: Да / Yes | FT29: Да / Yes | FW29: Нет / No | FY29: Нет / No | GA29: Нет / No | GC29: Нет / No | GE29: Нет / No | GG29: Нет / No | GI29: Нет / No | GJ29: Да / Yes | GM29: Нет / No | GO29: Нет / No | GQ29: Нет / No | GS29: Нет / No | GU29: Нет / No | GW29: Нет / No | GX29: Все это относится к РФ и путинскому режиму. В Грузии у меня подобных проблем не возникало. | GZ29: Немного/A little | HD29: Немного/A little | HI29: Довольно сильно/Quite a bit | HN29: Очень сильно/Extremely | HQ29: Довольно сильно/Quite a bit | HV29: Очень сильно/Extremely | HY29: Довольно сильно/Quite a bit | IC29: Довольно сильно/Quite a bit | IH29: Очень сильно/Extremely | IK29: Довольно сильно/Quite a bit | IM29: Совсем нет/Not at all | IR29: Немного/A little | IW29: Довольно сильно/Quite a bit | JB29: Очень сильно/Extremely | JF29: Очень сильно/Extremely | JH29: Немного/A little | JN29: Очень сильно/Extremely | JR29: Очень сильно/Extremely | JU29: Довольно сильно/Quite a bit | JY29: Довольно сильно/Quite a bit | KD29: Очень сильно/Extremely | KF29: Немного/A little | KL29: Очень сильно/Extremely | KP29: Очень сильно/Extremely | KT29: Очень сильно/Extremely | KX29: Очень сильно / Extremely | LA29: Довольно сильно / Quite a bit | LD29: Немного / A little | LJ29: Очень сильно / Extremely | LN29: Очень сильно / Extremely | LR29: Очень сильно / Extremely | LV29: Очень сильно / Extremely | LX29: Немного / A little | MD29: Очень сильно / Extremely | MH29: Очень сильно / Extremely | MK29: Довольно сильно / Quite a bit | MP29: Очень сильно / Extremely | MS29: Довольно сильно / Quite a bit | MW29: Довольно сильно / Quite a bit | NA29: Довольно сильно / Quite a bit | NF29: Очень сильно / Extremely | NJ29: Очень сильно / Extremely | NN29: Очень сильно / Extremely | NR29: Очень сильно / Extremely | NU29: Довольно сильно / Quite a bit | NZ29: Очень сильно / Extremely | OD29: Очень сильно / Extremely | OH29: Очень сильно / Extremely | OL29: Очень сильно / Extremely
A30: uu001 | B30: Да / Yes | D30: Да / Yes | F30: Да / Yes | I30: Мужской / Male | N30: 35-44 | R30: Русский(ая) / Russian | T30: Русский | U30: Тольятти | V30: Грузия, Тбилиси | W30: Женат (замужем) / Married | AD30: Да / Yes | AF30: 1 | AH30: Нет / No | AI30: 0 | AL30: Незаконченное высшее / Some college | AS30: Средний / Average | AU30: Не согласен с политикой государства причём очень давно. И не хочу, чтобы мой сын рос в этой стране. Отсутствие перспектив. | AW30: Скорее согласен / Moderately agree | BC30: Полностью не согласен / Strongly disagree | BE30: Скорее согласен / Moderately agree | BK30: Полностью не согласен / Strongly disagree | BM30: Скорее согласен / Moderately agree | BS30: Полностью не согласен / Strongly disagree | BW30: Полностью не согласен / Strongly disagree | BZ30: Скорее не согласен / Moderately disagree | CC30: Скорее согласен / Moderately agree | CF30: Полностью согласен / Strongly agree | CM30: Полностью не согласен / Strongly disagree | CP30: Скорее не согласен / Moderately disagree | CS30: Скорее согласен / Moderately agree | CX30: Скорее не согласен / Moderately disagree | DC30: Полностью не согласен / Strongly disagree | DF30: Скорее не согласен / Moderately disagree | DI30: Скорее согласен / Moderately agree | DL30: Полностью согласен / Strongly agree | DP30: Полностью согласен / Strongly agree | DU30: Скорее согласен / Moderately agree | EA30: Полностью не согласен / Strongly disagree | ED30: Скорее не согласен / Moderately disagree | EI30: Полностью не согласен / Strongly disagree | EL30: Скорее не согласен / Moderately disagree | EO30: Скорее согласен / Moderately agree | ER30: Полностью согласен / Strongly agree | EV30: Полностью согласен / Strongly agree | FB30: Скорее не согласен / Moderately disagree | FD30: Полностью согласен / Strongly agree | FH30: Полностью согласен / Strongly agree | FM30: Скорее согласен / Moderately agree | FQ30: Нет / No | FS30: Нет / No | FU30: Нет / No | FW30: Нет / No | FY30: Нет / No | GA30: Нет / No | GC30: Нет / No | GE30: Нет / No | GG30: Нет / No | GH30: Да / Yes | GJ30: Да / Yes | GL30: Да / Yes | GO30: Нет / No | GQ30: Нет / No | GS30: Нет / No | GU30: Нет / No | GW30: Нет / No | GX30: Если бы мне ничего не угрожало, я бы не уехал. А ждать пока совершат неправоправные действия не вижу смысла. | GZ30: Немного/A little | HD30: Немного/A little | HG30: Совсем нет/Not at all | HL30: Немного/A little | HP30: Немного/A little | HS30: Совсем нет/Not at all | HY30: Довольно сильно/Quite a bit | IA30: Совсем нет/Not at all | IG30: Довольно сильно/Quite a bit | II30: Совсем нет/Not at all | IM30: Совсем нет/Not at all | IQ30: Совсем нет/Not at all | IV30: Немного/A little | IZ30: Немного/A little | JD30: Немного/A little | JG30: Совсем нет/Not at all | JM30: Довольно сильно/Quite a bit | JO30: Совсем нет/Not at all | JS30: Совсем нет/Not at all | JW30: Совсем нет/Not at all | KB30: Немного/A little | KE30: Совсем нет/Not at all | KI30: Совсем нет/Not at all | KM30: Совсем нет/Not at all | KQ30: Совсем нет/Not at all | KV30: Немного / A little | KY30: Совсем нет / Not at all | LC30: Совсем нет / Not at all | LG30: Совсем нет / Not at all | LK30: Совсем нет / Not at all | LO30: Совсем нет / Not at all | LS30: Совсем нет / Not at all | LW30: Совсем нет / Not at all | MA30: Совсем нет / Not at all | MF30: Немного / A little | MI30: Совсем нет / Not at all | MM30: Совсем нет / Not at all | MQ30: Совсем нет / Not at all | MU30: Совсем нет / Not at all | MY30: Совсем нет / Not at all | ND30: Немного / A little | NI30: Довольно сильно / Quite a bit | NL30: Немного / A little | NO30: Совсем нет / Not at all | NT30: Немного / A little | NW30: Совсем нет / Not at all | OA30: Совсем нет / Not at all | OF30: Немного / A little | OJ30: Немного / A little
A31: ID FP001 | B31: Да / Yes | D31: Да / Yes | F31: Да / Yes | I31: Мужской / Male | M31: 25-34 | R31: Русский(ая) / Russian | T31: Русский, Английский | U31: Москва | V31: Тбилиси, Грузия | W31: Женат (замужем) / Married | AD31: Да / Yes | AF31: 1 | AH31: Нет / No | AO31: Магистратура / Master’s Degree | AS31: Средний / Average | AU31: Безопасность, диверсификация бизнес-рисков | AW31: Скорее согласен / Moderately agree | AZ31: Полностью согласен / Strongly agree | BD31: Полностью согласен / Strongly agree | BI31: Скорее согласен / Moderately agree | BM31: Скорее согласен / Moderately agree | BQ31: Скорее согласен / Moderately agree | BU31: Скорее согласен / Moderately agree | BX31: Полностью согласен / Strongly agree | CD31: Скорее не согласен / Moderately disagree | CG31: Скорее согласен / Moderately agree | CJ31: Полностью согласен / Strongly agree | CO31: Скорее согласен / Moderately agree | CT31: Скорее не согласен / Moderately disagree | CV31: Полностью согласен / Strongly agree | DA31: Скорее согласен / Moderately agree | DD31: Полностью согласен / Strongly agree | DH31: Полностью согласен / Strongly agree | DL31: Полностью согласен / Strongly agree | DQ31: Скорее согласен / Moderately agree | DV31: Скорее не согласен / Moderately disagree | DY31: Скорее согласен / Moderately agree | EC31: Скорее согласен / Moderately agree | EF31: Полностью согласен / Strongly agree | EL31: Скорее не согласен / Moderately disagree | EP31: Скорее не согласен / Moderately disagree | ET31: Скорее не согласен / Moderately disagree | EW31: Скорее согласен / Moderately agree | FA31: Скорее согласен / Moderately agree | FF31: Скорее не согласен / Moderately disagree | FH31: Полностью согласен / Strongly agree | FO31: Полностью не согласен / Strongly disagree | FQ31: Нет / No | FS31: Нет / No | FU31: Нет / No | FW31: Нет / No | FY31: Нет / No | GA31: Нет / No | GC31: Нет / No | GE31: Нет / No | GG31: Нет / No | GI31: Нет / No | GJ31: Да / Yes | GM31: Нет / No | GO31: Нет / No | GQ31: Нет / No | GS31: Нет / No | GU31: Нет / No | GW31: Нет / No | GX31: Боюсь исключительно разлуки с семьей | GZ31: Немного/A little | HC31: Совсем нет/Not at all | HG31: Совсем нет/Not at all | HM31: Довольно сильно/Quite a bit | HO31: Совсем нет/Not at all | HT31: Немного/A little | HW31: Совсем нет/Not at all | IA31: Совсем нет/Not at all | IF31: Немного/A little | IK31: Довольно сильно/Quite a bit | IM31: Совсем нет/Not at all | IQ31: Совсем нет/Not at all | IU31: Совсем нет/Not at all | IY31: Совсем нет/Not at all | JD31: Немного/A little | JG31: Совсем нет/Not at all | JK31: Совсем нет/Not at all | JO31: Совсем нет/Not at all | JS31: Совсем нет/Not at all | JW31: Совсем нет/Not at all | KA31: Совсем нет/Not at all | KE31: Совсем нет/Not at all | KI31: Совсем нет/Not at all | KM31: Совсем нет/Not at all | KQ31: Совсем нет/Not at all | KU31: Совсем нет / Not at all | KY31: Совсем нет / Not at all | LC31: Совсем нет / Not at all | LH31: Немного / A little | LL31: Немного / A little | LO31: Совсем нет / Not at all | LT31: Немного / A little | LW31: Совсем нет / Not at all | MA31: Совсем нет / Not at all | MF31: Немного / A little | MJ31: Немного / A little | MN31: Немного / A little | MQ31: Совсем нет / Not at all | MV31: Немного / A little | MZ31: Немного / A little | NC31: Совсем нет / Not at all | NG31: Совсем нет / Not at all | NM31: Довольно сильно / Quite a bit | NQ31: Довольно сильно / Quite a bit | NT31: Немного / A little | NX31: Немного / A little | OA31: Совсем нет / Not at all | OF31: Немного / A little | OJ31: Немного / A little
A32: FN001 | B32: Да / Yes | D32: Да / Yes | F32: Да / Yes | I32: Мужской / Male | L32: 18-24 | R32: Русский(ая) / Russian | T32: Русский, английский | U32: Москва | V32: Тбилиси, Грузия | AA32: Гражданский брак / Cohabiting with a significant other or in a domestic partnership | AE32: Нет / No | AH32: Нет / No | AL32: Незаконченное высшее / Some college | AS32: Средний / Average | AU32: Политическое преследование, ограничение свободы слова, преследование ЛГБТ персон | AX32: Скорее не согласен / Moderately disagree | BA32: Скорее согласен / Moderately agree | BF32: Скорее не согласен / Moderately disagree | BJ32: Скорее не согласен / Moderately disagree | BM32: Скорее согласен / Moderately agree | BR32: Скорее не согласен / Moderately disagree | BW32: Полностью не согласен / Strongly disagree | BY32: Скорее согласен / Moderately agree | CC32: Скорее согласен / Moderately agree | CH32: Скорее не согласен / Moderately disagree | CL32: Скорее не согласен / Moderately disagree | CO32: Скорее согласен / Moderately agree | CU32: Полностью не согласен / Strongly disagree | CY32: Полностью не согласен / Strongly disagree | DC32: Полностью не согласен / Strongly disagree | DD32: Полностью согласен / Strongly agree | DH32: Полностью согласен / Strongly agree | DM32: Скорее согласен / Moderately agree | DP32: Полностью согласен / Strongly agree | DU32: Скорее согласен / Moderately agree | EA32: Полностью не согласен / Strongly disagree | ED32: Скорее не согласен / Moderately disagree | EI32: Полностью не согласен / Strongly disagree | EL32: Скорее не согласен / Moderately disagree | EQ32: Полностью не согласен / Strongly disagree | ES32: Скорее согласен / Moderately agree | EW32: Скорее согласен / Moderately agree | FB32: Скорее не согласен / Moderately disagree | FE32: Скорее согласен / Moderately agree | FI32: Скорее согласен / Moderately agree | FL32: Полностью согласен / Strongly agree | FQ32: Нет / No | FS32: Нет / No | FT32: Да / Yes | FW32: Нет / No | FY32: Нет / No | GA32: Нет / No | GC32: Нет / No | GE32: Нет / No | GG32: Нет / No | GI32: Нет / No | GK32: Нет / No | GM32: Нет / No | GO32: Нет / No | GQ32: Нет / No | GS32: Нет / No | GU32: Нет / No | GW32: Нет / No | GZ32: Немного/A little | HC32: Совсем нет/Not at all | HH32: Немного/A little | HM32: Довольно сильно/Quite a bit | HQ32: Довольно сильно/Quite a bit | HT32: Немного/A little | HY32: Довольно сильно/Quite a bit | ID32: Очень сильно/Extremely | IG32: Довольно сильно/Quite a bit | IJ32: Немного/A little | IN32: Немного/A little | IQ32: Совсем нет/Not at all | IW32: Довольно сильно/Quite a bit | JA32: Довольно сильно/Quite a bit | JD32: Немного/A little | JG32: Совсем нет/Not at all | JL32: Немного/A little | JO32: Совсем нет/Not at all | JS32: Совсем нет/Not at all | JX32: Немного/A little | KB32: Немного/A little | KH32: Очень сильно/Extremely | KK32: Довольно сильно/Quite a bit | KM32: Совсем нет/Not at all | KQ32: Совсем нет/Not at all | KU32: Совсем нет / Not at all | KZ32: Немного / A little | LE32: Довольно сильно / Quite a bit | LH32: Немного / A little | LL32: Немного / A little | LO32: Совсем нет / Not at all | LU32: Довольно сильно / Quite a bit | LX32: Немного / A little | MA32: Совсем нет / Not at all | MF32: Немного / A little | MJ32: Немного / A little | MO32: Довольно сильно / Quite a bit | MQ32: Совсем нет / Not at all | MU32: Совсем нет / Not at all | NB32: Очень сильно / Extremely | NF32: Очень сильно / Extremely | NH32: Немного / A little | NM32: Довольно сильно / Quite a bit | NP32: Немного / A little | NS32: Совсем нет / Not at all | NZ32: Очень сильно / Extremely | OA32: Совсем нет / Not at all | OF32: Немного / A little | OL32: Очень сильно / Extremely
A33: NI001 | B33: Да / Yes | D33: Да / Yes | F33: Да / Yes | H33: Женский / Female | N33: 35-44 | R33: Русский(ая) / Russian | T33: English B1 | U33: Санкт-Петербург | V33: Тбилиси | Y33: В разводе / Divorced | AD33: Да / Yes | AF33: 1 | AH33: Нет / No | AI33: 0 | AN33: Высшее образование (специалист) / 5 years of college | AS33: Средний / Average | AU33: 1) Мне угрожал арест как гражданской активистке 2) Я не считаю возможным находиться в одной стране с людьми, поддерживающими войну 3) Дальнейшая деятельность в области общественной работы, которой я занималась, была бы в России бессмысленной. | AV33: Полностью согласен / Strongly agree | BC33: Полностью не согласен / Strongly disagree | BF33: Скорее не согласен / Moderately disagree | BJ33: Скорее не согласен / Moderately disagree | BL33: Полностью согласен / Strongly agree | BR33: Скорее не согласен / Moderately disagree | BV33: Скорее не согласен / Moderately disagree | BZ33: Скорее не согласен / Moderately disagree | CB33: Полностью согласен / Strongly agree | CH33: Скорее не согласен / Moderately disagree | CK33: Скорее согласен / Moderately agree | CO33: Скорее согласен / Moderately agree | CT33: Скорее не согласен / Moderately disagree | CY33: Полностью не согласен / Strongly disagree | DC33: Полностью не согласен / Strongly disagree | DG33: Полностью не согласен / Strongly disagree | DH33: Полностью согласен / Strongly agree | DN33: Скорее не согласен / Moderately disagree | DP33: Полностью согласен / Strongly agree | DT33: Полностью согласен / Strongly agree | EA33: Полностью не согласен / Strongly disagree | EC33: Скорее согласен / Moderately agree | EI33: Полностью не согласен / Strongly disagree | EM33: Полностью не согласен / Strongly disagree | EQ33: Полностью не согласен / Strongly disagree | ES33: Скорее согласен / Moderately agree | EV33: Полностью согласен / Strongly agree | FB33: Скорее не согласен / Moderately disagree | FF33: Скорее не согласен / Moderately disagree | FK33: Полностью не согласен / Strongly disagree | FL33: Полностью согласен / Strongly agree | FP33: Да / Yes | FS33: Нет / No | FU33: Нет / No | FW33: Нет / No | FY33: Нет / No | GA33: Нет / No | GC33: Нет / No | GE33: Нет / No | GG33: Нет / No | GI33: Нет / No | GJ33: Да / Yes | GL33: Да / Yes | GO33: Нет / No | GQ33: Нет / No | GR33: Да / Yes | GU33: Нет / No | GW33: Нет / No | GX33: Похищение ребенка. | GY33: Совсем нет/Not at all | HC33: Совсем нет/Not at all | HG33: Совсем нет/Not at all | HL33: Немного/A little | HO33: Совсем нет/Not at all | HS33: Совсем нет/Not at all | HZ33: Очень сильно/Extremely | IB33: Немного/A little | IE33: Совсем нет/Not at all | IJ33: Немного/A little | IN33: Немного/A little | IQ33: Совсем нет/Not at all | IW33: Довольно сильно/Quite a bit | JA33: Довольно сильно/Quite a bit | JC33: Совсем нет/Not at all | JH33: Немного/A little | JL33: Немного/A little | JO33: Совсем нет/Not at all | JS33: Совсем нет/Not at all | JW33: Совсем нет/Not at all | KA33: Совсем нет/Not at all | KE33: Совсем нет/Not at all | KL33: Очень сильно/Extremely | KM33: Совсем нет/Not at all | KR33: Немного/A little | KU33: Совсем нет / Not at all | KY33: Совсем нет / Not at all | LC33: Совсем нет / Not at all | LG33: Совсем нет / Not at all | LK33: Совсем нет / Not at all | LO33: Совсем нет / Not at all | LS33: Совсем нет / Not at all | LY33: Довольно сильно / Quite a bit | MB33: Немного / A little | MF33: Немного / A little | ML33: Очень сильно / Extremely | MO33: Довольно сильно / Quite a bit | MQ33: Совсем нет / Not at all | MW33: Довольно сильно / Quite a bit | MY33: Совсем нет / Not at all | ND33: Немного / A little | NH33: Немного / A little | NM33: Довольно сильно / Quite a bit | NP33: Немного / A little | NV33: Очень сильно / Extremely | NW33: Совсем нет / Not at all | OC33: Довольно сильно / Quite a bit | OH33: Очень сильно / Extremely | OK33: Довольно сильно / Quite a bit
A34: EE001 | B34: Да / Yes | D34: Да / Yes | F34: Да / Yes | H34: Женский / Female | L34: 18-24 | S34: Смесь русской, еврейской, мордовской национальностей, но в целом не отождествляю себя с конкретной национальностью | T34: Русский, английский | U34: Москва | V34: Ереван, Армения | AA34: Гражданский брак / Cohabiting with a significant other or in a domestic partnership | AE34: Нет / No | AH34: Нет / No | AM34: Высшее образование (бакалавриат) / Bachelor’s Degree | AR34: Ниже среднего / Below average | AU34: Непосредственный повод - мой партнер попадал под уголовное преследование за активную политическую позицию, а также был в опасности призыва в армию. Конкретно моими причинами были небезопасность, высочайший уровень стресса и тревожности, страх за себя и близких, нежелание чувствовать себя причастной к военным действиям, большой стресс при осознании и наблюдении того, как 90% моего мира и жизни разрушаются. | AX34: Скорее не согласен / Moderately disagree | AZ34: Полностью согласен / Strongly agree | BG34: Полностью не согласен / Strongly disagree | BJ34: Скорее не согласен / Moderately disagree | BM34: Скорее согласен / Moderately agree | BR34: Скорее не согласен / Moderately disagree | BW34: Полностью не согласен / Strongly disagree | BX34: Полностью согласен / Strongly agree | CD34: Скорее не согласен / Moderately disagree | CG34: Скорее согласен / Moderately agree | CL34: Скорее не согласен / Moderately disagree | CO34: Скорее согласен / Moderately agree | CR34: Полностью согласен / Strongly agree | CX34: Скорее не согласен / Moderately disagree | DC34: Полностью не согласен / Strongly disagree | DF34: Скорее не согласен / Moderately disagree | DH34: Полностью согласен / Strongly agree | DL34: Полностью согласен / Strongly agree | DP34: Полностью согласен / Strongly agree | DU34: Скорее согласен / Moderately agree | EA34: Полностью не согласен / Strongly disagree | EC34: Скорее согласен / Moderately agree | EI34: Полностью не согласен / Strongly disagree | EL34: Скорее не согласен / Moderately disagree | EO34: Скорее согласен / Moderately agree | ET34: Скорее не согласен / Moderately disagree | EW34: Скорее согласен / Moderately agree | EZ34: Полностью согласен / Strongly agree | FF34: Скорее не согласен / Moderately disagree | FI34: Скорее согласен / Moderately agree | FN34: Скорее не согласен / Moderately disagree | FP34: Да / Yes | FS34: Нет / No | FU34: Нет / No | FW34: Нет / No | FY34: Нет / No | GA34: Нет / No | GC34: Нет / No | GE34: Нет / No | GG34: Нет / No | GI34: Нет / No | GJ34: Да / Yes | GL34: Да / Yes | GO34: Нет / No | GQ34: Нет / No | GS34: Нет / No | GU34: Нет / No | GW34: Нет / No | GX34: Когда началась война, когда началась мобилизация - вообще нахождение внутри России и полная неизвестность, какой еще закон выйдет на следующий день и что теперь с нами можно будет делать законно - понимание, что это может быть абсолютно всё, что угодно. Авария. Угрозы физической расправы от родственников. Психическое давление от родственников. Невосприятие моего ответа "нет" со стороны мужского пола. | HA34: Довольно сильно/Quite a bit | HF34: Очень сильно/Extremely | HH34: Немного/A little | HN34: Очень сильно/Extremely | HR34: Очень сильно/Extremely | HV34: Очень сильно/Extremely | HZ34: Очень сильно/Extremely | ID34: Очень сильно/Extremely | IH34: Очень сильно/Extremely | IL34: Очень сильно/Extremely | IO34: Довольно сильно/Quite a bit | IR34: Немного/A little | IW34: Довольно сильно/Quite a bit | JB34: Очень сильно/Extremely | JE34: Довольно сильно/Quite a bit | JJ34: Очень сильно/Extremely | JN34: Очень сильно/Extremely | JP34: Немного/A little | JU34: Довольно сильно/Quite a bit | JY34: Довольно сильно/Quite a bit | KD34: Очень сильно/Extremely | KE34: Совсем нет/Not at all | KL34: Очень сильно/Extremely | KP34: Очень сильно/Extremely | KQ34: Совсем нет/Not at all | KX34: Очень сильно / Extremely | LB34: Очень сильно / Extremely | LE34: Довольно сильно / Quite a bit | LJ34: Очень сильно / Extremely | LN34: Очень сильно / Extremely | LP34: Немного / A little | LV34: Очень сильно / Extremely | LZ34: Очень сильно / Extremely | MB34: Немного / A little | MH34: Очень сильно / Extremely | ML34: Очень сильно / Extremely | MO34: Довольно сильно / Quite a bit | MT34: Очень сильно / Extremely | MU34: Совсем нет / Not at all | MY34: Совсем нет / Not at all | NF34: Очень сильно / Extremely | NH34: Немного / A little | NM34: Довольно сильно / Quite a bit | NP34: Немного / A little | NT34: Немного / A little | NY34: Довольно сильно / Quite a bit | OD34: Очень сильно / Extremely | OH34: Очень сильно / Extremely | OL34: Очень сильно / Extremely
A35: OM001 | B35: Да / Yes | D35: Да / Yes | F35: Да / Yes | H35: Женский / Female | L35: 18-24 | R35: Русский(ая) / Russian | T35: Fussian. A little English. | U35: Moscow | V35: Tbilisi | AB35: Никогда не был женат (замужем) / Single, never married | AE35: Нет / No | AF35: I don't have children | AH35: Нет / No | AI35: No | AK35: Среднее образование / High school graduate | AR35: Ниже среднего / Below average | AU35: Я уехала с родителями. Мы все не поддерживаем войну. А так же после того как мои родители выходили на антивоенную акцию, к нам приходили люди из фсб с угрозами. Стало не безопасно находиться дома. | AX35: Скорее не согласен / Moderately disagree | AZ35: Полностью согласен / Strongly agree | BE35: Скорее согласен / Moderately agree | BJ35: Скорее не согласен / Moderately disagree | BN35: Скорее не согласен / Moderately disagree | BP35: Полностью согласен / Strongly agree | BV35: Скорее не согласен / Moderately disagree | BY35: Скорее согласен / Moderately agree | CC35: Скорее согласен / Moderately agree | CH35: Скорее не согласен / Moderately disagree | CK35: Скорее согласен / Moderately agree | CO35: Скорее согласен / Moderately agree | CS35: Скорее согласен / Moderately agree | CX35: Скорее не согласен / Moderately disagree | DC35: Полностью не согласен / Strongly disagree | DE35: Скорее согласен / Moderately agree | DI35: Скорее согласен / Moderately agree | DM35: Скорее согласен / Moderately agree | DP35: Полностью согласен / Strongly agree | DU35: Скорее согласен / Moderately agree | DZ35: Скорее не согласен / Moderately disagree | EE35: Полностью не согласен / Strongly disagree | EI35: Полностью не согласен / Strongly disagree | EK35: Скорее согласен / Moderately agree | EP35: Скорее не согласен / Moderately disagree | ES35: Скорее согласен / Moderately agree | EW35: Скорее согласен / Moderately agree | FB35: Скорее не согласен / Moderately disagree | FF35: Скорее не согласен / Moderately disagree | FH35: Полностью согласен / Strongly agree | FN35: Скорее не согласен / Moderately disagree | FP35: Да / Yes | FR35: Да / Yes | FU35: Нет / No | FW35: Нет / No | FY35: Нет / No | GA35: Нет / No | GC35: Нет / No | GE35: Нет / No | GG35: Нет / No | GI35: Нет / No | GJ35: Да / Yes | GL35: Да / Yes | GO35: Нет / No | GQ35: Нет / No | GS35: Нет / No | GU35: Нет / No | GW35: Нет / No | GX35: Not | GZ35: Немного/A little | HD35: Немного/A little | HH35: Немного/A little | HK35: Совсем нет/Not at all | HO35: Совсем нет/Not at all | HT35: Немного/A little | HX35: Немного/A little | IB35: Немного/A little | IE35: Совсем нет/Not at all | II35: Совсем нет/Not at all | IN35: Немного/A little | IQ35: Совсем нет/Not at all | IV35: Немного/A little | IY35: Совсем нет/Not at all | JC35: Совсем нет/Not at all | JH35: Немного/A little | JK35: Совсем нет/Not at all | JP35: Немного/A little | JS35: Совсем нет/Not at all | JX35: Немного/A little | KA35: Совсем нет/Not at all | KE35: Совсем нет/Not at all | KI35: Совсем нет/Not at all | KN35: Немного/A little | KQ35: Совсем нет/Not at all | KU35: Совсем нет / Not at all | KZ35: Немного / A little | LC35: Совсем нет / Not at all | LH35: Немного / A little | LK35: Совсем нет / Not at all | LO35: Совсем нет / Not at all | LT35: Немного / A little | LX35: Немного / A little | MA35: Совсем нет / Not at all | MF35: Немного / A little | MJ35: Немного / A little | MO35: Довольно сильно / Quite a bit | MR35: Немного / A little | MV35: Немного / A little | MY35: Совсем нет / Not at all | ND35: Немного / A little | NH35: Немного / A little | NL35: Немного / A little | NP35: Немного / A little | NS35: Совсем нет / Not at all | NX35: Немного / A little | OA35: Совсем нет / Not at all | OF35: Немного / A little | OJ35: Немного / A little
A36: MT001 | B36: Да / Yes | D36: Да / Yes | F36: Да / Yes | H36: Женский / Female | M36: 25-34 | R36: Русский(ая) / Russian | T36: English (B2) | U36: Moscow | V36: Tbilisi, Georgia | W36: Женат (замужем) / Married | AE36: Нет / No | AF36: нет | AH36: Нет / No | AI36: Нет | AM36: Высшее образование (бакалавриат) / Bachelor’s Degree | AT36: Выше среднего / Above average | AU36: Стало страшно там оставаться. за своих близких и за себя, за свое будущее. Происходящее стало похоже на хаос без законов. Первые месяцы остро переживалось начало войны. Потом я переживала больше уже за себя. Не хотелось быть взаперти. | AW36: Скорее согласен / Moderately agree | BA36: Скорее согласен / Moderately agree | BE36: Скорее согласен / Moderately agree | BJ36: Скорее не согласен / Moderately disagree | BL36: Полностью согласен / Strongly agree | BP36: Полностью согласен / Strongly agree | BU36: Скорее согласен / Moderately agree | BY36: Скорее согласен / Moderately agree | CC36: Скорее согласен / Moderately agree | CH36: Скорее не согласен / Moderately disagree | CJ36: Полностью согласен / Strongly agree | CO36: Скорее согласен / Moderately agree | CU36: Полностью не согласен / Strongly disagree | CV36: Полностью согласен / Strongly agree | DA36: Скорее согласен / Moderately agree | DD36: Полностью согласен / Strongly agree | DH36: Полностью согласен / Strongly agree | DM36: Скорее согласен / Moderately agree | DR36: Скорее не согласен / Moderately disagree | DV36: Скорее не согласен / Moderately disagree | DZ36: Скорее не согласен / Moderately disagree | ED36: Скорее не согласен / Moderately disagree | EH36: Скорее не согласен / Moderately disagree | EK36: Скорее согласен / Moderately agree | EP36: Скорее не согласен / Moderately disagree | ET36: Скорее не согласен / Moderately disagree | EW36: Скорее согласен / Moderately agree | FB36: Скорее не согласен / Moderately disagree | FE36: Скорее согласен / Moderately agree | FH36: Полностью согласен / Strongly agree | FM36: Скорее согласен / Moderately agree | FQ36: Нет / No | FS36: Нет / No | FU36: Нет / No | FW36: Нет / No | FY36: Нет / No | GA36: Нет / No | GC36: Нет / No | GE36: Нет / No | GG36: Нет / No | GI36: Нет / No | GJ36: Да / Yes | GM36: Нет / No | GO36: Нет / No | GQ36: Нет / No | GS36: Нет / No | GU36: Нет / No | GW36: Нет / No | GX36: Когда объявили мобилизацию. Впервые в жизни я испытала ужас смерти своего близкого человека. Вместе с сестрой, мы сутки гнали на юг России, чтобы мой мужчина смог пересечь границу. Это были одни из самых страшных часов в жизни. | GZ36: Немного/A little | HC36: Совсем нет/Not at all | HG36: Совсем нет/Not at all | HK36: Совсем нет/Not at all | HO36: Совсем нет/Not at all | HS36: Совсем нет/Not at all | HX36: Немного/A little | IB36: Немного/A little | IF36: Немного/A little | IK36: Довольно сильно/Quite a bit | IM36: Совсем нет/Not at all | IQ36: Совсем нет/Not at all | IV36: Немного/A little | JB36: Очень сильно/Extremely | JC36: Совсем нет/Not at all | JG36: Совсем нет/Not at all | JL36: Немного/A little | JP36: Немного/A little | JS36: Совсем нет/Not at all | JW36: Совсем нет/Not at all | KA36: Совсем нет/Not at all | KE36: Совсем нет/Not at all | KJ36: Немного/A little | KN36: Немного/A little | KQ36: Совсем нет/Not at all | KU36: Совсем нет / Not at all | KY36: Совсем нет / Not at all | LC36: Совсем нет / Not at all | LH36: Немного / A little | LL36: Немного / A little | LO36: Совсем нет / Not at all | LT36: Немного / A little | LX36: Немного / A little | MB36: Немного / A little | MF36: Немного / A little | MJ36: Немного / A little | MO36: Довольно сильно / Quite a bit | MS36: Довольно сильно / Quite a bit | MW36: Довольно сильно / Quite a bit | MY36: Совсем нет / Not at all | NC36: Совсем нет / Not at all | NH36: Немного / A little | NL36: Немного / A little | NP36: Немного / A little | NT36: Немного / A little | NY36: Довольно сильно / Quite a bit | OB36: Немного / A little | OG36: Довольно сильно / Quite a bit | OJ36: Немного / A little
A37: LO001 | B37: Да / Yes | D37: Да / Yes | F37: Да / Yes | I37: Мужской / Male | M37: 25-34 | R37: Русский(ая) / Russian | T37: Русский, English | U37: Москва | V37: Тбилиси | AA37: Гражданский брак / Cohabiting with a significant other or in a domestic partnership | AE37: Нет / No | AH37: Нет / No | AO37: Магистратура / Master’s Degree | AT37: Выше среднего / Above average | AU37: несогласие с войной и проводимой политикой | AX37: Скорее не согласен / Moderately disagree | BB37: Скорее не согласен / Moderately disagree | BE37: Скорее согласен / Moderately agree | BJ37: Скорее не согласен / Moderately disagree | BN37: Скорее не согласен / Moderately disagree | BS37: Полностью не согласен / Strongly disagree | BV37: Скорее не согласен / Moderately disagree | BY37: Скорее согласен / Moderately agree | CD37: Скорее не согласен / Moderately disagree | CG37: Скорее согласен / Moderately agree | CK37: Скорее согласен / Moderately agree | CN37: Полностью согласен / Strongly agree | CU37: Полностью не согласен / Strongly disagree | CW37: Скорее согласен / Moderately agree | DB37: Скорее не согласен / Moderately disagree | DD37: Полностью согласен / Strongly agree | DH37: Полностью согласен / Strongly agree | DL37: Полностью согласен / Strongly agree | DQ37: Скорее согласен / Moderately agree | DV37: Скорее не согласен / Moderately disagree | EA37: Полностью не согласен / Strongly disagree | ED37: Скорее не согласен / Moderately disagree | EF37: Полностью согласен / Strongly agree | EL37: Скорее не согласен / Moderately disagree | EQ37: Полностью не согласен / Strongly disagree | ET37: Скорее не согласен / Moderately disagree | EV37: Полностью согласен / Strongly agree | FB37: Скорее не согласен / Moderately disagree | FE37: Скорее согласен / Moderately agree | FH37: Полностью согласен / Strongly agree | FM37: Скорее согласен / Moderately agree | FP37: Да / Yes | FS37: Нет / No | FU37: Нет / No | FW37: Нет / No | FY37: Нет / No | GA37: Нет / No | GC37: Нет / No | GE37: Нет / No | GG37: Нет / No | GI37: Нет / No | GK37: Нет / No | GM37: Нет / No | GO37: Нет / No | GQ37: Нет / No | GS37: Нет / No | GU37: Нет / No | GW37: Нет / No | GX37: таких ситуаций не было | GZ37: Немного/A little | HC37: Совсем нет/Not at all | HG37: Совсем нет/Not at all | HL37: Немного/A little | HO37: Совсем нет/Not at all | HV37: Очень сильно/Extremely | HY37: Довольно сильно/Quite a bit | IC37: Довольно сильно/Quite a bit | IG37: Довольно сильно/Quite a bit | IL37: Очень сильно/Extremely | IM37: Совсем нет/Not at all | IQ37: Совсем нет/Not at all | IV37: Немного/A little | JB37: Очень сильно/Extremely | JC37: Совсем нет/Not at all | JG37: Совсем нет/Not at all | JM37: Довольно сильно/Quite a bit | JO37: Совсем нет/Not at all | JS37: Совсем нет/Not at all | JW37: Совсем нет/Not at all | KB37: Немного/A little | KE37: Совсем нет/Not at all | KI37: Совсем нет/Not at all | KM37: Совсем нет/Not at all | KQ37: Совсем нет/Not at all | KV37: Немного / A little | KZ37: Немного / A little | LC37: Совсем нет / Not at all | LI37: Довольно сильно / Quite a bit | LK37: Совсем нет / Not at all | LO37: Совсем нет / Not at all | LU37: Довольно сильно / Quite a bit | LW37: Совсем нет / Not at all | MA37: Совсем нет / Not at all | MF37: Немного / A little | MI37: Совсем нет / Not at all | MM37: Совсем нет / Not at all | MQ37: Совсем нет / Not at all | MU37: Совсем нет / Not at all | MZ37: Немного / A little | NE37: Довольно сильно / Quite a bit | NJ37: Очень сильно / Extremely | NL37: Немного / A little | NP37: Немного / A little | NS37: Совсем нет / Not at all | NY37: Довольно сильно / Quite a bit | OA37: Совсем нет / Not at all | OF37: Немного / A little | OJ37: Немного / A little
A38: DA001 | B38: Да / Yes | D38: Да / Yes | F38: Да / Yes | I38: Мужской / Male | M38: 25-34 | S38: Татарин на половину русский | T38: Русский, очень плохо английский, татарский | U38: Москва | V38: Тбилиси | W38: Женат (замужем) / Married | AE38: Нет / No | AF38: 0 | AH38: Нет / No | AI38: 0 | AN38: Высшее образование (специалист) / 5 years of college | AS38: Средний / Average | AU38: Началась мобилизация гражданского населения РФ. А умирать, становиться инвалидом или убивать ради Путина не хочу. И в целом не хочу участвовать в военных действиях. | AX38: Скорее не согласен / Moderately disagree | BA38: Скорее согласен / Moderately agree | BE38: Скорее согласен / Moderately agree | BI38: Скорее согласен / Moderately agree | BN38: Скорее не согласен / Moderately disagree | BR38: Скорее не согласен / Moderately disagree | BT38: Полностью согласен / Strongly agree | BX38: Полностью согласен / Strongly agree | CB38: Полностью согласен / Strongly agree | CG38: Скорее согласен / Moderately agree | CJ38: Полностью согласен / Strongly agree | CO38: Скорее согласен / Moderately agree | CS38: Скорее согласен / Moderately agree | CV38: Полностью согласен / Strongly agree | CZ38: Полностью согласен / Strongly agree | DD38: Полностью согласен / Strongly agree | DH38: Полностью согласен / Strongly agree | DL38: Полностью согласен / Strongly agree | DP38: Полностью согласен / Strongly agree | DU38: Скорее согласен / Moderately agree | DY38: Скорее согласен / Moderately agree | EC38: Скорее согласен / Moderately agree | EH38: Скорее не согласен / Moderately disagree | EM38: Полностью не согласен / Strongly disagree | EQ38: Полностью не согласен / Strongly disagree | ES38: Скорее согласен / Moderately agree | EV38: Полностью согласен / Strongly agree | EZ38: Полностью согласен / Strongly agree | FD38: Полностью согласен / Strongly agree | FH38: Полностью согласен / Strongly agree | FM38: Скорее согласен / Moderately agree | FQ38: Нет / No | FS38: Нет / No | FU38: Нет / No | FW38: Нет / No | FY38: Нет / No | GA38: Нет / No | GC38: Нет / No | GE38: Нет / No | GG38: Нет / No | GH38: Да / Yes | GJ38: Да / Yes | GM38: Нет / No | GO38: Нет / No | GQ38: Нет / No | GS38: Нет / No | GU38: Нет / No | GW38: Нет / No | GX38: Участие в митингах в Москве, во время досмотра на постах ГАИ во время пути к границе России. Когда 21 сентября кто то пытался войти в мою квартиру хотя я никого не ждал, это оказалась подруга жены. | GZ38: Немного/A little | HC38: Совсем нет/Not at all | HG38: Совсем нет/Not at all | HL38: Немного/A little | HP38: Немного/A little | HU38: Довольно сильно/Quite a bit | HY38: Довольно сильно/Quite a bit | IB38: Немного/A little | IF38: Немного/A little | IK38: Довольно сильно/Quite a bit | IM38: Совсем нет/Not at all | IQ38: Совсем нет/Not at all | IV38: Немного/A little | JA38: Довольно сильно/Quite a bit | JC38: Совсем нет/Not at all | JG38: Совсем нет/Not at all | JL38: Немного/A little | JQ38: Довольно сильно/Quite a bit | JT38: Немного/A little | JW38: Совсем нет/Not at all | KC38: Довольно сильно/Quite a bit | KF38: Немного/A little | KI38: Совсем нет/Not at all | KM38: Совсем нет/Not at all | KQ38: Совсем нет/Not at all | KV38: Немного / A little | KZ38: Немного / A little | LC38: Совсем нет / Not at all | LG38: Совсем нет / Not at all | LL38: Немного / A little | LO38: Совсем нет / Not at all | LT38: Немного / A little | LX38: Немного / A little | MA38: Совсем нет / Not at all | MF38: Немного / A little | MI38: Совсем нет / Not at all | MN38: Немного / A little | MR38: Немного / A little | MW38: Довольно сильно / Quite a bit | MY38: Совсем нет / Not at all | ND38: Немного / A little | NI38: Довольно сильно / Quite a bit | NM38: Довольно сильно / Quite a bit | NQ38: Довольно сильно / Quite a bit | NT38: Немного / A little | NW38: Совсем нет / Not at all | OA38: Совсем нет / Not at all | OF38: Немного / A little | OK38: Довольно сильно / Quite a bit
A39: LU001 | B39: Да / Yes | D39: Да / Yes | F39: Да / Yes | H39: Женский / Female | L39: 18-24 | R39: Русский(ая) / Russian | T39: русский, английский | U39: Москва | V39: Тбилиси | AB39: Никогда не был женат (замужем) / Single, never married | AE39: Нет / No | AH39: Нет / No | AO39: Магистратура / Master’s Degree | AS39: Средний / Average | AU39: Я не могу высказывать свое мнение о ситуации в стране, ко мне приходила полиция, я не вижу перспективы жить в России | AW39: Скорее согласен / Moderately agree | BA39: Скорее согласен / Moderately agree | BE39: Скорее согласен / Moderately agree | BI39: Скорее согласен / Moderately agree | BL39: Полностью согласен / Strongly agree | BR39: Скорее не согласен / Moderately disagree | BU39: Скорее согласен / Moderately agree | BX39: Полностью согласен / Strongly agree | CB39: Полностью согласен / Strongly agree | CF39: Полностью согласен / Strongly agree | CL39: Скорее не согласен / Moderately disagree | CO39: Скорее согласен / Moderately agree | CR39: Полностью согласен / Strongly agree | CW39: Скорее согласен / Moderately agree | CZ39: Полностью согласен / Strongly agree | DE39: Скорее согласен / Moderately agree | DH39: Полностью согласен / Strongly agree | DM39: Скорее согласен / Moderately agree | DR39: Скорее не согласен / Moderately disagree | DV39: Скорее не согласен / Moderately disagree | EA39: Полностью не согласен / Strongly disagree | EC39: Скорее согласен / Moderately agree | EI39: Полностью не согласен / Strongly disagree | EJ39: Полностью согласен / Strongly agree | EP39: Скорее не согласен / Moderately disagree | ES39: Скорее согласен / Moderately agree | EZ39: Полностью согласен / Strongly agree | FD39: Полностью согласен / Strongly agree | FH39: Полностью согласен / Strongly agree | FM39: Скорее согласен / Moderately agree | FP39: Да / Yes | FS39: Нет / No | FU39: Нет / No | FW39: Нет / No | FY39: Нет / No | GA39: Нет / No | GC39: Нет / No | GE39: Нет / No | GG39: Нет / No | GI39: Нет / No | GJ39: Да / Yes | GM39: Нет / No | GO39: Нет / No | GQ39: Нет / No | GS39: Нет / No | GU39: Нет / No | GW39: Нет / No | GX39: любой митинг | GY39: Совсем нет/Not at all | HC39: Совсем нет/Not at all | HI39: Довольно сильно/Quite a bit | HM39: Довольно сильно/Quite a bit | HR39: Очень сильно/Extremely | HV39: Очень сильно/Extremely | HZ39: Очень сильно/Extremely | ID39: Очень сильно/Extremely | IH39: Очень сильно/Extremely | IL39: Очень сильно/Extremely | IP39: Очень сильно/Extremely | IR39: Немного/A little | IX39: Очень сильно/Extremely | JB39: Очень сильно/Extremely | JF39: Очень сильно/Extremely | JG39: Совсем нет/Not at all | JN39: Очень сильно/Extremely | JQ39: Довольно сильно/Quite a bit | JT39: Немного/A little | JZ39: Очень сильно/Extremely | KD39: Очень сильно/Extremely | KE39: Совсем нет/Not at all | KI39: Совсем нет/Not at all | KM39: Совсем нет/Not at all | KS39: Довольно сильно/Quite a bit | KU39: Совсем нет / Not at all | KZ39: Немного / A little | LC39: Совсем нет / Not at all | LJ39: Очень сильно / Extremely | LM39: Довольно сильно / Quite a bit | LP39: Немного / A little | LV39: Очень сильно / Extremely | LY39: Довольно сильно / Quite a bit | MB39: Немного / A little | MH39: Очень сильно / Extremely | MK39: Довольно сильно / Quite a bit | MN39: Немного / A little | MR39: Немного / A little | MX39: Очень сильно / Extremely | MZ39: Немного / A little | NE39: Довольно сильно / Quite a bit | NJ39: Очень сильно / Extremely | NM39: Довольно сильно / Quite a bit | NR39: Очень сильно / Extremely | NU39: Довольно сильно / Quite a bit | NY39: Довольно сильно / Quite a bit | OC39: Довольно сильно / Quite a bit | OG39: Довольно сильно / Quite a bit | OJ39: Немного / A little
A40: TC001 | B40: Да / Yes | D40: Да / Yes | F40: Да / Yes | I40: Мужской / Male | M40: 25-34 | R40: Русский(ая) / Russian | T40: русский | U40: Москва | V40: Тбилиси | AB40: Никогда не был женат (замужем) / Single, never married | AE40: Нет / No | AF40: - | AH40: Нет / No | AI40: - | AN40: Высшее образование (специалист) / 5 years of college | AR40: Ниже среднего / Below average | AU40: чтобы не быть мобилизованным и не идти воевать | AY40: Полностью не согласен / Strongly disagree | BA40: Скорее согласен / Moderately agree | BE40: Скорее согласен / Moderately agree | BJ40: Скорее не согласен / Moderately disagree | BM40: Скорее согласен / Moderately agree | BP40: Полностью согласен / Strongly agree | BV40: Скорее не согласен / Moderately disagree | BZ40: Скорее не согласен / Moderately disagree | CC40: Скорее согласен / Moderately agree | CH40: Скорее не согласен / Moderately disagree | CL40: Скорее не согласен / Moderately disagree | CO40: Скорее согласен / Moderately agree | CS40: Скорее согласен / Moderately agree | CW40: Скорее согласен / Moderately agree | DB40: Скорее не согласен / Moderately disagree | DE40: Скорее согласен / Moderately agree | DI40: Скорее согласен / Moderately agree | DM40: Скорее согласен / Moderately agree | DP40: Полностью согласен / Strongly agree | DU40: Скорее согласен / Moderately agree | DZ40: Скорее не согласен / Moderately disagree | EB40: Полностью согласен / Strongly agree | EG40: Скорее согласен / Moderately agree | EK40: Скорее согласен / Moderately agree | EP40: Скорее не согласен / Moderately disagree | ES40: Скорее согласен / Moderately agree | EV40: Полностью согласен / Strongly agree | FB40: Скорее не согласен / Moderately disagree | FE40: Скорее согласен / Moderately agree | FI40: Скорее согласен / Moderately agree | FN40: Скорее не согласен / Moderately disagree | FP40: Да / Yes | FS40: Нет / No | FU40: Нет / No | FW40: Нет / No | FY40: Нет / No | GA40: Нет / No | GC40: Нет / No | GE40: Нет / No | GG40: Нет / No | GH40: Да / Yes | GJ40: Да / Yes | GM40: Нет / No | GO40: Нет / No | GQ40: Нет / No | GS40: Нет / No | GU40: Нет / No | GW40: Нет / No | GX40: при пересечении границы был страх, что не выпустят из страны и направят на войну | GZ40: Немного/A little | HC40: Совсем нет/Not at all | HG40: Совсем нет/Not at all | HK40: Совсем нет/Not at all | HO40: Совсем нет/Not at all | HT40: Немного/A little | HW40: Совсем нет/Not at all | IB40: Немного/A little | IE40: Совсем нет/Not at all | II40: Совсем нет/Not at all | IN40: Немного/A little | IQ40: Совсем нет/Not at all | IW40: Довольно сильно/Quite a bit | IZ40: Немного/A little | JD40: Немного/A little | JG40: Совсем нет/Not at all | JL40: Немного/A little | JO40: Совсем нет/Not at all | JS40: Совсем нет/Not at all | JW40: Совсем нет/Not at all | KD40: Очень сильно/Extremely | KH40: Очень сильно/Extremely | KJ40: Немного/A little | KM40: Совсем нет/Not at all | KQ40: Совсем нет/Not at all | KU40: Совсем нет / Not at all | KY40: Совсем нет / Not at all | LC40: Совсем нет / Not at all | LG40: Совсем нет / Not at all | LK40: Совсем нет / Not at all | LO40: Совсем нет / Not at all | LS40: Совсем нет / Not at all | LW40: Совсем нет / Not at all | MA40: Совсем нет / Not at all | MF40: Немного / A little | MJ40: Немного / A little | MM40: Совсем нет / Not at all | MQ40: Совсем нет / Not at all | MV40: Немного / A little | MY40: Совсем нет / Not at all | ND40: Немного / A little | NH40: Немного / A little | NK40: Совсем нет / Not at all | NO40: Совсем нет / Not at all | NT40: Немного / A little | NW40: Совсем нет / Not at all | OA40: Совсем нет / Not at all | OF40: Немного / A little | OJ40: Немного / A little
A41: CD002 | B41: Да / Yes | D41: Да / Yes | F41: Да / Yes | H41: Женский / Female | M41: 25-34 | R41: Русский(ая) / Russian | T41: Русский, английский | U41: Москва | V41: Тбилиси, Грузия | AB41: Никогда не был женат (замужем) / Single, never married | AE41: Нет / No | AF41: 0 | AH41: Нет / No | AI41: 0 | AN41: Высшее образование (специалист) / 5 years of college | AS41: Средний / Average | AU41: 1. Безопасность. Я протестовала против войны и помогала правозащитным организациям. Я продолжаю делать это в Грузии. 2. Экзистенциальные. Я была активистом в охране природы, война обесценила для меня эту активность. Вдобавок новые репрессивные законы в России мешают любым горизонтальным инициативам. 3. Личные. Морально тяжело было находиться в России, хотелось вдохнуть свежего воздуха. Я всегда знала, что не хочу жить за железным занавесом в условиях авторитарной диктатуры. 4. Это вызов. Мне было интересно узнать, чего я стою, если вырвать меня из привычной среды. | AW41: Скорее согласен / Moderately agree | AZ41: Полностью согласен / Strongly agree | BD41: Полностью согласен / Strongly agree | BH41: Полностью согласен / Strongly agree | BM41: Скорее согласен / Moderately agree | BS41: Полностью не согласен / Strongly disagree | BT41: Полностью согласен / Strongly agree | BY41: Скорее согласен / Moderately agree | CB41: Полностью согласен / Strongly agree | CH41: Скорее не согласен / Moderately disagree | CJ41: Полностью согласен / Strongly agree | CO41: Скорее согласен / Moderately agree | CU41: Полностью не согласен / Strongly disagree | CV41: Полностью согласен / Strongly agree | CZ41: Полностью согласен / Strongly agree | DD41: Полностью согласен / Strongly agree | DH41: Полностью согласен / Strongly agree | DL41: Полностью согласен / Strongly agree | DP41: Полностью согласен / Strongly agree | DU41: Скорее согласен / Moderately agree | EA41: Полностью не согласен / Strongly disagree | ED41: Скорее не согласен / Moderately disagree | EI41: Полностью не согласен / Strongly disagree | EM41: Полностью не согласен / Strongly disagree | EQ41: Полностью не согласен / Strongly disagree | EU41: Полностью не согласен / Strongly disagree | EW41: Скорее согласен / Moderately agree | FC41: Полностью не согласен / Strongly disagree | FE41: Скорее согласен / Moderately agree | FH41: Полностью согласен / Strongly agree | FN41: Скорее не согласен / Moderately disagree | FQ41: Нет / No | FS41: Нет / No | FU41: Нет / No | FW41: Нет / No | FY41: Нет / No | GA41: Нет / No | GB41: Да / Yes | GE41: Нет / No | GG41: Нет / No | GI41: Нет / No | GJ41: Да / Yes | GL41: Да / Yes | GO41: Нет / No | GQ41: Нет / No | GS41: Нет / No | GU41: Нет / No | GW41: Нет / No | GX41: Война и репрессии (в отношении других) сами по себе стали травмой. | GZ41: Немного/A little | HC41: Совсем нет/Not at all | HH41: Немного/A little | HN41: Очень сильно/Extremely | HR41: Очень сильно/Extremely | HV41: Очень сильно/Extremely | HZ41: Очень сильно/Extremely | ID41: Очень сильно/Extremely | IH41: Очень сильно/Extremely | IL41: Очень сильно/Extremely | IM41: Совсем нет/Not at all | IQ41: Совсем нет/Not at all | IX41: Очень сильно/Extremely | JB41: Очень сильно/Extremely | JE41: Довольно сильно/Quite a bit | JG41: Совсем нет/Not at all | JN41: Очень сильно/Extremely | JO41: Совсем нет/Not at all | JT41: Немного/A little | JX41: Немного/A little | KD41: Очень сильно/Extremely | KH41: Очень сильно/Extremely | KK41: Довольно сильно/Quite a bit | KM41: Совсем нет/Not at all | KQ41: Совсем нет/Not at all | KV41: Немного / A little | KZ41: Немного / A little | LC41: Совсем нет / Not at all | LH41: Немного / A little | LK41: Совсем нет / Not at all | LO41: Совсем нет / Not at all | LT41: Немного / A little | LY41: Довольно сильно / Quite a bit | MC41: Довольно сильно / Quite a bit | MH41: Очень сильно / Extremely | MK41: Довольно сильно / Quite a bit | MP41: Очень сильно / Extremely | MS41: Довольно сильно / Quite a bit | MX41: Очень сильно / Extremely | NA41: Довольно сильно / Quite a bit | NF41: Очень сильно / Extremely | NJ41: Очень сильно / Extremely | NN41: Очень сильно / Extremely | NR41: Очень сильно / Extremely | NV41: Очень сильно / Extremely | NX41: Немного / A little | OD41: Очень сильно / Extremely | OH41: Очень сильно / Extremely | OK41: Довольно сильно / Quite a bit
A42: СМ001 | B42: Да / Yes | D42: Да / Yes | F42: Да / Yes | H42: Женский / Female | L42: 18-24 | R42: Русский(ая) / Russian | T42: Английский, немецкий, русский, белорусский | U42: Москва | V42: Тбилиси, Грузия | W42: Женат (замужем) / Married | AE42: Нет / No | AH42: Нет / No | AL42: Незаконченное высшее / Some college | AS42: Средний / Average | AU42: Из-за сложившейся политической и экономической ситуации | AW42: Скорее согласен / Moderately agree | AZ42: Полностью согласен / Strongly agree | BF42: Скорее не согласен / Moderately disagree | BJ42: Скорее не согласен / Moderately disagree | BN42: Скорее не согласен / Moderately disagree | BP42: Полностью согласен / Strongly agree | BU42: Скорее согласен / Moderately agree | BZ42: Скорее не согласен / Moderately disagree | CD42: Скорее не согласен / Moderately disagree | CG42: Скорее согласен / Moderately agree | CJ42: Полностью согласен / Strongly agree | CO42: Скорее согласен / Moderately agree | CS42: Скорее согласен / Moderately agree | CV42: Полностью согласен / Strongly agree | CZ42: Полностью согласен / Strongly agree | DD42: Полностью согласен / Strongly agree | DI42: Скорее согласен / Moderately agree | DM42: Скорее согласен / Moderately agree | DQ42: Скорее согласен / Moderately agree | DV42: Скорее не согласен / Moderately disagree | DZ42: Скорее не согласен / Moderately disagree | EI42: Полностью не согласен / Strongly disagree | EL42: Скорее не согласен / Moderately disagree | EQ42: Полностью не согласен / Strongly disagree | ET42: Скорее не согласен / Moderately disagree | EX42: Скорее не согласен / Moderately disagree | FB42: Скорее не согласен / Moderately disagree | FG42: Полностью не согласен / Strongly disagree | FH42: Полностью согласен / Strongly agree | FL42: Полностью согласен / Strongly agree | FQ42: Нет / No | FS42: Нет / No | FU42: Нет / No | FW42: Нет / No | FY42: Нет / No | GA42: Нет / No | GC42: Нет / No | GE42: Нет / No | GG42: Нет / No | GI42: Нет / No | GJ42: Да / Yes | GM42: Нет / No | GO42: Нет / No | GQ42: Нет / No | GS42: Нет / No | GU42: Нет / No | GW42: Нет / No | GX42: Когда началась война; когда началась мобилизация; когда упали ракеты в Польшу и Молдавию | HA42: Довольно сильно/Quite a bit | HD42: Немного/A little | HI42: Довольно сильно/Quite a bit | HL42: Немного/A little | HO42: Совсем нет/Not at all | HV42: Очень сильно/Extremely | HX42: Немного/A little | IC42: Довольно сильно/Quite a bit | IH42: Очень сильно/Extremely | IL42: Очень сильно/Extremely | IO42: Довольно сильно/Quite a bit | IS42: Довольно сильно/Quite a bit | IV42: Немного/A little | IY42: Совсем нет/Not at all | JC42: Совсем нет/Not at all | JG42: Совсем нет/Not at all | JL42: Немного/A little | JQ42: Довольно сильно/Quite a bit | JU42: Довольно сильно/Quite a bit | JX42: Немного/A little | KC42: Довольно сильно/Quite a bit | KG42: Довольно сильно/Quite a bit | KK42: Довольно сильно/Quite a bit | KN42: Немного/A little | KR42: Немного/A little | KW42: Довольно сильно / Quite a bit | LA42: Довольно сильно / Quite a bit | LE42: Довольно сильно / Quite a bit | LI42: Довольно сильно / Quite a bit | LM42: Довольно сильно / Quite a bit | LP42: Немного / A little | LT42: Немного / A little | LX42: Немного / A little | MC42: Довольно сильно / Quite a bit | MF42: Немного / A little
A43: LO001 | C43: Нет / No | D43: Да / Yes | F43: Да / Yes | I43: Мужской / Male | M43: 25-34 | R43: Русский(ая) / Russian | T43: Русский, English | U43: Москва | V43: Тбилиси | AA43: Гражданский брак / Cohabiting with a significant other or in a domestic partnership | AE43: Нет / No | AH43: Нет / No | AO43: Магистратура / Master’s Degree | AT43: Выше среднего / Above average | AU43: не согласие с проводимой политикой
A44: DA001 | B44: Да / Yes | D44: Да / Yes | F44: Да / Yes | I44: Мужской / Male | N44: 35-44 | S44: Formally Russian, but consider myself closer to Jewish traditions and values | T44: English, French, some Hebrew , study German, Spanish , Ukrainian | U44: Moscow , Moscow region ( Korolev ) | V44: Arinj, suburb of Yerevan Yetevan Armenia | AA44: Гражданский брак / Cohabiting with a significant other or in a domestic partnership | AE44: Нет / No | AF44: 0 | AG44: Да / Yes | AI44: 1 2 cats :) | AO44: Магистратура / Master’s Degree | AS44: Средний / Average | AU44: Fear of closing country borders Need to unlock distant job services ( upwork) outside Russia Expected mass mobilization , didn't want to go to war I politically support Ukraine but have "family motherland"( property) in Russia Inability ( huge risks ) to protest openly in Russia and to openly choose and help opposite side of the conflict Cannot work productively on any job while there's no stability in the country and a lot of stress | AX44: Скорее не согласен / Moderately disagree | BB44: Скорее не согласен / Moderately disagree | BF44: Скорее не согласен / Moderately disagree | BJ44: Скорее не согласен / Moderately disagree | BM44: Скорее согласен / Moderately agree | BR44: Скорее не согласен / Moderately disagree | BV44: Скорее не согласен / Moderately disagree | BY44: Скорее согласен / Moderately agree | CD44: Скорее не согласен / Moderately disagree | CH44: Скорее не согласен / Moderately disagree | CK44: Скорее согласен / Moderately agree | CP44: Скорее не согласен / Moderately disagree | CT44: Скорее не согласен / Moderately disagree | CW44: Скорее согласен / Moderately agree | DB44: Скорее не согласен / Moderately disagree | DF44: Скорее не согласен / Moderately disagree | DI44: Скорее согласен / Moderately agree | DM44: Скорее согласен / Moderately agree | DR44: Скорее не согласен / Moderately disagree | DV44: Скорее не согласен / Moderately disagree | EA44: Полностью не согласен / Strongly disagree | ED44: Скорее не согласен / Moderately disagree | EH44: Скорее не согласен / Moderately disagree | EL44: Скорее не согласен / Moderately disagree | EP44: Скорее не согласен / Moderately disagree | ET44: Скорее не согласен / Moderately disagree | EW44: Скорее согласен / Moderately agree | FB44: Скорее не согласен / Moderately disagree | FF44: Скорее не согласен / Moderately disagree | FI44: Скорее согласен / Moderately agree | FM44: Скорее согласен / Moderately agree | FP44: Да / Yes | FS44: Нет / No | FU44: Нет / No | FV44: Да / Yes | FY44: Нет / No | GA44: Нет / No | GC44: Нет / No | GD44: Да / Yes | GF44: Да / Yes | GI44: Нет / No | GK44: Нет / No | GL44: Да / Yes | GO44: Нет / No | GQ44: Нет / No | GS44: Нет / No | GU44: Нет / No | GW44: Нет / No | GX44: While leaving Russia on may 9th, 2022,was detained by Russian police in Vladikavkaz just for walking alone in the city . There were psychological threats , was fully undressed and searched for unallowed stuff . They suspected me in drug dealing In yerevan several days after arrival ( I was making photos on volunteering projects and undeliberately caught military cars on my camera ). I had around $ 10k in cash taken from Russia and put it openly on the table .when all issues were resolved , one of the policemen has taken the money to count ( he shouldn't have done it ) and then like 'remembered' his mistake, returned the money, I recounted and found $1000 missing. Since then I searched the pockets of the policeman, have found nothing, had to accept the loss. There were no cameras or independent witnesses ,so I cannot prove that was him who stole it
A45: PF001 | B45: Да / Yes | D45: Да / Yes | F45: Да / Yes | J45: Небинарный / Non-binary | M45: 25-34 | R45: Русский(ая) / Russian | T45: Русский, English | U45: Москва | V45: Тбилиси, Грузия | AA45: Гражданский брак / Cohabiting with a significant other or in a domestic partnership | AE45: Нет / No | AF45: 0 | AH45: Нет / No | AI45: 0 | AM45: Высшее образование (бакалавриат) / Bachelor’s Degree | AR45: Ниже среднего / Below average | AU45: Я против войны и полити Российских властей | AW45: Скорее согласен / Moderately agree | BA45: Скорее согласен / Moderately agree | BD45: Полностью согласен / Strongly agree | BI45: Скорее согласен / Moderately agree | BN45: Скорее не согласен / Moderately disagree | BS45: Полностью не согласен / Strongly disagree | BV45: Скорее не согласен / Moderately disagree | BX45: Полностью согласен / Strongly agree | CE45: Полностью не согласен / Strongly disagree | CG45: Скорее согласен / Moderately agree | CK45: Скорее согласен / Moderately agree | CN45: Полностью согласен / Strongly agree | CS45: Скорее согласен / Moderately agree | CX45: Скорее не согласен / Moderately disagree | DA45: Скорее согласен / Moderately agree | DF45: Скорее не согласен / Moderately disagree | DI45: Скорее согласен / Moderately agree | DL45: Полностью согласен / Strongly agree | DQ45: Скорее согласен / Moderately agree | DV45: Скорее не согласен / Moderately disagree | EA45: Полностью не согласен / Strongly disagree | EE45: Полностью не согласен / Strongly disagree | EI45: Полностью не согласен / Strongly disagree | EM45: Полностью не согласен / Strongly disagree | EO45: Скорее согласен / Moderately agree | EU45: Полностью не согласен / Strongly disagree | EW45: Скорее согласен / Moderately agree | FC45: Полностью не согласен / Strongly disagree | FE45: Скорее согласен / Moderately agree | FJ45: Скорее не согласен / Moderately disagree | FM45: Скорее согласен / Moderately agree | FQ45: Нет / No | FS45: Нет / No | FU45: Нет / No | FW45: Нет / No | FY45: Нет / No | GA45: Нет / No | GC45: Нет / No | GE45: Нет / No | GG45: Нет / No | GI45: Нет / No | GJ45: Да / Yes | GM45: Нет / No | GO45: Нет / No | GQ45: Нет / No | GS45: Нет / No | GU45: Нет / No | GW45: Нет / No | GX45: Думаю, моя жизнь достаточно спокойна, особенно по сравнению с тем, что приходится пережить жителям Украины | GY45: Совсем нет/Not at all | HC45: Совсем нет/Not at all | HG45: Совсем нет/Not at all | HM45: Довольно сильно/Quite a bit | HP45: Немного/A little | HS45: Совсем нет/Not at all | HZ45: Очень сильно/Extremely | IB45: Немного/A little | IE45: Совсем нет/Not at all | IJ45: Немного/A little | IO45: Довольно сильно/Quite a bit | IQ45: Совсем нет/Not at all | IW45: Довольно сильно/Quite a bit | IZ45: Немного/A little | JE45: Довольно сильно/Quite a bit | JG45: Совсем нет/Not at all | JL45: Немного/A little | JP45: Немного/A little | JT45: Немного/A little | JW45: Совсем нет/Not at all | KC45: Довольно сильно/Quite a bit | KE45: Совсем нет/Not at all | KI45: Совсем нет/Not at all | KM45: Совсем нет/Not at all | KQ45: Совсем нет/Not at all | KU45: Совсем нет / Not at all | KY45: Совсем нет / Not at all | LC45: Совсем нет / Not at all | LG45: Совсем нет / Not at all | LK45: Совсем нет / Not at all | LO45: Совсем нет / Not at all | LS45: Совсем нет / Not at all | LW45: Совсем нет / Not at all | MA45: Совсем нет / Not at all | ME45: Совсем нет / Not at all | ML45: Очень сильно / Extremely | MO45: Довольно сильно / Quite a bit | MQ45: Совсем нет / Not at all | MU45: Совсем нет / Not at all | MY45: Совсем нет / Not at all | ND45: Немного / A little | NI45: Довольно сильно / Quite a bit | NM45: Довольно сильно / Quite a bit | NQ45: Довольно сильно / Quite a bit | NS45: Совсем нет / Not at all | NX45: Немного / A little | OC45: Довольно сильно / Quite a bit | OH45: Очень сильно / Extremely | OK45: Довольно сильно / Quite a bit
A46: MC001 | B46: Да / Yes | D46: Да / Yes | F46: Да / Yes | H46: Женский / Female | N46: 35-44 | R46: Русский(ая) / Russian | T46: русский, английский, учу немецкий | U46: Санкт-Петербург | V46: Тбилиси | AB46: Никогда не был женат (замужем) / Single, never married | AE46: Нет / No | AF46: нет | AH46: Нет / No | AI46: нет | AM46: Высшее образование (бакалавриат) / Bachelor’s Degree | AR46: Ниже среднего / Below average | AU46: Отсутствие перспектив во всех сферах моей деятельности, отсутствие поддержки людей, невозможность обсудить текущую ситуацию, страх с кем и о чем разговаривать, страх остаться в разваленной стране без возможности расти и нормально жить, плохая еда, экология, невозможность помочь пострадавшим в Украине, невозможность помочь стране, понижение уровня жизни, невозможность построить здоровую нормальную семью, страх, что мои дети будут расти с детьми убийц, страх, что все, чем я занималась станет ненужным, невозможность продолжать нормально жить | AX46: Скорее не согласен / Moderately disagree | BA46: Скорее согласен / Moderately agree | BF46: Скорее не согласен / Moderately disagree | BK46: Полностью не согласен / Strongly disagree | BM46: Скорее согласен / Moderately agree | BR46: Скорее не согласен / Moderately disagree | BU46: Скорее согласен / Moderately agree | BY46: Скорее согласен / Moderately agree | CD46: Скорее не согласен / Moderately disagree | CG46: Скорее согласен / Moderately agree | CL46: Скорее не согласен / Moderately disagree | CQ46: Полностью не согласен / Strongly disagree | CR46: Полностью согласен / Strongly agree | CX46: Скорее не согласен / Moderately disagree | DB46: Скорее не согласен / Moderately disagree | DD46: Полностью согласен / Strongly agree | DI46: Скорее согласен / Moderately agree | DL46: Полностью согласен / Strongly agree | DP46: Полностью согласен / Strongly agree | DU46: Скорее согласен / Moderately agree | EA46: Полностью не согласен / Strongly disagree | EE46: Полностью не согласен / Strongly disagree | EI46: Полностью не согласен / Strongly disagree | EJ46: Полностью согласен / Strongly agree | EQ46: Полностью не согласен / Strongly disagree | ET46: Скорее не согласен / Moderately disagree | EV46: Полностью согласен / Strongly agree | FA46: Скорее согласен / Moderately agree | FF46: Скорее не согласен / Moderately disagree | FH46: Полностью согласен / Strongly agree | FM46: Скорее согласен / Moderately agree | FP46: Да / Yes | FS46: Нет / No | FU46: Нет / No | FW46: Нет / No | FY46: Нет / No | GA46: Нет / No | GC46: Нет / No | GE46: Нет / No | GG46: Нет / No | GI46: Нет / No | GK46: Нет / No | GL46: Да / Yes | GO46: Нет / No | GQ46: Нет / No | GS46: Нет / No | GU46: Нет / No | GW46: Нет / No | GX46: 1.захват крыма 2.война 3.закрытие границ | GZ46: Немного/A little | HE46: Довольно сильно/Quite a bit | HI46: Довольно сильно/Quite a bit | HN46: Очень сильно/Extremely | HR46: Очень сильно/Extremely | HU46: Довольно сильно/Quite a bit | HZ46: Очень сильно/Extremely | ID46: Очень сильно/Extremely | IG46: Довольно сильно/Quite a bit | IK46: Довольно сильно/Quite a bit | IO46: Довольно сильно/Quite a bit | IR46: Немного/A little | IW46: Довольно сильно/Quite a bit | JB46: Очень сильно/Extremely | JE46: Довольно сильно/Quite a bit | JI46: Довольно сильно/Quite a bit | JM46: Довольно сильно/Quite a bit | JP46: Немного/A little | JT46: Немного/A little | JX46: Немного/A little | KD46: Очень сильно/Extremely | KE46: Совсем нет/Not at all | KK46: Довольно сильно/Quite a bit | KP46: Очень сильно/Extremely | KS46: Довольно сильно/Quite a bit | KV46: Немного / A little | LA46: Довольно сильно / Quite a bit | LD46: Немного / A little | LI46: Довольно сильно / Quite a bit | LL46: Немного / A little | LO46: Совсем нет / Not at all | LT46: Немного / A little | LY46: Довольно сильно / Quite a bit | MB46: Немного / A little | MG46: Довольно сильно / Quite a bit | ML46: Очень сильно / Extremely | MM46: Совсем нет / Not at all | MT46: Очень сильно / Extremely | MX46: Очень сильно / Extremely | NB46: Очень сильно / Extremely | NF46: Очень сильно / Extremely | NJ46: Очень сильно / Extremely | NN46: Очень сильно / Extremely | NQ46: Довольно сильно / Quite a bit | NV46: Очень сильно / Extremely | NX46: Немного / A little | OC46: Довольно сильно / Quite a bit | OF46: Немного / A little | OL46: Очень сильно / Extremely
